Workbook

Sheet Dados Programa
B1: Programação Perfiladeira U 4,75 MM - 2026 | J1: 900
I2: =SUM(I4:I42) -> 902 | J2: =SUM(J4:J53) -> 397.071 | O2: =SUM(O4:O61) -> 164.5371
A3: OP | B3: Cód. | C3: Descrição do Produto | D3: Esp. | E3: Kg/m | F3: Ton/H | G3: Veloc. Programado | H3: Tempo Programado | I3: Programado | J3: Realizado | K3: Inicio | L3: Termino | M3: Data prevista Comercial | N3: Matéria Prima | O3: Pedido de Venda | P3: Observação
B4: PRF10255 | C4: PERFIL U ENRIJ LQ 3,00 X 200 X 75 X 20 MM | D4: 3 | I4: 10 | J4: 12.07 | K4: 46174 | L4: 46174 | M4: =L4+4 -> 46178 | N4: mp-ok | O4: =-1*(IF(VLOOKUP(B4,Estoque!B:J,8,FALSE)>0,0,VLOOKUP(B4,Estoque!B:J,8))) -> 0 | P4: 0022.36086
B5: PRF10246 | C5: PERFIL U ENRIJ LQ 3,35 X 200 X 75 X 20 MM | D5: 3.35 | I5: 10 | J5: 8.483 | K5: 46175 | L5: 46175 | M5: =L5+4 -> 46179 | N5: mp-ok | O5: 5.236 | P5: 0022.36242
B6: PRF10120 | C6: PERFIL U ENRIJ LQ 2,25 X 200 X 75 X 20 MM | D6: 2.25 | I6: 20 | J6: 6.004 | K6: - | L6: - | M6: =L6+4 -> #VALUE! | N6: 6t-ok (SEM MP) | O6: =-1*(IF(VLOOKUP(B6,Estoque!B:J,8,FALSE)>0,0,VLOOKUP(B6,Estoque!B:J,8))) -> 0 | P6: 0022.36100
B7: PRF10060 | C7: PERFIL U ENRIJ LQ 2,00 X 200 X 75 X 20 MM | D7: 2 | I7: 35 | J7: 34.365 | K7: 46176 | L7: 46176 | M7: =L7+2 -> 46178 | N7: 31t-ok | O7: =-1*(IF(VLOOKUP(B7,Estoque!B:J,8,FALSE)>0,0,VLOOKUP(B7,Estoque!B:J,8))) -> 0 | P7: 0022.36101
B8: PRF10180 | C8: PERFIL U ENRIJ LQ 2,65 X 200 X 75 X 20 MM | D8: 2.65 | I8: 25 | J8: 22.46 | K8: 46178 | L8: 46178 | M8: =L8+3 -> 46181 | N8: mp-ok | O8: =-1*(IF(VLOOKUP(B8,Estoque!B:J,8,FALSE)>0,0,VLOOKUP(B8,Estoque!B:J,8))) -> 0.67 | P8: 0022.36103
B9: PRF10370 | C9: PERFIL U SIMPLES LQ 2,00 X 200 X 50 MM | D9: 2 | I9: 10 | J9: 11.56 | K9: 46181 | L9: 46181 | M9: =L9+2 -> 46183 | N9: mp-ok | O9: =-1*(IF(VLOOKUP(B9,Estoque!B:J,8,FALSE)>0,0,VLOOKUP(B9,Estoque!B:J,8))) -> 0 | P9: 0022.36104
B10: PRF10550 | C10: PERFIL U SIMPLES LQ 2,65 X 200 X 50 MM | D10: 2.65 | I10: 15 | J10: 24.13 | K10: 46181 | L10: 46181 | M10: =L10+2 -> 46183 | N10: mp-ok | O10: =-1*(IF(VLOOKUP(B10,Estoque!B:J,8,FALSE)>0,0,VLOOKUP(B10,Estoque!B:J,8))) -> 0 | P10: 0022.36105
B11: PRF10642 | C11: PERFIL U SIMPLES LQ 3,00 X 200 X 50 MM | D11: 3 | I11: 30 | J11: 38.03 | K11: 46181 | L11: 46181 | M11: =L11+3 -> 46184 | N11: mp-ok | O11: =-1*(IF(VLOOKUP(B11,Estoque!B:J,8,FALSE)>0,0,VLOOKUP(B11,Estoque!B:J,8))) -> 0 | P11: 0022.36106
B12: PRF100081 | C12: PERFIL U ENRIJ LQ 1,80 X 150 X 60 X 20 MM - COMPR. ESPECIAL | D12: 1.8 | I12: 16 | J12: 14.4596 | K12: 46182 | L12: 46182 | M12: =L12+2 -> 46184 | N12: mp-ok | O12: 14.4596 | P12: 0022.36230 | Q12: COMPRIMENTO ESPECIAL
B13: PRF10008 | C13: PERFIL U ENRIJ LQ 1,80 X 150 X 60 X 20 MM | D13: 1.8 | J13: 3.4954 | K13: - | L13: - | M13: - | N13: passou porque tinha no chão | O13: 0 | P13: 0022.36230
B14: PRZ101401 | C14: PERFIL U ENRIJ ZC 1,95 X 150 X 60 X 20 MM - COMPR. ESPECIAL | D14: 1.95 | I14: 2 | J14: 1.23 | K14: 46182 | L14: 46182 | M14: =L14+2 -> 46184 | N14: mp-ok | O14: 1.282 | P14: 0022.36231 | Q14: COMPRIMENTO ESPECIAL
B15: PRZ10140 | C15: PERFIL U ENRIJ ZC 1,95 X 150 X 60 X 20 MM | D15: 1.95 | I15: 10 | J15: 24.535 | K15: 46183 | L15: 46183 | M15: =L15+2 -> 46185 | N15: mp-ok | O15: =-1*(IF(VLOOKUP(B15,Estoque!B:J,8,FALSE)>0,0,VLOOKUP(B15,Estoque!B:J,8))) -> 0 | P15: 0022.36231
B16: PRF10050 | C16: PERFIL U ENRIJ LQ 2,00 X 150 X 60 X 20 MM | D16: 2 | I16: 50 | J16: 48.25 | K16: 46183 | L16: 46183 | M16: =L16+2 -> 46185 | N16: mp-ok | O16: =-1*(IF(VLOOKUP(B16,Estoque!B:J,8,FALSE)>0,0,VLOOKUP(B16,Estoque!B:J,8))) -> 0 | P16: 0022.36233
B17: PRF10170 | C17: PERFIL U ENRIJ LQ 2,65 X 150 X 60 X 20 MM | D17: 2.65 | I17: 30 | J17: 49.08 | K17: 46183 | L17: 46183 | M17: =L17+2 -> 46185 | N17: mp-ok | O17: =-1*(IF(VLOOKUP(B17,Estoque!B:J,8,FALSE)>0,0,VLOOKUP(B17,Estoque!B:J,8))) -> 0 | P17: 0022.36234
B18: PRF102301 | C18: PERFIL U ENRIJ LQ 3,00 X 150 X 60 X 20 MM - COMPR. ESPECIAL | D18: 3 | I18: 10 | J18: 8.542 | K18: 46184 | L18: 46184 | M18: =L18+4 -> 46188 | N18: MP-ok | O18: 8.58 | P18: 0022.36235 | Q18: COMPRIMENTO ESPECIAL
B19: PRF10230 | C19: PERFIL U ENRIJ LQ 3,00 X 150 X 60 X 20 MM | D19: 3 | I19: 50 | J19: 58.072 | K19: 46184 | L19: 46184 | M19: =L19+4 -> 46188 | N19: mp-ok | O19: 0 | P19: 0022.36235
B20: PRF10244 | C20: PERFIL U ENRIJ LQ 3,35 X 150 X 60 X 20 MM | D20: 3.35 | I20: 10 | J20: 10.59 | K20: 46185 | L20: 46185 | M20: 46185 | N20: mp-ok | O20: 0 | P20: 0022.36236
B21: PRF10009 | C21: PERFIL U ENRIJ LQ 1,80 X 150 X 50 X 20 MM | D21: 1.8 | I21: 10 | J21: 12.46 | K21: 46188 | L21: 46188 | M21: =L25+2 -> 46191 | N21: mp-ok | O21: =-1*(IF(VLOOKUP(B21,Estoque!B:J,8,FALSE)>0,0,VLOOKUP(B21,Estoque!B:J,8))) -> 5.1482 | P21: 0022.36303
B22: PRF10051 | C22: PERFIL U ENRIJ LQ 2,00 X 150 X 50 X 20 MM | D22: 2 | I22: 25 | J22: 9.255 | K22: 46188 | L22: 46188 | N22: mp-ok | O22: =-1*(IF(VLOOKUP(B22,Estoque!B:J,8,FALSE)>0,0,VLOOKUP(B22,Estoque!B:J,8))) -> 10.7693 | P22: 0022.36302
B23: PRF101111 | C23: PERFIL U ENRIJ LQ 2,25 X 150 X 50 X 20 MM - COMPR. ESPECIAL | D23: 2.25 | I23: 3 | K23: 46188 | L23: 46188 | N23: mp-ok | O23: 1.67 | P23: 0022.36301 | Q23: COMPRIMENTO ESPECIAL
B24: PRF10111 | C24: PERFIL U ENRIJ LQ 2,25 X 150 X 50 X 20 MM | D24: 2.25 | I24: 10 | K24: 46188 | L24: 46188 | N24: 2t-ok | O24: =-1*(IF(VLOOKUP(B24,Estoque!B:J,8,FALSE)>0,0,VLOOKUP(B24,Estoque!B:J,8))) -> 0 | P24: 0022.36301
B25: PRF10171 | C25: PERFIL U ENRIJ LQ 2,65 X 150 X 50 X 20 MM | D25: 2.65 | I25: 25 | K25: 46189 | L25: 46189 | N25: MP-OK | O25: 8.058 | P25: 0022.36300
B26: PRF10229 | C26: PERFIL U ENRIJ LQ 3,00 X 150 X50 X 20 MM | D26: 3 | I26: 30 | K26: 46189 | L26: 46189 | N26: MP | O26: =-1*(IF(VLOOKUP(B26,Estoque!B:J,8,FALSE)>0,0,VLOOKUP(B26,Estoque!B:J,8))) -> 7.7983 | P26: 0022.36337
B27: PRF10288 | C27: PERFIL U SIMPLES LQ 1,80 X 150 X 50 MM | D27: 1.8 | I27: 10 | K27: 46190 | L27: 46190 | M27: =L27+3 -> 46193 | N27: 5t-ok | O27: =-1*(IF(VLOOKUP(B27,Estoque!B:J,8,FALSE)>0,0,VLOOKUP(B27,Estoque!B:J,8))) -> 0 | P27: 0022.36338
B28: PRF10360 | C28: PERFIL U SIMPLES LQ 2,00 X 150 X 50 MM | D28: 2 | I28: 10 | K28: 46190 | L28: 46190 | M28: =L28+3 -> 46193 | N28: mp-ok | O28: =-1*(IF(VLOOKUP(B28,Estoque!B:J,8,FALSE)>0,0,VLOOKUP(B28,Estoque!B:J,8))) -> 0.2384 | P28: 0022.36339
B29: PRF10450 | C29: PERFIL U SIMPLES LQ 2,25 X 150 X 50 MM | D29: 2.25 | I29: 25 | K29: 46190 | L29: 46190 | M29: =L29+2 -> 46192 | O29: =-1*(IF(VLOOKUP(B29,Estoque!B:J,8,FALSE)>0,0,VLOOKUP(B29,Estoque!B:J,8))) -> 0 | P29: 0022.36340
B30: PRF10540 | C30: PERFIL U SIMPLES LQ 2,65 X 150 X 50 MM | D30: 2.65 | I30: 20 | K30: 46191 | L30: 46191 | M30: =L30+3 -> 46194 | O30: =-1*(IF(VLOOKUP(B30,Estoque!B:J,8,FALSE)>0,0,VLOOKUP(B30,Estoque!B:J,8))) -> 0.115 | P30: 0022.36341
B31: PRF10816 | C31: PERFIL U SIMPLES LQ 2,65 X 150 X 50 MM COR400 | D31: 2.65 | I31: 10 | K31: 46191 | L31: 46191 | M31: 46192 | N31: MP | O31: 4.4376 | P31: 0022.36382 | Q31: COR30
B32: PRF10630 | C32: PERFIL U SIMPLES LQ 3,00 X 150 X 50 MM | D32: 3 | I32: 70 | K32: 46191 | L32: 46192 | M32: =L32+2 -> 46194 | N32: 19t-ok | O32: =-1*(IF(VLOOKUP(B32,Estoque!B:J,8,FALSE)>0,0,VLOOKUP(B32,Estoque!B:J,8))) -> 10.4154 | P32: 0022.36342
B33: PRF10690 | C33: PERFIL U SIMPLES LQ 4,75 X 150 X 50 MM | D33: 4.75 | I33: 50 | K33: 46195 | L33: 46195 | N33: MP | O33: =-1*(IF(VLOOKUP(B33,Estoque!B:J,8,FALSE)>0,0,VLOOKUP(B33,Estoque!B:J,8))) -> 11.8424 | P33: 0022.36403
B34: PRF10342 | C34: PERFIL U SIMPLES LQ 2,00 X 100 X 40 MM | D34: 2 | I34: 25 | K34: 46196 | L34: 46196 | M34: =L34+4 -> 46200 | O34: =-1*(IF(VLOOKUP(B34,Estoque!B:J,8,FALSE)>0,0,VLOOKUP(B34,Estoque!B:J,8))) -> 3.514
B35: PRF10343 | C35: PERFIL U SIMPLES LQ 2,00 X 100 X 50 MM | D35: 2 | I35: 10 | K35: 46196 | L35: 46196 | M35: =L35+4 -> 46200 | O35: =-1*(IF(VLOOKUP(B35,Estoque!B:J,8,FALSE)>0,0,VLOOKUP(B35,Estoque!B:J,8))) -> 3.514
B36: PRZ10344 | C36: PERFIL U SIMPLES ZC 1,95 X 100 X 50 MM | D36: 1.95 | I36: 10 | K36: 46196 | L36: 46196 | M36: =L36+4 -> 46200 | O36: =-1*(IF(VLOOKUP(B36,Estoque!B:J,8,FALSE)>0,0,VLOOKUP(B36,Estoque!B:J,8))) -> 0
B37: PRF10431 | C37: PERFIL U SIMPLES LQ 2,25 X 100 X 40 MM | D37: 2.25 | I37: 10 | K37: 46197 | L37: 46197 | M37: =L37+5 -> 46202 | O37: =-1*(IF(VLOOKUP(B37,Estoque!B:J,8,FALSE)>0,0,VLOOKUP(B37,Estoque!B:J,8))) -> 1.283
B38: PRF10430 | C38: PERFIL U SIMPLES LQ 2,25 X 100 X 50 MM | D38: 2.25 | I38: 20 | K38: 46197 | L38: 46197 | M38: =L38+5 -> 46202 | O38: =-1*(IF(VLOOKUP(B38,Estoque!B:J,8,FALSE)>0,0,VLOOKUP(B38,Estoque!B:J,8))) -> 4.987
B39: PRF10521 | C39: PERFIL U SIMPLES LQ 2,65 X 100 X 40 MM | D39: 2.65 | I39: 40 | K39: 46197 | L39: 46198 | M39: =L39+5 -> 46203 | O39: 2.138
B40: PRF10522 | C40: PERFIL U SIMPLES LQ 2,65 X 100 X 50 MM | D40: 2.65 | I40: 81 | K40: 46198 | L40: 46199 | M40: =L40+3 -> 46202 | O40: =-1*(IF(VLOOKUP(B40,Estoque!B:J,8,FALSE)>0,0,VLOOKUP(B40,Estoque!B:J,8))) -> 15.8112
B41: PRF10611 | C41: PERFIL U SIMPLES LQ 3,00 X 100 X 40 MM | D41: 3 | I41: 35 | K41: 46202 | L41: 46202 | M41: =L41+3 -> 46205 | O41: =-1*(IF(VLOOKUP(B41,Estoque!B:J,8,FALSE)>0,0,VLOOKUP(B41,Estoque!B:J,8))) -> 0
B42: PRF10612 | C42: PERFIL U SIMPLES LQ 3,00 X 100 X 50 MM | D42: 3 | I42: 40 | K42: 46202 | L42: 46203 | M42: =L42+5 -> 46208 | O42: 5.3503
B43: PRF10670 | C43: PERFIL U SIMPLES LQ 4,75 X 100 X 40 MM | D43: 4.75 | I43: 40 | K43: - | L43: - | M43: - | N43: Só slittar com autorização | O43: =-1*(IF(VLOOKUP(B43,Estoque!B:J,8,FALSE)>0,0,VLOOKUP(B43,Estoque!B:J,8))) -> 0
B44: PMG10130 | C44: PERFIL U SIMPLES – 1,95 X 75 X 40 MAGNELIS ZM310 | D44: 1.95 | I44: 20 | K44: 46204 | L44: 46204 | O44: 17.55 | Q44: MAGNELIS ZM310
B45: PRF10321 | C45: PERFIL U SIMPLES LQ 2,00 X 75 X 40 MM | D45: 2 | I45: 25 | K45: 46205 | L45: 46205 | O45: =-1*(IF(VLOOKUP(B45,Estoque!B:J,8,FALSE)>0,0,VLOOKUP(B45,Estoque!B:J,8))) -> 0
B46: PRF10500 | C46: PERFIL U SIMPLES LQ 2,65 X 75 X 40 MM | D46: 2.65 | I46: 25 | K46: 46205 | L46: 46205 | O46: =-1*(IF(VLOOKUP(B46,Estoque!B:J,8,FALSE)>0,0,VLOOKUP(B46,Estoque!B:J,8))) -> 0
B47: PRF10710 | C47: PERFIL U SIMPLES LQ 3,75 X 75 X 40 MM | D47: 3.75 | I47: 10 | K47: 46206 | L47: 46206 | O47: =-1*(IF(VLOOKUP(B47,Estoque!B:J,8,FALSE)>0,0,VLOOKUP(B47,Estoque!B:J,8))) -> 0.9931
B48: PRF10651 | C48: PERFIL U SIMPLES LQ 4,75 X 75 X 40 MM | D48: 4.75 | I48: 40 | K48: 46209 | L48: 46209 | O48: =-1*(IF(VLOOKUP(B48,Estoque!B:J,8,FALSE)>0,0,VLOOKUP(B48,Estoque!B:J,8))) -> 1.0138
B49: PRF10005 | C49: PERFIL U ENRIJ LQ 1,80 X 75 X 40 X 15 MM | D49: 1.8 | I49: 20 | K49: 46210 | L49: 46210 | O49: =-1*(IF(VLOOKUP(B49,Estoque!B:J,8,FALSE)>0,0,VLOOKUP(B49,Estoque!B:J,8))) -> 0
B50: PRF100201 | C50: PERFIL U ENRIJ LQ 2,00 X 75 X 40 X 15 MM - COMPR. ESPECIAL | D50: 2 | I50: 5 | K50: 46210 | L50: 46210 | O50: 2.3625
B51: PRF10020 | C51: PERFIL U ENRIJ LQ 2,00 X 75 X 40 X 15 MM | D51: 2 | I51: 35 | K51: 46210 | L51: 46211 | O51: =-1*(IF(VLOOKUP(B51,Estoque!B:J,8,FALSE)>0,0,VLOOKUP(B51,Estoque!B:J,8))) -> 0
B52: PRF100801 | C52: PERFIL U ENRIJ LQ 2,25 X 75 X 40 X 15 MM - COMPR. ESPECIAL | D52: 2.25 | I52: 18 | K52: 46211 | L52: 46211 | O52: 15.3
B53: PRF10080 | C53: PERFIL U ENRIJ LQ 2,25 X 75 X 40 X 15 MM | D53: 2.25 | I53: 20 | K53: 46212 | L53: 46212 | O53: =-1*(IF(VLOOKUP(B53,Estoque!B:J,8,FALSE)>0,0,VLOOKUP(B53,Estoque!B:J,8))) -> 0
B54: PRF10140 | C54: PERFIL U ENRIJ LQ 2,65 X 75 X 40 X 15 MM | D54: 2.65 | I54: 20 | K54: 46212 | L54: 46212 | O54: =-1*(IF(VLOOKUP(B54,Estoque!B:J,8,FALSE)>0,0,VLOOKUP(B54,Estoque!B:J,8))) -> 0

Sheet memoria
A1: Programação Perfiladeira U 4,75 MM - Junho 2026 | G1: META TOTAL | K1: 1500 | L1: DATA
G2: METAL PERFIL 3/16 | K2: 900 | L2: 46185
A3: Código | B3: Descrição do Perfil | C3: Esp. | D3: Tonelada | E3: Data | G3: Data | H3: Tonelada | I3: OBSERVAÇÕES | K3: Pedidos | L3: Estoque Slitter
D4: Programada | E4: Prevista | G4: Prevista | H4: Realizada | K4: de Venda
D5: =SUM(D6:D40) -> 706 | E5: Comercial | F5: PEDIDO | G5: Produção | H5: =SUM(H6:H487) -> 397.071 | K5: =SUM(K6:K484) -> 164.5371
A6: ='Dados Programa'!B4 -> PRF10255 | B6: ='Dados Programa'!C4 -> PERFIL U ENRIJ LQ 3,00 X 200 X 75 X 20 MM | C6: ='Dados Programa'!D4 -> 3 | D6: ='Dados Programa'!I4 -> 10 | E6: =G6+3 -> 46177 | F6: closed | G6: ='Dados Programa'!L4 -> 46174 | H6: ='Dados Programa'!J4 -> 12.07 | I6: ='Dados Programa'!Q4 -> 0 | J6: ='Dados Programa'!P4 -> 0022.36086 | K6: ='Dados Programa'!O4 -> 0 | L6: ='Dados Programa'!N4 -> mp-ok
A7: ='Dados Programa'!B5 -> PRF10246 | B7: ='Dados Programa'!C5 -> PERFIL U ENRIJ LQ 3,35 X 200 X 75 X 20 MM | C7: ='Dados Programa'!D5 -> 3.35 | D7: ='Dados Programa'!I5 -> 10 | E7: =G7+3 -> 46178 | F7: closed | G7: ='Dados Programa'!L5 -> 46175 | H7: ='Dados Programa'!J5 -> 8.483 | I7: ='Dados Programa'!Q5 -> 0 | J7: ='Dados Programa'!P5 -> 0022.36242 | K7: ='Dados Programa'!O5 -> 5.236 | L7: ='Dados Programa'!N5 -> mp-ok
A8: ='Dados Programa'!B6 -> PRF10120 | B8: ='Dados Programa'!C6 -> PERFIL U ENRIJ LQ 2,25 X 200 X 75 X 20 MM | C8: ='Dados Programa'!D6 -> 2.25 | D8: ='Dados Programa'!I6 -> 20 | E8: =G8+3 -> #VALUE! | F8: closed | G8: ='Dados Programa'!L6 -> - | H8: ='Dados Programa'!J6 -> 6.004 | I8: ='Dados Programa'!Q6 -> 0 | J8: ='Dados Programa'!P6 -> 0022.36100 | K8: ='Dados Programa'!O6 -> 0 | L8: ='Dados Programa'!N6 -> 6t-ok (SEM MP)
A9: ='Dados Programa'!B7 -> PRF10060 | B9: ='Dados Programa'!C7 -> PERFIL U ENRIJ LQ 2,00 X 200 X 75 X 20 MM | C9: ='Dados Programa'!D7 -> 2 | D9: ='Dados Programa'!I7 -> 35 | E9: =G9+3 -> 46179 | F9: closed | G9: ='Dados Programa'!L7 -> 46176 | H9: ='Dados Programa'!J7 -> 34.365 | I9: ='Dados Programa'!Q7 -> 0 | J9: ='Dados Programa'!P7 -> 0022.36101 | K9: ='Dados Programa'!O7 -> 0 | L9: ='Dados Programa'!N7 -> 31t-ok
A10: ='Dados Programa'!B8 -> PRF10180 | B10: ='Dados Programa'!C8 -> PERFIL U ENRIJ LQ 2,65 X 200 X 75 X 20 MM | C10: ='Dados Programa'!D8 -> 2.65 | D10: ='Dados Programa'!I8 -> 25 | E10: =G10+3 -> 46181 | F10: closed | G10: ='Dados Programa'!L8 -> 46178 | H10: ='Dados Programa'!J8 -> 22.46 | I10: ='Dados Programa'!Q8 -> 0 | J10: ='Dados Programa'!P8 -> 0022.36103 | K10: ='Dados Programa'!O8 -> 0.67 | L10: ='Dados Programa'!N8 -> mp-ok
A11: ='Dados Programa'!B9 -> PRF10370 | B11: ='Dados Programa'!C9 -> PERFIL U SIMPLES LQ 2,00 X 200 X 50 MM | C11: ='Dados Programa'!D9 -> 2 | D11: ='Dados Programa'!I9 -> 10 | E11: =G11+3 -> 46184 | F11: closed | G11: ='Dados Programa'!L9 -> 46181 | H11: ='Dados Programa'!J9 -> 11.56 | I11: ='Dados Programa'!Q9 -> 0 | J11: ='Dados Programa'!P9 -> 0022.36104 | K11: ='Dados Programa'!O9 -> 0 | L11: ='Dados Programa'!N9 -> mp-ok
A12: ='Dados Programa'!B10 -> PRF10550 | B12: ='Dados Programa'!C10 -> PERFIL U SIMPLES LQ 2,65 X 200 X 50 MM | C12: ='Dados Programa'!D10 -> 2.65 | D12: ='Dados Programa'!I10 -> 15 | E12: =G12+3 -> 46184 | F12: closed | G12: ='Dados Programa'!L10 -> 46181 | H12: ='Dados Programa'!J10 -> 24.13 | I12: ='Dados Programa'!Q10 -> 0 | J12: ='Dados Programa'!P10 -> 0022.36105 | K12: ='Dados Programa'!O10 -> 0 | L12: ='Dados Programa'!N10 -> mp-ok
A13: ='Dados Programa'!B11 -> PRF10642 | B13: ='Dados Programa'!C11 -> PERFIL U SIMPLES LQ 3,00 X 200 X 50 MM | C13: ='Dados Programa'!D11 -> 3 | D13: ='Dados Programa'!I11 -> 30 | E13: =G13+3 -> 46184 | F13: closed | G13: ='Dados Programa'!L11 -> 46181 | H13: ='Dados Programa'!J11 -> 38.03 | I13: ='Dados Programa'!Q11 -> 0 | J13: ='Dados Programa'!P11 -> 0022.36106 | K13: ='Dados Programa'!O11 -> 0 | L13: ='Dados Programa'!N11 -> mp-ok
A14: ='Dados Programa'!B12 -> PRF100081 | B14: ='Dados Programa'!C12 -> PERFIL U ENRIJ LQ 1,80 X 150 X 60 X 20 MM - COMPR. ESPECIAL | C14: ='Dados Programa'!D12 -> 1.8 | D14: ='Dados Programa'!I12 -> 16 | E14: =G14+3 -> 46185 | F14: closed | G14: ='Dados Programa'!L12 -> 46182 | H14: ='Dados Programa'!J12 -> 14.4596 | I14: ='Dados Programa'!Q12 -> COMPRIMENTO ESPECIAL | J14: ='Dados Programa'!P12 -> 0022.36230 | K14: ='Dados Programa'!O12 -> 14.4596 | L14: ='Dados Programa'!N12 -> mp-ok
A15: ='Dados Programa'!B13 -> PRF10008 | B15: ='Dados Programa'!C13 -> PERFIL U ENRIJ LQ 1,80 X 150 X 60 X 20 MM | C15: ='Dados Programa'!D13 -> 1.8 | D15: ='Dados Programa'!I13 -> 0 | E15: =G15+3 -> #VALUE! | F15: closed | G15: ='Dados Programa'!L13 -> - | H15: ='Dados Programa'!J13 -> 3.4954 | I15: ='Dados Programa'!Q13 -> 0 | J15: ='Dados Programa'!P13 -> 0022.36230 | K15: ='Dados Programa'!O13 -> 0 | L15: ='Dados Programa'!N13 -> passou porque tinha no chão
A16: ='Dados Programa'!B14 -> PRZ101401 | B16: ='Dados Programa'!C14 -> PERFIL U ENRIJ ZC 1,95 X 150 X 60 X 20 MM - COMPR. ESPECIAL | C16: ='Dados Programa'!D14 -> 1.95 | D16: ='Dados Programa'!I14 -> 2 | E16: =G16+3 -> 46185 | F16: closed | G16: ='Dados Programa'!L14 -> 46182 | H16: ='Dados Programa'!J14 -> 1.23 | I16: ='Dados Programa'!Q14 -> COMPRIMENTO ESPECIAL | J16: ='Dados Programa'!P14 -> 0022.36231 | K16: ='Dados Programa'!O14 -> 1.282 | L16: ='Dados Programa'!N14 -> mp-ok
A17: ='Dados Programa'!B15 -> PRZ10140 | B17: ='Dados Programa'!C15 -> PERFIL U ENRIJ ZC 1,95 X 150 X 60 X 20 MM | C17: ='Dados Programa'!D15 -> 1.95 | D17: ='Dados Programa'!I15 -> 10 | E17: =G17+3 -> 46186 | F17: closed | G17: ='Dados Programa'!L15 -> 46183 | H17: ='Dados Programa'!J15 -> 24.535 | I17: ='Dados Programa'!Q15 -> 0 | J17: ='Dados Programa'!P15 -> 0022.36231 | K17: ='Dados Programa'!O15 -> 0 | L17: ='Dados Programa'!N15 -> mp-ok
... A44: ='Dados Programa'!B42 -> PRF10612 | B44: ='Dados Programa'!C42 -> PERFIL U SIMPLES LQ 3,00 X 100 X 50 MM | C44: ='Dados Programa'!D42 -> 3 | D44: ='Dados Programa'!I42 -> 40 | E44: =G44+3 -> 46206 | F44: closed | G44: ='Dados Programa'!L42 -> 46203 | H44: ='Dados Programa'!J42 -> 0 | I44: ='Dados Programa'!Q42 -> 0 | J44: ='Dados Programa'!P42 -> 0 | K44: ='Dados Programa'!O42 -> 5.3503 | L44: ='Dados Programa'!N42 -> 0
A45: ='Dados Programa'!B44 -> PMG10130 | B45: ='Dados Programa'!C44 -> PERFIL U SIMPLES – 1,95 X 75 X 40 MAGNELIS ZM310 | C45: ='Dados Programa'!D44 -> 1.95 | D45: ='Dados Programa'!I44 -> 20 | E45: =G45+3 -> 46207 | F45: closed | G45: ='Dados Programa'!L44 -> 46204 | H45: ='Dados Programa'!J44 -> 0 | I45: ='Dados Programa'!Q44 -> MAGNELIS ZM310 | J45: ='Dados Programa'!P44 -> 0 | K45: ='Dados Programa'!O44 -> 17.55 | L45: ='Dados Programa'!N44 -> 0
A46: ='Dados Programa'!B45 -> PRF10321 | B46: ='Dados Programa'!C45 -> PERFIL U SIMPLES LQ 2,00 X 75 X 40 MM | C46: ='Dados Programa'!D45 -> 2 | D46: ='Dados Programa'!I45 -> 25 | E46: =G46+3 -> 46208 | F46: closed | G46: ='Dados Programa'!L45 -> 46205 | H46: ='Dados Programa'!J45 -> 0 | I46: ='Dados Programa'!Q45 -> 0 | J46: ='Dados Programa'!P45 -> 0 | K46: ='Dados Programa'!O45 -> 0 | L46: ='Dados Programa'!N45 -> 0
A47: ='Dados Programa'!B46 -> PRF10500 | B47: ='Dados Programa'!C46 -> PERFIL U SIMPLES LQ 2,65 X 75 X 40 MM | C47: ='Dados Programa'!D46 -> 2.65 | D47: ='Dados Programa'!I46 -> 25 | E47: =G47+3 -> 46208 | F47: closed | G47: ='Dados Programa'!L46 -> 46205 | H47: ='Dados Programa'!J46 -> 0 | I47: ='Dados Programa'!Q46 -> 0 | J47: ='Dados Programa'!P46 -> 0 | K47: ='Dados Programa'!O46 -> 0 | L47: ='Dados Programa'!N46 -> 0
A48: ='Dados Programa'!B47 -> PRF10710 | B48: ='Dados Programa'!C47 -> PERFIL U SIMPLES LQ 3,75 X 75 X 40 MM | C48: ='Dados Programa'!D47 -> 3.75 | D48: ='Dados Programa'!I47 -> 10 | E48: =G48+3 -> 46209 | F48: closed | G48: ='Dados Programa'!L47 -> 46206 | H48: ='Dados Programa'!J47 -> 0 | I48: ='Dados Programa'!Q47 -> 0 | J48: ='Dados Programa'!P47 -> 0 | K48: ='Dados Programa'!O47 -> 0.9931 | L48: ='Dados Programa'!N47 -> 0
A49: ='Dados Programa'!B48 -> PRF10651 | B49: ='Dados Programa'!C48 -> PERFIL U SIMPLES LQ 4,75 X 75 X 40 MM | C49: ='Dados Programa'!D48 -> 4.75 | D49: ='Dados Programa'!I48 -> 40 | E49: =G49+3 -> 46212 | F49: closed | G49: ='Dados Programa'!L48 -> 46209 | H49: ='Dados Programa'!J48 -> 0 | I49: ='Dados Programa'!Q48 -> 0 | J49: ='Dados Programa'!P48 -> 0 | K49: ='Dados Programa'!O48 -> 1.0138 | L49: ='Dados Programa'!N48 -> 0
A50: ='Dados Programa'!B49 -> PRF10005 | B50: ='Dados Programa'!C49 -> PERFIL U ENRIJ LQ 1,80 X 75 X 40 X 15 MM | C50: ='Dados Programa'!D49 -> 1.8 | D50: ='Dados Programa'!I49 -> 20 | E50: =G50+3 -> 46213 | F50: closed | G50: ='Dados Programa'!L49 -> 46210 | H50: ='Dados Programa'!J49 -> 0 | I50: ='Dados Programa'!Q49 -> 0 | J50: ='Dados Programa'!P49 -> 0 | K50: ='Dados Programa'!O49 -> 0 | L50: ='Dados Programa'!N49 -> 0
A51: ='Dados Programa'!B50 -> PRF100201 | B51: ='Dados Programa'!C50 -> PERFIL U ENRIJ LQ 2,00 X 75 X 40 X 15 MM - COMPR. ESPECIAL | C51: ='Dados Programa'!D50 -> 2 | D51: ='Dados Programa'!I50 -> 5 | E51: =G51+3 -> 46213 | F51: closed | G51: ='Dados Programa'!L50 -> 46210 | H51: ='Dados Programa'!J50 -> 0 | I51: ='Dados Programa'!Q50 -> 0 | J51: ='Dados Programa'!P50 -> 0 | K51: ='Dados Programa'!O50 -> 2.3625 | L51: ='Dados Programa'!N50 -> 0
A52: ='Dados Programa'!B51 -> PRF10020 | B52: ='Dados Programa'!C51 -> PERFIL U ENRIJ LQ 2,00 X 75 X 40 X 15 MM | C52: ='Dados Programa'!D51 -> 2 | D52: ='Dados Programa'!I51 -> 35 | E52: =G52+3 -> 46214 | F52: closed | G52: ='Dados Programa'!L51 -> 46211 | H52: ='Dados Programa'!J51 -> 0 | I52: ='Dados Programa'!Q51 -> 0 | J52: ='Dados Programa'!P51 -> 0 | K52: ='Dados Programa'!O51 -> 0 | L52: ='Dados Programa'!N51 -> 0
A53: ='Dados Programa'!B52 -> PRF100801 | B53: ='Dados Programa'!C52 -> PERFIL U ENRIJ LQ 2,25 X 75 X 40 X 15 MM - COMPR. ESPECIAL | C53: ='Dados Programa'!D52 -> 2.25 | D53: ='Dados Programa'!I52 -> 18 | E53: =G53+3 -> 46214 | F53: closed | G53: ='Dados Programa'!L52 -> 46211 | H53: ='Dados Programa'!J52 -> 0 | I53: ='Dados Programa'!Q52 -> 0 | J53: ='Dados Programa'!P52 -> 0 | K53: ='Dados Programa'!O52 -> 15.3 | L53: ='Dados Programa'!N52 -> 0
A54: ='Dados Programa'!B53 -> PRF10080 | B54: ='Dados Programa'!C53 -> PERFIL U ENRIJ LQ 2,25 X 75 X 40 X 15 MM | C54: ='Dados Programa'!D53 -> 2.25 | D54: ='Dados Programa'!I53 -> 20 | E54: =G54+3 -> 46215 | F54: closed | G54: ='Dados Programa'!L53 -> 46212 | H54: ='Dados Programa'!J53 -> 0 | I54: ='Dados Programa'!Q53 -> 0 | J54: ='Dados Programa'!P53 -> 0 | K54: ='Dados Programa'!O53 -> 0 | L54: ='Dados Programa'!N53 -> 0
A55: ='Dados Programa'!B54 -> PRF10140 | B55: ='Dados Programa'!C54 -> PERFIL U ENRIJ LQ 2,65 X 75 X 40 X 15 MM | C55: ='Dados Programa'!D54 -> 2.65 | D55: ='Dados Programa'!I54 -> 20 | E55: =G55+3 -> 46215 | F55: closed | G55: ='Dados Programa'!L54 -> 46212 | H55: ='Dados Programa'!J54 -> 0 | I55: ='Dados Programa'!Q54 -> 0 | J55: ='Dados Programa'!P54 -> 0 | K55: ='Dados Programa'!O54 -> 0 | L55: ='Dados Programa'!N54 -> 0

Sheet rascunho
A1: Estabelecimento | B1: Item | C1: Descrição | D1: Saldo 001A | E1: Saldo Calogi | F1: Pendência de Vendas | G1: Saldo Disponível
A2: 0022_OI_CED_IND | B2: PMG10130 | C2: PERFIL U SIMPLES – 1,95 X 75 X 40 MAGNELIS | D2: 0 | E2: 0 | F2: 17.55 | G2: -17.55
A3: 0022_OI_CED_IND | B3: PMG101301 | C3: PERFIL U SIMPLES – 1,95 X 75 X 40 MAGNELIS - COMP. ESPECIAL | D3: 0 | E3: 0 | F3: 0 | G3: 0
A4: 0022_OI_CED_IND | B4: PMG10132 | C4: PERFIL U SIMPLES – 1,95 X 68 X 30 MAGNELIS | D4: 0 | E4: 0 | F4: 0 | G4: 0
A5: 0022_OI_CED_IND | B5: PMG10134 | C5: PERFIL U ENRIJ 1,95 X 100 X 40 X 17 MM -MAGNELIS | D5: 0 | E5: 0 | F5: 8.865 | G5: -8.865
A6: 0022_OI_CED_IND | B6: PMG10135 | C6: PERFIL U ENRIJ 1,95 X 127 X 50 X 17 MM -MAGNELIS | D6: 0 | E6: 9.442 | F6: 3.39 | G6: 6.052
A7: 0022_OI_CED_IND | B7: PMG10135 | C7: PERFIL U ENRIJ ZC 1,95 X 127 X 50 X 17 MM -MAGNELIS | D7: 0 | E7: 9.442 | F7: 3.39 | G7: 6.052
A8: 0022_OI_CED_IND | B8: PMG10140 | C8: PERFIL U ENRIJ 1,95 X 150 X 60 X 20 MM MAGNELIS | D8: 0 | E8: 0 | F8: 0 | G8: 0
A9: 0022_OI_CED_IND | B9: PMG10142 | C9: PERFIL U ENRIJ – 1,95 X 75 X 40 X 15 MAGNELIS | D9: 0 | E9: 4.674 | F9: 0 | G9: 4.674
A10: 0022_OI_CED_IND | B10: PMG10142 | C10: PERFIL U ENRIJECIDO – 1,95 X 75 X 40 X 15 MAGNELIS | D10: 0 | E10: 4.674 | F10: 0 | G10: 4.674
A11: 0022_OI_CED_IND | B11: PMG101421 | C11: PERFIL U ENRIJ ZC 1,95 X 150 X 60 X 20 MM - COMP. ESPECIAL | D11: 0 | E11: 0 | F11: 0 | G11: 0
A12: 0022_OI_CED_IND | B12: PMG10160 | C12: PERFIL U ENRIJ ZC 1,95 X 200 X 75 X 20 MM -MAGNELIS | D12: 0 | E12: 0 | F12: 0 | G12: 0
A13: 0022_OI_CED_IND | B13: PMG10180 | C13: PERFIL U SIMPLES 2,30 X 92 X 30 MM MAGNELIS | D13: 0 | E13: 0 | F13: 0 | G13: 0
... A393: 0022_OI_CED_IND | B393: PRZ10549 | C393: PERFIL U SIMPLES ZC 3,00 X 100 X 50 MM | D393: 0 | E393: 0.1838 | F393: 0 | G393: 0.1838

Sheet prog im
A1: Item | B1: Descrição | C1: Data | D1: Fornecedor | E1: Qtd
A2: PMG10130 | B2: PERFIL U SIMPLES – 1,95 X 75 X 40 MAGNELIS | C2: 46176 | E2: 18
A3: PMG10134 | B3: PERFIL U ENRIJ 1,95 X 100 X 40 X 17 MM -MAGNELIS | C3: 46176 | E3: 9
A4: PMG10135 | B4: PERFIL U ENRIJ 1,95 X 127 X 50 X 17 MM -MAGNELIS | C4: 46176 | E4: 5
A5: PRF10004 | B5: PERFIL U ENRIJ LQ 1,80 X 50 X 25 X 10 MM | C5: 46176 | E5: 12
A6: PRF10005 | B6: PERFIL U ENRIJ LQ 1,80 X 75 X 40 X 15 MM | C6: 46176 | E6: 19
A7: PRF10006 | B7: PERFIL U ENRIJ LQ 1,80 X 100 X 50 X 17 MM | C7: 46176 | E7: 23
A8: PRF10009 | B8: PERFIL U ENRIJ LQ 1,80 X 150 X 50 X 20 MM | C8: 46176 | E8: 5
A9: PRF10020 | B9: PERFIL U ENRIJ LQ 2,00 X 75 X 40 X 15 MM | C9: 46176 | E9: 35
A10: PRF10022 | B10: PERFIL U ENRIJ LQ 1,80 X 100 X 40 X 17 MM | C10: 46176 | E10: 48
A11: PRF10031 | B11: PERFIL U ENRIJ LQ 2,00 X 100 X 40 X 17 MM | C11: 46176 | E11: 65
A12: PRF10032 | B12: PERFIL U ENRIJ LQ 2,00 X 100 X 50 X 17 MM | C12: 46176 | E12: 71
A13: PRF10050 | B13: PERFIL U ENRIJ LQ 2,00 X 150 X 60 X 20 MM | C13: 46176 | E13: 59
... A57: PRZ10120 | B57: PERFIL U ENRIJ ZC 1,95 X 100 X 50 X 17 MM | C57: 46176 | E57: 26

Sheet Faturamento
C1: 42370 | D1: 42401 | E1: 42430 | F1: 42461 | G1: 42491 | H1: 42522 | I1: 42552 | J1: 42583 | K1: 42614 | L1: 42644 | M1: 42675 | N1: 42705 | O1: 42736 | P1: 42767 | Q1: 42795 | R1: 42826 | S1: 42856 | T1: 42887 | U1: 42917 | V1: 42948 | W1: 42979 | X1: 43009 | Y1: 43040 | Z1: 43070 | AA1: 43101 | AB1: 43132 | AC1: 43160 | AD1: 43191 | AE1: 43221 | AF1: 43252 | AG1: 43282 | AH1: 43313 | AI1: 43344 | AJ1: 43374 | AK1: 43405 | AL1: 43435 | AM1: 43466 | AN1: 43497 | AO1: 43525 | AP1: 43556 | AQ1: 43586 | AR1: 43617 | AS1: 43647 | AT1: 43678 | AU1: 43709 | AV1: 43739 | AW1: 43770 | AX1: 43800 | AY1: 43831 | AZ1: 43862 | BA1: 43891 | BB1: 43922 | BC1: 43952 | BD1: 43983 | BE1: 44013 | BF1: 44044 | BG1: 44075 | BH1: 44105 | BI1: 44136 | BJ1: 44166 | BK1: 44197 | BL1: 44228 | BM1: 44256 | BN1: 44287 | BO1: 44317 | BP1: 44348 | BQ1: 44378 | BR1: 44409 | BS1: 44440 | BT1: 44470 | BU1: 44501 | BV1: 44531 | BW1: 44562 | BX1: 44593 | BY1: 44621 | BZ1: 44652 | CA1: 44682 | CB1: 44713 | CC1: 44743 | CD1: 44774 | CE1: 44805 | CF1: 44835 | CG1: 44866 | CH1: 44896 | CI1: 44927 | CJ1: 44958 | CK1: 44986 | CL1: 45017 | CM1: 45047 | CN1: 45078 | CO1: 45108 | CP1: 45139 | CQ1: 45170 | CR1: 45200 | CS1: 45231 | CT1: 45261 | CU1: 45292 | CV1: 45323 | CW1: 45352 | CX1: 45383 | CY1: 45413 | CZ1: 45444 | DA1: 45474 | DB1: 45505 | DC1: 45536 | DD1: 45566 | DE1: 45597 | DF1: 45627 | DG1: 45658 | DH1: 45689 | DI1: 45717 | DJ1: 45748 | DK1: 45778 | DL1: 45809 | DM1: 45839 | DN1: 45870 | DO1: 45901 | DP1: 45931 | DQ1: 45962 | DR1: 45992 | DS1: 46023 | DT1: 46054 | DU1: 46082 | DV1: 46113 | DW1: 46143 | DX1: Média de Venda Semestre | DY1: Estoque p/ 45 dias | DZ1: Sugestão de Programação | EA1: Estoque Atual | EB1: Programado
A2: Item | B2: Descrição | C2: =SUM(C3:C284) -> 388.1275 | D2: =SUM(D3:D284) -> 364.6075 | E2: =SUM(E3:E284) -> 626.6115 | F2: =SUM(F3:F284) -> 495.3549 | G2: =SUM(G3:G284) -> 231.1674 | H2: =SUM(H3:H284) -> 300.7712 | I2: =SUM(I3:I284) -> 293.9931 | J2: =SUM(J3:J284) -> 355.9513 | ... DW2: =SUM(DW3:DW284) -> 1342.8437 | DX2: =SUM(DX3:DX472) -> 1354.8621 | DY2: =SUM(DY3:DY472) -> 2032.2932 | EA2: =SUBTOTAL(9,EA3:EA278) -> #N/A | EB2: =SUBTOTAL(9,EB3:EB263) -> #N/A | EC2: 1° Produção | ED2: 2° Produção | EE2: 3° Produção
A3: PRF10001 | B3: PERFIL U SIMPLES LQ 1,50 X 68 X 30 MM | AO3: 7.2 | BD3: 5 | BG3: 1.58 | BH3: 6.66 | BI3: 4.69 | BJ3: 5.918 | BK3: 1.58 | BL3: 1.74 | BM3: 0.42 | CK3: 7 | CR3: 0.189 | CT3: 0.45 | CU3: =IFERROR(VLOOKUP(A3,'fat-01-24'!A:C,3,FALSE),"") | CV3: =IFERROR(VLOOKUP(A3,'fat-02-24'!A:C,3,FALSE),"") -> 3.766 | CW3: =IFERROR(VLOOKUP(A3,'fat-03-24'!A:C,3,FALSE),"") | CX3: =IFERROR(VLOOKUP(A3,'fat-04-24'!A:C,3,FALSE),"") | CY3: =IFERROR(VLOOKUP(A3,'fat-05-24'!A:C,3,FALSE),"") | CZ3: =IFERROR(VLOOKUP(A3,'fat-06-24'!A:C,3,FALSE),"") | DA3: =IFERROR(VLOOKUP(A3,'fat-07-24'!A:C,3,FALSE),"") | DB3: =IFERROR(VLOOKUP(A3,'fat-08-24'!A:D,3,FALSE),"") | DC3: =IFERROR(VLOOKUP(A3,'fat-09-24'!A:C,3,FALSE),"") | DD3: =IFERROR(VLOOKUP(A3,'fat-10-24'!A:C,3,FALSE),"") -> 11.189 | DE3: =IFERROR(VLOOKUP(A3,'fat-11-24'!A:C,3,FALSE),"") -> 0 | DF3: =IFERROR(VLOOKUP(A3,'fat-12-24'!A:D,3,FALSE),"") -> 28.474 | DG3: =IFERROR(VLOOKUP(A3,'fat-01-25'!A:D,3,FALSE),"") -> 5.222 | DH3: =IFERROR(VLOOKUP(A3,'fat-02-25'!A:D,3,FALSE),"") -> 0 | DI3: =IFERROR(VLOOKUP(A3,'fat-03-25'!A:C,3,FALSE),"") -> 0 | DJ3: =IFERROR(VLOOKUP(A3,'fat-04-25'!A:C,3,FALSE),"") -> 5 | DK3: =IFERROR(VLOOKUP(A3,'fat-02-25'!A:C,3,FALSE),"") -> 0 | DL3: =IFERROR(VLOOKUP(A3,'fat-06-25'!A:C,3,FALSE),"") -> 0 | DM3: =IFERROR(VLOOKUP(A3,'fat-05-25'!A:C,3,FALSE),"") -> 0.468 | DN3: =IFERROR(VLOOKUP(A3,'fat-08-25'!A:C,3,FALSE),"") -> 7.46 | DO3: =IFERROR(VLOOKUP(A3,'fat-09-25'!A:C,3,FALSE),"") -> 0 | DP3: =IFERROR(VLOOKUP(A3,'fat-10-25'!A:C,3,FALSE),"") -> 5.272 | DQ3: =IFERROR(VLOOKUP(A3,'fat-11-25'!A:D,3,FALSE),"") | DR3: =IFERROR(VLOOKUP(A3,'fat-12-25'!A:D,3,FALSE),"") | DS3: =IFERROR(VLOOKUP(A3,'fat-01-26'!A:C,3,FALSE),"") | DT3: =IFERROR(VLOOKUP(A3,'fat-02-26'!A:C,3,FALSE),"") | DU3: =IFERROR(VLOOKUP(A3,'fat-03-26'!A:C,3,FALSE),"") | DV3: =IFERROR(VLOOKUP(A3,'fat-04-26'!A:C,3,FALSE),"") | DW3: =IFERROR(VLOOKUP(A3,'fat-05-26'!A:C,3,FALSE),"") | DX3: =SUM(DR3:DW3)/6 -> 0 | DY3: =DX3/30*45 -> 0 | EA3: =VLOOKUP(A3,Estoque!B:I,8,FALSE) -> 0.002 | EB3: =VLOOKUP(A3,Estoque!B:N,13,FALSE) -> 0
A4: PRF10002 | B4: PERFIL U SIMPLES LQ 1,50 X 100 X 40 MM | CU4: =IFERROR(VLOOKUP(A4,'fat-01-24'!A:C,3,FALSE),"") | CV4: =IFERROR(VLOOKUP(A4,'fat-02-24'!A:C,3,FALSE),"") | CW4: =IFERROR(VLOOKUP(A4,'fat-03-24'!A:C,3,FALSE),"") | CX4: =IFERROR(VLOOKUP(A4,'fat-04-24'!A:C,3,FALSE),"") | CY4: =IFERROR(VLOOKUP(A4,'fat-05-24'!A:C,3,FALSE),"") | CZ4: =IFERROR(VLOOKUP(A4,'fat-06-24'!A:C,3,FALSE),"") | DA4: =IFERROR(VLOOKUP(A4,'fat-07-24'!A:C,3,FALSE),"") | DB4: =IFERROR(VLOOKUP(A4,'fat-08-24'!A:D,3,FALSE),"") | DC4: =IFERROR(VLOOKUP(A4,'fat-09-24'!A:C,3,FALSE),"") | DD4: =IFERROR(VLOOKUP(A4,'fat-10-24'!A:C,3,FALSE),"") | DE4: =IFERROR(VLOOKUP(A4,'fat-11-24'!A:C,3,FALSE),"") | DF4: =IFERROR(VLOOKUP(A4,'fat-12-24'!A:D,3,FALSE),"") | DG4: =IFERROR(VLOOKUP(A4,'fat-01-25'!A:D,3,FALSE),"") | DH4: =IFERROR(VLOOKUP(A4,'fat-02-25'!A:D,3,FALSE),"") | DI4: =IFERROR(VLOOKUP(A4,'fat-03-25'!A:C,3,FALSE),"") | DJ4: =IFERROR(VLOOKUP(A4,'fat-04-25'!A:C,3,FALSE),"") | DK4: =IFERROR(VLOOKUP(A4,'fat-02-25'!A:C,3,FALSE),"") | DL4: =IFERROR(VLOOKUP(A4,'fat-06-25'!A:C,3,FALSE),"") | DM4: =IFERROR(VLOOKUP(A4,'fat-05-25'!A:C,3,FALSE),"") | DN4: =IFERROR(VLOOKUP(A4,'fat-08-25'!A:C,3,FALSE),"") | DO4: =IFERROR(VLOOKUP(A4,'fat-09-25'!A:C,3,FALSE),"") | DP4: =IFERROR(VLOOKUP(A4,'fat-10-25'!A:C,3,FALSE),"") | DQ4: =IFERROR(VLOOKUP(A4,'fat-11-25'!A:D,3,FALSE),"") | DR4: =IFERROR(VLOOKUP(A4,'fat-12-25'!A:D,3,FALSE),"") | DS4: =IFERROR(VLOOKUP(A4,'fat-01-26'!A:C,3,FALSE),"") | DT4: =IFERROR(VLOOKUP(A4,'fat-02-26'!A:C,3,FALSE),"") | DU4: =IFERROR(VLOOKUP(A4,'fat-03-26'!A:C,3,FALSE),"") | DV4: =IFERROR(VLOOKUP(A4,'fat-04-26'!A:C,3,FALSE),"") | DW4: =IFERROR(VLOOKUP(A4,'fat-05-26'!A:C,3,FALSE),"") | DX4: =SUM(DR4:DW4)/6 -> 0 | DY4: =DX4/30*45 -> 0 | EA4: =VLOOKUP(A4,Estoque!B:I,8,FALSE) -> 0 | EB4: =VLOOKUP(A4,Estoque!B:N,13,FALSE) -> 0
A5: PRF10003 | B5: PERFIL U SIMPLES LQ 1,50 X 75 X 40 MM | AO5: 10.88 | AR5: 10.26 | AW5: 4.945 | BG5: 0.41 | CL5: 7 | CT5: 0.55 | CU5: =IFERROR(VLOOKUP(A5,'fat-01-24'!A:C,3,FALSE),"") | CV5: =IFERROR(VLOOKUP(A5,'fat-02-24'!A:C,3,FALSE),"") -> 1.403 | CW5: =IFERROR(VLOOKUP(A5,'fat-03-24'!A:C,3,FALSE),"") | CX5: =IFERROR(VLOOKUP(A5,'fat-04-24'!A:C,3,FALSE),"") | CY5: =IFERROR(VLOOKUP(A5,'fat-05-24'!A:C,3,FALSE),"") | CZ5: =IFERROR(VLOOKUP(A5,'fat-06-24'!A:C,3,FALSE),"") | DA5: =IFERROR(VLOOKUP(A5,'fat-07-24'!A:C,3,FALSE),"") | DB5: =IFERROR(VLOOKUP(A5,'fat-08-24'!A:D,3,FALSE),"") | DC5: =IFERROR(VLOOKUP(A5,'fat-09-24'!A:C,3,FALSE),"") | DD5: =IFERROR(VLOOKUP(A5,'fat-10-24'!A:C,3,FALSE),"") | DE5: =IFERROR(VLOOKUP(A5,'fat-11-24'!A:C,3,FALSE),"") | DF5: =IFERROR(VLOOKUP(A5,'fat-12-24'!A:D,3,FALSE),"") -> 10.004 | DG5: =IFERROR(VLOOKUP(A5,'fat-01-25'!A:D,3,FALSE),"") -> 2.614 | DH5: =IFERROR(VLOOKUP(A5,'fat-02-25'!A:D,3,FALSE),"") | DI5: =IFERROR(VLOOKUP(A5,'fat-03-25'!A:C,3,FALSE),"") | DJ5: =IFERROR(VLOOKUP(A5,'fat-04-25'!A:C,3,FALSE),"") | DK5: =IFERROR(VLOOKUP(A5,'fat-02-25'!A:C,3,FALSE),"") | DL5: =IFERROR(VLOOKUP(A5,'fat-06-25'!A:C,3,FALSE),"") -> 0 | DM5: =IFERROR(VLOOKUP(A5,'fat-05-25'!A:C,3,FALSE),"") | DN5: =IFERROR(VLOOKUP(A5,'fat-08-25'!A:C,3,FALSE),"") -> 8.89 | DO5: =IFERROR(VLOOKUP(A5,'fat-09-25'!A:C,3,FALSE),"") -> 0 | DP5: =IFERROR(VLOOKUP(A5,'fat-10-25'!A:C,3,FALSE),"") -> 0 | DQ5: =IFERROR(VLOOKUP(A5,'fat-11-25'!A:D,3,FALSE),"") | DR5: =IFERROR(VLOOKUP(A5,'fat-12-25'!A:D,3,FALSE),"") | DS5: =IFERROR(VLOOKUP(A5,'fat-01-26'!A:C,3,FALSE),"") | DT5: =IFERROR(VLOOKUP(A5,'fat-02-26'!A:C,3,FALSE),"") | DU5: =IFERROR(VLOOKUP(A5,'fat-03-26'!A:C,3,FALSE),"") | DV5: =IFERROR(VLOOKUP(A5,'fat-04-26'!A:C,3,FALSE),"") | DW5: =IFERROR(VLOOKUP(A5,'fat-05-26'!A:C,3,FALSE),"") | DX5: =SUM(DR5:DW5)/6 -> 0 | DY5: =DX5/30*45 -> 0 | EA5: =VLOOKUP(A5,Estoque!B:I,8,FALSE) -> 0 | EB5: =VLOOKUP(A5,Estoque!B:N,13,FALSE) -> 0
A6: PRF10004 | B6: PERFIL U ENRIJ LQ 1,80 X 50 X 25 X 10 MM | C6: 12.48 | D6: 11.363 | E6: 6.62 | F6: 6.825 | G6: 0.05 | H6: 3.615 | I6: 3.451 | K6: 7.4 | L6: 2.63 | M6: 6.029 | N6: 6.875 | O6: 2 | P6: 9.68 | Q6: 3.604 | R6: 0.115 | S6: -3.4601 | U6: 2.558 | V6: 3.37 | W6: 0.214 | AB6: 4.165 | AC6: 3.46 | AD6: 0.72 | AE6: 2.673 | AG6: 3.456 | AH6: 0.036 | AI6: 38.289 | AJ6: 8.052 | AK6: 4.156 | AL6: 5.535 | AM6: 7.273 | AN6: 1.725 | AO6: 1.35 | AP6: 6.005 | AQ6: 9.358 | AR6: 0.405 | AS6: 11.635 | AT6: 8.126 | AU6: 14.866 | AV6: 17.271 | AW6: 7.716 | AX6: 2.175 | AY6: 5.594 | AZ6: 13.051 | BA6: 20.135 | BB6: 14.295 | BC6: 8.7807 | BD6: 23.26 | BE6: 28.832 | BF6: 18.6228 | BG6: 26.165 | BH6: 4.953 | BI6: 85.027 | BJ6: 2.919 | BK6: 2.06 | BL6: 24.172 | BM6: 9.256 | BN6: 9.854 | BO6: 57.28 | BP6: 14.025 | BQ6: 5.516 | BR6: 0.51 | BS6: 1.163 | BT6: 0.82 | BU6: 1.74 | BV6: 5.12 | BW6: 3.261 | BX6: 0.56 | BY6: 1.995 | BZ6: 40.433 | CA6: 3.245 | CB6: 0.18 | CD6: 10.4198 | CE6: 12.041 | CF6: 1.16 | CG6: 30.412 | CH6: 0.9 | CI6: -0.316 | CJ6: 0.289 | CK6: 36.336 | CL6: 6.074 | CM6: 19.872 | CN6: 9.759 | CO6: 19.296 | CP6: 4.797 | CQ6: 3.122 | CR6: 4.809 | CS6: 4.2697748 | CT6: 27.574 | CU6: =IFERROR(VLOOKUP(A6,'fat-01-24'!A:C,3,FALSE),"") -> 61.949 | CV6: =IFERROR(VLOOKUP(A6,'fat-02-24'!A:C,3,FALSE),"") -> 13.719 | CW6: =IFERROR(VLOOKUP(A6,'fat-03-24'!A:C,3,FALSE),"") -> 18.363 | CX6: =IFERROR(VLOOKUP(A6,'fat-04-24'!A:C,3,FALSE),"") -> 23.749 | CY6: =IFERROR(VLOOKUP(A6,'fat-05-24'!A:C,3,FALSE),"") -> 11.5411 | CZ6: =IFERROR(VLOOKUP(A6,'fat-06-24'!A:C,3,FALSE),"") -> 9.759 | DA6: =IFERROR(VLOOKUP(A6,'fat-07-24'!A:C,3,FALSE),"") | DB6: =IFERROR(VLOOKUP(A6,'fat-08-24'!A:D,3,FALSE),"") -> 60.965 | DC6: =IFERROR(VLOOKUP(A6,'fat-09-24'!A:C,3,FALSE),"") -> 17.632 | DD6: =IFERROR(VLOOKUP(A6,'fat-10-24'!A:C,3,FALSE),"") -> 25.492 | DE6: =IFERROR(VLOOKUP(A6,'fat-11-24'!A:C,3,FALSE),"") -> 46.023 | DF6: =IFERROR(VLOOKUP(A6,'fat-12-24'!A:D,3,FALSE),"") -> 12.32 | DG6: =IFERROR(VLOOKUP(A6,'fat-01-25'!A:D,3,FALSE),"") -> 33.614 | DH6: =IFERROR(VLOOKUP(A6,'fat-02-25'!A:D,3,FALSE),"") -> 7.722 | DI6: =IFERROR(VLOOKUP(A6,'fat-03-25'!A:C,3,FALSE),"") -> 0.54 | DJ6: =IFERROR(VLOOKUP(A6,'fat-04-25'!A:C,3,FALSE),"") -> 23.785 | DK6: =IFERROR(VLOOKUP(A6,'fat-02-25'!A:C,3,FALSE),"") -> 7.722 | DL6: =IFERROR(VLOOKUP(A6,'fat-06-25'!A:C,3,FALSE),"") -> 7.488 | DM6: =IFERROR(VLOOKUP(A6,'fat-05-25'!A:C,3,FALSE),"") -> 8.678 | DN6: =IFERROR(VLOOKUP(A6,'fat-08-25'!A:C,3,FALSE),"") -> 6.916 | DO6: =IFERROR(VLOOKUP(A6,'fat-09-25'!A:C,3,FALSE),"") -> 8.962 | DP6: =IFERROR(VLOOKUP(A6,'fat-10-25'!A:C,3,FALSE),"") -> 13.032 | DQ6: =IFERROR(VLOOKUP(A6,'fat-11-25'!A:D,3,FALSE),"") -> 18.071 | DR6: =IFERROR(VLOOKUP(A6,'fat-12-25'!A:D,3,FALSE),"") -> 15.32 | DS6: =IFERROR(VLOOKUP(A6,'fat-01-26'!A:C,3,FALSE),"") -> 15.204 | DT6: =IFERROR(VLOOKUP(A6,'fat-02-26'!A:C,3,FALSE),"") -> 14.644 | DU6: =IFERROR(VLOOKUP(A6,'fat-03-26'!A:C,3,FALSE),"") -> 36.637 | DV6: =IFERROR(VLOOKUP(A6,'fat-04-26'!A:C,3,FALSE),"") -> 16.42 | DW6: =IFERROR(VLOOKUP(A6,'fat-05-26'!A:C,3,FALSE),"") -> 4.063 | DX6: =SUM(DR6:DW6)/6 -> 17.048 | DY6: =DX6/30*45 -> 25.572 | EA6: =VLOOKUP(A6,Estoque!B:I,8,FALSE) -> 22.4562 | EB6: =VLOOKUP(A6,Estoque!B:N,13,FALSE) -> 20 | EC6: 90 | ED6: 20 | EE6: 20
A7: PRF10005 | B7: PERFIL U ENRIJ LQ 1,80 X 75 X 40 X 15 MM | C7: 27.08 | D7: 15.99 | E7: 57.49 | F7: 65.5 | G7: 15.46 | H7: 21.52 | I7: 18.515 | J7: 17.955 | K7: 24.855 | M7: 10.135 | N7: 1.685 | P7: 26.405 | Q7: 24.945 | R7: 0.9933 | S7: -11.085 | T7: 1.96 | U7: 4.768 | V7: 11.692 | W7: 3.266 | AA7: 0.028 | AB7: 1.91 | AC7: 10.465 | AD7: 19.242 | AE7: 8.608 | AF7: 11.382 | AG7: 4.822 | AH7: 9.47 | AI7: 70.196 | AJ7: 13.41 | AK7: 16.717 | AL7: 35.033 | AM7: 21.674 | AN7: 54.967 | AO7: 4.897 | AP7: 28.032 | AQ7: 28.603 | AR7: 4.195 | AS7: 52.955 | AT7: 50.27 | AU7: 33.746 | AV7: 58.461 | AW7: 7.513 | AX7: 22.744 | AY7: 26.165 | AZ7: 38.078 | BA7: 28.297 | BB7: 57.167 | BC7: 26.2328 | BD7: 47.236 | BE7: 68.635 | BF7: 40.853 | BG7: 57.58 | BH7: 11.32 | BI7: 67.1652 | BJ7: 21.61 | BK7: 29.143 | BL7: 2.625 | BM7: 68.037 | BN7: 3.5 | BO7: 39.203 | BP7: 21.671 | BQ7: 14.025 | BR7: 7.55 | BS7: 3.5046 | BT7: 1.03 | BU7: 8.161 | BV7: 5.992 | BW7: 15.045 | BX7: 10.065 | BY7: 28.338 | BZ7: 1.3326 | CA7: 49.726 | CB7: 10.208 | CC7: 6.861 | CD7: 6.6134 | CE7: 30.847 | CF7: 84.638 | CG7: 48.917 | CH7: 31.5295 | CI7: 55.0811 | CJ7: 28.18 | CK7: 40.577 | CL7: 4.915 | CM7: 42.901 | CN7: 21.1145 | CO7: 12.0745 | CP7: 18.228 | CQ7: 32.9395 | CR7: 18.5215 | CS7: 24.864 | CT7: 11.21 | CU7: =IFERROR(VLOOKUP(A7,'fat-01-24'!A:C,3,FALSE),"") -> 12.151 | CV7: =IFERROR(VLOOKUP(A7,'fat-02-24'!A:C,3,FALSE),"") -> 12.8885 | CW7: =IFERROR(VLOOKUP(A7,'fat-03-24'!A:C,3,FALSE),"") -> 115.093 | CX7: =IFERROR(VLOOKUP(A7,'fat-04-24'!A:C,3,FALSE),"") -> 31.7265 | CY7: =IFERROR(VLOOKUP(A7,'fat-05-24'!A:C,3,FALSE),"") -> 30.5397 | CZ7: =IFERROR(VLOOKUP(A7,'fat-06-24'!A:C,3,FALSE),"") -> 21.1145 | DA7: =IFERROR(VLOOKUP(A7,'fat-07-24'!A:C,3,FALSE),"") -> 3.082 | DB7: =IFERROR(VLOOKUP(A7,'fat-08-24'!A:D,3,FALSE),"") -> 12.9955 | DC7: =IFERROR(VLOOKUP(A7,'fat-09-24'!A:C,3,FALSE),"") -> 53.4525 | DD7: =IFERROR(VLOOKUP(A7,'fat-10-24'!A:C,3,FALSE),"") -> 59.488 | DE7: =IFERROR(VLOOKUP(A7,'fat-11-24'!A:C,3,FALSE),"") -> 19.922 | DF7: =IFERROR(VLOOKUP(A7,'fat-12-24'!A:D,3,FALSE),"") -> 63.9795 | DG7: =IFERROR(VLOOKUP(A7,'fat-01-25'!A:D,3,FALSE),"") -> 19.959 | DH7: =IFERROR(VLOOKUP(A7,'fat-02-25'!A:D,3,FALSE),"") -> 30.8349 | DI7: =IFERROR(VLOOKUP(A7,'fat-03-25'!A:C,3,FALSE),"") -> 27.5105 | DJ7: =IFERROR(VLOOKUP(A7,'fat-04-25'!A:C,3,FALSE),"") -> 44.7573 | DK7: =IFERROR(VLOOKUP(A7,'fat-02-25'!A:C,3,FALSE),"") -> 30.8349 | DL7: =IFERROR(VLOOKUP(A7,'fat-06-25'!A:C,3,FALSE),"") -> 13.1755 | DM7: =IFERROR(VLOOKUP(A7,'fat-05-25'!A:C,3,FALSE),"") -> 24.788 | DN7: =IFERROR(VLOOKUP(A7,'fat-08-25'!A:C,3,FALSE),"") -> 36.732 | DO7: =IFERROR(VLOOKUP(A7,'fat-09-25'!A:C,3,FALSE),"") -> 30.28 | DP7: =IFERROR(VLOOKUP(A7,'fat-10-25'!A:C,3,FALSE),"") -> 5.646 | DQ7: =IFERROR(VLOOKUP(A7,'fat-11-25'!A:D,3,FALSE),"") -> 28.9395 | DR7: =IFERROR(VLOOKUP(A7,'fat-12-25'!A:D,3,FALSE),"") -> 11.973 | DS7: =IFERROR(VLOOKUP(A7,'fat-01-26'!A:C,3,FALSE),"") -> 29.4945 | DT7: =IFERROR(VLOOKUP(A7,'fat-02-26'!A:C,3,FALSE),"") -> 50.971 | DU7: =IFERROR(VLOOKUP(A7,'fat-03-26'!A:C,3,FALSE),"") -> 108.809 | DV7: =IFERROR(VLOOKUP(A7,'fat-04-26'!A:C,3,FALSE),"") -> 30.4565 | DW7: =IFERROR(VLOOKUP(A7,'fat-05-26'!A:C,3,FALSE),"") -> 38.0235 | DX7: =SUM(DR7:DW7)/6 -> 44.954583 | DY7: =DX7/30*45 -> 67.431875 | EA7: =VLOOKUP(A7,Estoque!B:I,8,FALSE) -> 60.4503 | EB7: =VLOOKUP(A7,Estoque!B:N,13,FALSE) -> 0 | ED7: 50 | EE7: 50
A8: PRF10006 | B8: PERFIL U ENRIJ LQ 1,80 X 100 X 50 X 17 MM | C8: 7.43 | D8: 1.796 | E8: 6.247 | F8: 9 | G8: 0.1199 | H8: 6.848 | J8: 0.955 | K8: 9.39 | L8: 5.995 | N8: 4.125 | P8: 2.63 | Q8: 2.993 | R8: 0.055 | T8: 0.873 | U8: 2.865 | V8: 1.3023 | W8: 3.558 | X8: 0.951 | Y8: 0.27 | AA8: 2.824 | AC8: 2.41 | AD8: 1.466 | AE8: 2.04 | AF8: 4.275 | AG8: 1.254 | AI8: 1.325 | AJ8: 8.647 | AK8: 1.96 | AL8: 5.21 | AM8: 1.87 | AN8: 3.745 | AO8: 0.985 | AP8: 11.497 | AQ8: 5.453 | AS8: 4.809 | AT8: 8.575 | AU8: 3.38 | AV8: 7.812 | AW8: 6.355 | AX8: 1.895 | AY8: 2.931 | AZ8: 3.3 | BA8: 14.26 | BB8: 0.56 | BC8: 4.19 | BD8: 10.715 | BE8: 3.25 | BF8: 8.177 | BH8: 1.625 | BI8: 5.214 | BJ8: 10.2 | BK8: 12.95 | BL8: 8.089 | BM8: 14.47 | BN8: 0.885 | BO8: 5.995 | BP8: 8.73 | BQ8: 3.17 | BR8: 3.895 | BS8: 6.808 | BT8: 0.485 | BU8: 2.535 | BV8: 2.966 | BW8: 5.13 | BY8: 0.965 | BZ8: 6.356 | CA8: 7.18 | CB8: 0.68 | CC8: 2.035 | CD8: 14.706 | CE8: 10.095 | CF8: 4.614 | CG8: 3.347 | CH8: 7.63 | CI8: 2.546 | CJ8: 0.435 | CK8: 11.4612 | CL8: 7.898 | CM8: 7.218 | CN8: 5.31 | CO8: 1.01 | CP8: 3.579 | CQ8: 4.0856 | CR8: 1.494 | CS8: 22.5426 | CT8: 11.6838 | CU8: =IFERROR(VLOOKUP(A8,'fat-01-24'!A:C,3,FALSE),"") -> 2.54 | CV8: =IFERROR(VLOOKUP(A8,'fat-02-24'!A:C,3,FALSE),"") -> 1.6638 | CW8: =IFERROR(VLOOKUP(A8,'fat-03-24'!A:C,3,FALSE),"") -> 16.64 | CX8: =IFERROR(VLOOKUP(A8,'fat-04-24'!A:C,3,FALSE),"") -> 3.938 | CY8: =IFERROR(VLOOKUP(A8,'fat-05-24'!A:C,3,FALSE),"") -> 11.824 | CZ8: =IFERROR(VLOOKUP(A8,'fat-06-24'!A:C,3,FALSE),"") -> 5.31 | DA8: =IFERROR(VLOOKUP(A8,'fat-07-24'!A:C,3,FALSE),"") -> 17.858 | DB8: =IFERROR(VLOOKUP(A8,'fat-08-24'!A:D,3,FALSE),"") -> 10.729 | DC8: =IFERROR(VLOOKUP(A8,'fat-09-24'!A:C,3,FALSE),"") -> 12.607 | DD8: =IFERROR(VLOOKUP(A8,'fat-10-24'!A:C,3,FALSE),"") -> 7.693 | DE8: =IFERROR(VLOOKUP(A8,'fat-11-24'!A:C,3,FALSE),"") -> 33.1834 | DF8: =IFERROR(VLOOKUP(A8,'fat-12-24'!A:D,3,FALSE),"") -> 26.7494 | DG8: =IFERROR(VLOOKUP(A8,'fat-01-25'!A:D,3,FALSE),"") -> 7.4522 | DH8: =IFERROR(VLOOKUP(A8,'fat-02-25'!A:D,3,FALSE),"") -> 7.001 | DI8: =IFERROR(VLOOKUP(A8,'fat-03-25'!A:C,3,FALSE),"") -> 48.1626 | DJ8: =IFERROR(VLOOKUP(A8,'fat-04-25'!A:C,3,FALSE),"") -> 4.756 | DK8: =IFERROR(VLOOKUP(A8,'fat-02-25'!A:C,3,FALSE),"") -> 7.001 | DL8: =IFERROR(VLOOKUP(A8,'fat-06-25'!A:C,3,FALSE),"") -> 1.59 | DM8: =IFERROR(VLOOKUP(A8,'fat-05-25'!A:C,3,FALSE),"") -> 2.309 | DN8: =IFERROR(VLOOKUP(A8,'fat-08-25'!A:C,3,FALSE),"") -> 8.902 | DO8: =IFERROR(VLOOKUP(A8,'fat-09-25'!A:C,3,FALSE),"") -> 16.951 | DP8: =IFERROR(VLOOKUP(A8,'fat-10-25'!A:C,3,FALSE),"") -> 16.61 | DQ8: =IFERROR(VLOOKUP(A8,'fat-11-25'!A:D,3,FALSE),"") -> 1.021 | DR8: =IFERROR(VLOOKUP(A8,'fat-12-25'!A:D,3,FALSE),"") -> 17.238 | DS8: =IFERROR(VLOOKUP(A8,'fat-01-26'!A:C,3,FALSE),"") -> 7.553 | DT8: =IFERROR(VLOOKUP(A8,'fat-02-26'!A:C,3,FALSE),"") -> 11.298 | DU8: =IFERROR(VLOOKUP(A8,'fat-03-26'!A:C,3,FALSE),"") -> 14.8588 | DV8: =IFERROR(VLOOKUP(A8,'fat-04-26'!A:C,3,FALSE),"") -> 9.264 | DW8: =IFERROR(VLOOKUP(A8,'fat-05-26'!A:C,3,FALSE),"") -> 20.483 | DX8: =SUM(DR8:DW8)/6 -> 13.449133 | DY8: =DX8/30*45 -> 20.1737 | EA8: =VLOOKUP(A8,Estoque!B:I,8,FALSE) -> -1.9066 | EB8: =VLOOKUP(A8,Estoque!B:N,13,FALSE) -> 0 | EC8: 15
A9: PRF10007 | B9: PERFIL U ENRIJ LQ 1,80 X 127 X 50 X 17 MM | E9: 0.658 | G9: 1.31 | H9: 1.345 | I9: 0.71 | L9: 2.03 | M9: 2.725 | O9: 18.49 | P9: 1.388 | Q9: 2.04 | S9: 5.28 | T9: 10.773 | U9: 11.33 | V9: 6.255 | W9: 2.232 | X9: 1.346 | AA9: 3.9 | AB9: 2.94 | AE9: 2.88 | AG9: 2.02 | AH9: 2.155 | AI9: 1.315 | AJ9: 1.205 | AK9: 0.525 | AL9: 10.21 | AM9: -1.05 | AN9: 2.165 | AO9: 0.1 | AP9: 0.8 | AQ9: 21.74 | AS9: 0.318 | AT9: 12.724 | AU9: 6.855 | AV9: 5.7179 | AW9: 0.714 | AX9: 3.49 | AY9: 1.31 | AZ9: 5.295 | BA9: 1.315 | BB9: 0.51 | BC9: 6.195 | BD9: 3.662 | BE9: 3.475 | BF9: 10.528 | BG9: 0.315 | BJ9: 0.115 | BK9: 2.66 | BL9: 8.12 | BM9: 0.91 | BO9: 0.702 | BP9: 2.21 | BR9: 0.76 | BT9: 1.405 | BV9: 1.49 | BX9: 0.31 | BY9: 0.325 | BZ9: 1.585 | CA9: 0.189 | CB9: 3.01 | CD9: 2.4 | CF9: 20.45 | CH9: 2.155 | CI9: 1.302 | CJ9: 4.305 | CK9: 13.209 | CL9: 1.155 | CM9: 5.161 | CN9: 7.098 | CO9: 1.239 | CP9: 16.018 | CR9: 9.501 | CS9: 3.8 | CT9: 14.429 | CU9: =IFERROR(VLOOKUP(A9,'fat-01-24'!A:C,3,FALSE),"") -> 6.111 | CV9: =IFERROR(VLOOKUP(A9,'fat-02-24'!A:C,3,FALSE),"") -> 2.032 | CW9: =IFERROR(VLOOKUP(A9,'fat-03-24'!A:C,3,FALSE),"") -> 10.57 | CX9: =IFERROR(VLOOKUP(A9,'fat-04-24'!A:C,3,FALSE),"") -> 12.931 | CY9: =IFERROR(VLOOKUP(A9,'fat-05-24'!A:C,3,FALSE),"") -> 4.377 | CZ9: =IFERROR(VLOOKUP(A9,'fat-06-24'!A:C,3,FALSE),"") -> 7.098 | DA9: =IFERROR(VLOOKUP(A9,'fat-07-24'!A:C,3,FALSE),"") -> 6.316 | DB9: =IFERROR(VLOOKUP(A9,'fat-08-24'!A:D,3,FALSE),"") -> 9.496 | DC9: =IFERROR(VLOOKUP(A9,'fat-09-24'!A:C,3,FALSE),"") -> 1.946 | DD9: =IFERROR(VLOOKUP(A9,'fat-10-24'!A:C,3,FALSE),"") -> 8.918 | DE9: =IFERROR(VLOOKUP(A9,'fat-11-24'!A:C,3,FALSE),"") -> 21.709 | DF9: =IFERROR(VLOOKUP(A9,'fat-12-24'!A:D,3,FALSE),"") -> 13.959 | DG9: =IFERROR(VLOOKUP(A9,'fat-01-25'!A:D,3,FALSE),"") -> 3.432 | DH9: =IFERROR(VLOOKUP(A9,'fat-02-25'!A:D,3,FALSE),"") -> 12.486 | DI9: =IFERROR(VLOOKUP(A9,'fat-03-25'!A:C,3,FALSE),"") -> 9.78 | DJ9: =IFERROR(VLOOKUP(A9,'fat-04-25'!A:C,3,FALSE),"") -> 20.65 | DK9: =IFERROR(VLOOKUP(A9,'fat-02-25'!A:C,3,FALSE),"") -> 12.486 | DL9: =IFERROR(VLOOKUP(A9,'fat-06-25'!A:C,3,FALSE),"") -> 3.082 | DM9: =IFERROR(VLOOKUP(A9,'fat-05-25'!A:C,3,FALSE),"") -> 1.743 | DN9: =IFERROR(VLOOKUP(A9,'fat-08-25'!A:C,3,FALSE),"") -> 8.938 | DO9: =IFERROR(VLOOKUP(A9,'fat-09-25'!A:C,3,FALSE),"") -> 12.622 | DP9: =IFERROR(VLOOKUP(A9,'fat-10-25'!A:C,3,FALSE),"") -> 3.331 | DQ9: =IFERROR(VLOOKUP(A9,'fat-11-25'!A:D,3,FALSE),"") | DR9: =IFERROR(VLOOKUP(A9,'fat-12-25'!A:D,3,FALSE),"") | DS9: =IFERROR(VLOOKUP(A9,'fat-01-26'!A:C,3,FALSE),"") -> 6.884 | DT9: =IFERROR(VLOOKUP(A9,'fat-02-26'!A:C,3,FALSE),"") -> 6.513 | DU9: =IFERROR(VLOOKUP(A9,'fat-03-26'!A:C,3,FALSE),"") -> 10.717 | DV9: =IFERROR(VLOOKUP(A9,'fat-04-26'!A:C,3,FALSE),"") -> 3.918 | DW9: =IFERROR(VLOOKUP(A9,'fat-05-26'!A:C,3,FALSE),"") -> 4.845 | DX9: =SUM(DR9:DW9)/6 -> 5.4795 | DY9: =DX9/30*45 -> 8.21925 | EA9: =VLOOKUP(A9,Estoque!B:I,8,FALSE) -> 10.006 | EB9: =VLOOKUP(A9,Estoque!B:N,13,FALSE) -> 0 | EC9: 10
A10: PRF10008 | B10: PERFIL U ENRIJ LQ 1,80 X 150 X 60 X 20 MM | C10: 4.68 | D10: 0.735 | G10: 0.49 | H10: 12.145 | N10: 0.865 | P10: 1.7 | Q10: 2.23 | S10: 2.37 | T10: 0.222 | U10: 2.23 | W10: 0.32 | AC10: 0.85 | AD10: 0.298 | AG10: 0.551 | AH10: 0.4 | AJ10: 4.35 | AK10: 1 | AL10: 1.426 | AM10: 4.745 | AN10: 3.311 | AP10: 2.37 | AQ10: 0.505 | AR10: 1 | AT10: 3.598 | AW10: 1.871 | AZ10: 0.42 | BA10: 0.12 | BB10: 8.43 | BC10: 0.325 | BD10: 5.295 | BE10: 3.845 | BF10: 6.842 | BG10: 7.533 | BH10: 5.625 | BI10: 0.5 | BJ10: 0.3 | BK10: 0.855 | BL10: 1 | BM10: 8.436 | BN10: 1.48 | BO10: 7.695 | BP10: 0.315 | BQ10: 3.415 | BU10: 0.985 | BV10: 0.785 | BX10: 6.305 | BY10: 9.53 | BZ10: 4.135 | CA10: 3.89 | CB10: 3.53 | CC10: 1.195 | CD10: 0.25 | CF10: 3.325 | CG10: 0.25 | CH10: 3.6 | CI10: 3.4 | CL10: 0.175 | CM10: 5.025 | CN10: 0.05 | CP10: 2.275 | CR10: 1.741 | CS10: 6.97 | CT10: 3.208 | CU10: =IFERROR(VLOOKUP(A10,'fat-01-24'!A:C,3,FALSE),"") -> 2.263 | CV10: =IFERROR(VLOOKUP(A10,'fat-02-24'!A:C,3,FALSE),"") -> 0.8 | CW10: =IFERROR(VLOOKUP(A10,'fat-03-24'!A:C,3,FALSE),"") -> 1.125 | CX10: =IFERROR(VLOOKUP(A10,'fat-04-24'!A:C,3,FALSE),"") -> 4.525 | CY10: =IFERROR(VLOOKUP(A10,'fat-05-24'!A:C,3,FALSE),"") -> 0.175 | CZ10: =IFERROR(VLOOKUP(A10,'fat-06-24'!A:C,3,FALSE),"") -> 0.05 | DA10: =IFERROR(VLOOKUP(A10,'fat-07-24'!A:C,3,FALSE),"") -> 7.815 | DB10: =IFERROR(VLOOKUP(A10,'fat-08-24'!A:D,3,FALSE),"") -> 2.4 | DC10: =IFERROR(VLOOKUP(A10,'fat-09-24'!A:C,3,FALSE),"") -> 6.396 | DD10: =IFERROR(VLOOKUP(A10,'fat-10-24'!A:C,3,FALSE),"") -> 2.01 | DE10: =IFERROR(VLOOKUP(A10,'fat-11-24'!A:C,3,FALSE),"") -> 2.37 | DF10: =IFERROR(VLOOKUP(A10,'fat-12-24'!A:D,3,FALSE),"") -> 13.075 | DG10: =IFERROR(VLOOKUP(A10,'fat-01-25'!A:D,3,FALSE),"") -> 0.675 | DH10: =IFERROR(VLOOKUP(A10,'fat-02-25'!A:D,3,FALSE),"") -> 2.71 | DI10: =IFERROR(VLOOKUP(A10,'fat-03-25'!A:C,3,FALSE),"") -> 0.425 | DJ10: =IFERROR(VLOOKUP(A10,'fat-04-25'!A:C,3,FALSE),"") -> 0 | DK10: =IFERROR(VLOOKUP(A10,'fat-02-25'!A:C,3,FALSE),"") -> 2.71 | DL10: =IFERROR(VLOOKUP(A10,'fat-06-25'!A:C,3,FALSE),"") -> 0.625 | DM10: =IFERROR(VLOOKUP(A10,'fat-05-25'!A:C,3,FALSE),"") -> 2 | DN10: =IFERROR(VLOOKUP(A10,'fat-08-25'!A:C,3,FALSE),"") -> 0 | DO10: =IFERROR(VLOOKUP(A10,'fat-09-25'!A:C,3,FALSE),"") -> 2.501 | DP10: =IFERROR(VLOOKUP(A10,'fat-10-25'!A:C,3,FALSE),"") -> 0.425 | DQ10: =IFERROR(VLOOKUP(A10,'fat-11-25'!A:D,3,FALSE),"") -> 1.6 | DR10: =IFERROR(VLOOKUP(A10,'fat-12-25'!A:D,3,FALSE),"") -> 0 | DS10: =IFERROR(VLOOKUP(A10,'fat-01-26'!A:C,3,FALSE),"") -> 11.325 | DT10: =IFERROR(VLOOKUP(A10,'fat-02-26'!A:C,3,FALSE),"") -> 6.14 | DU10: =IFERROR(VLOOKUP(A10,'fat-03-26'!A:C,3,FALSE),"") -> 2.69 | DV10: =IFERROR(VLOOKUP(A10,'fat-04-26'!A:C,3,FALSE),"") -> 3.476 | DW10: =IFERROR(VLOOKUP(A10,'fat-05-26'!A:C,3,FALSE),"") -> 1.455 | DX10: =SUM(DR10:DW10)/6 -> 4.181 | DY10: =DX10/30*45 -> 6.2715 | EA10: =VLOOKUP(A10,Estoque!B:I,8,FALSE) -> 39.0392 | EB10: =VLOOKUP(A10,Estoque!B:N,13,FALSE) -> 0 | ED10: 10
A11: PRF10009 | B11: PERFIL U ENRIJ LQ 1,80 X 150 X 50 X 20 MM | AS11: 18.127 | AT11: 2.11 | AU11: 4.16 | AV11: 3.09 | AW11: 3.45 | AZ11: 3.755 | BB11: 0.505 | BC11: 11.428 | BD11: 3.14 | BE11: 4.12 | BF11: 2.595 | BG11: 10.875 | BH11: 5.68 | BK11: 5.45 | BL11: 2 | BN11: 1 | BO11: 7.305 | BP11: 0.5 | BT11: 4.356 | BU11: 3.03 | BV11: 0.965 | BX11: 2.03 | BY11: 0.45 | BZ11: 12.325 | CB11: 0.925 | CC11: 1.52 | CD11: 9.024 | CF11: 1.904 | CG11: 0.48 | CH11: 3.815 | CI11: 3.504 | CK11: 2 | CL11: 5.088 | CM11: 5.61 | CN11: 2 | CP11: 3.532 | CQ11: 5.82 | CR11: 8.363 | CS11: 9.492 | CT11: 3.851 | CU11: =IFERROR(VLOOKUP(A11,'fat-01-24'!A:C,3,FALSE),"") -> 7.587 | CV11: =IFERROR(VLOOKUP(A11,'fat-02-24'!A:C,3,FALSE),"") -> 3.843 | CW11: =IFERROR(VLOOKUP(A11,'fat-03-24'!A:C,3,FALSE),"") -> 14.417 | CX11: =IFERROR(VLOOKUP(A11,'fat-04-24'!A:C,3,FALSE),"") -> 1.104 | CY11: =IFERROR(VLOOKUP(A11,'fat-05-24'!A:C,3,FALSE),"") -> 8.788 | CZ11: =IFERROR(VLOOKUP(A11,'fat-06-24'!A:C,3,FALSE),"") -> 2 | DA11: =IFERROR(VLOOKUP(A11,'fat-07-24'!A:C,3,FALSE),"") -> 5.354 | DB11: =IFERROR(VLOOKUP(A11,'fat-08-24'!A:D,3,FALSE),"") -> 9.317 | DC11: =IFERROR(VLOOKUP(A11,'fat-09-24'!A:C,3,FALSE),"") -> 10.192 | DD11: =IFERROR(VLOOKUP(A11,'fat-10-24'!A:C,3,FALSE),"") -> 8.637 | DE11: =IFERROR(VLOOKUP(A11,'fat-11-24'!A:C,3,FALSE),"") -> 14.966 | DF11: =IFERROR(VLOOKUP(A11,'fat-12-24'!A:D,3,FALSE),"") -> 17.274 | DG11: =IFERROR(VLOOKUP(A11,'fat-01-25'!A:D,3,FALSE),"") -> 5.808 | DH11: =IFERROR(VLOOKUP(A11,'fat-02-25'!A:D,3,FALSE),"") -> 16.392 | DI11: =IFERROR(VLOOKUP(A11,'fat-03-25'!A:C,3,FALSE),"") -> 6.436 | DJ11: =IFERROR(VLOOKUP(A11,'fat-04-25'!A:C,3,FALSE),"") -> 11.081 | DK11: =IFERROR(VLOOKUP(A11,'fat-02-25'!A:C,3,FALSE),"") -> 16.392 | DL11: =IFERROR(VLOOKUP(A11,'fat-06-25'!A:C,3,FALSE),"") -> 6.779 | DM11: =IFERROR(VLOOKUP(A11,'fat-05-25'!A:C,3,FALSE),"") -> 6.916 | DN11: =IFERROR(VLOOKUP(A11,'fat-08-25'!A:C,3,FALSE),"") -> 8.871 | DO11: =IFERROR(VLOOKUP(A11,'fat-09-25'!A:C,3,FALSE),"") -> 7.994 | DP11: =IFERROR(VLOOKUP(A11,'fat-10-25'!A:C,3,FALSE),"") -> 0 | DQ11: =IFERROR(VLOOKUP(A11,'fat-11-25'!A:D,3,FALSE),"") -> 3.712 | DR11: =IFERROR(VLOOKUP(A11,'fat-12-25'!A:D,3,FALSE),"") -> 0.816 | DS11: =IFERROR(VLOOKUP(A11,'fat-01-26'!A:C,3,FALSE),"") -> 4.476 | DT11: =IFERROR(VLOOKUP(A11,'fat-02-26'!A:C,3,FALSE),"") -> 0.408 | DU11: =IFERROR(VLOOKUP(A11,'fat-03-26'!A:C,3,FALSE),"") -> 14.03 | DV11: =IFERROR(VLOOKUP(A11,'fat-04-26'!A:C,3,FALSE),"") -> 8.998 | DW11: =IFERROR(VLOOKUP(A11,'fat-05-26'!A:C,3,FALSE),"") -> 1.348 | DX11: =SUM(DR11:DW11)/6 -> 5.0126667 | DY11: =DX11/30*45 -> 7.519 | EA11: =VLOOKUP(A11,Estoque!B:I,8,FALSE) -> -5.1482 | EB11: =VLOOKUP(A11,Estoque!B:N,13,FALSE) -> 0 | ED11: 10
A12: PRF10010 | B12: PERFIL U ENRIJ LQ 2,00 X 50 X 25 X 10 MM | C12: 0.7027 | D12: 11.4746 | E12: 6.699 | F12: 4.08 | G12: 0.055 | H12: 7.533 | I12: 0.845 | J12: 0.04 | K12: 6.025 | L12: 19.335 | M12: 0.05 | N12: 4.766 | O12: 1.169 | P12: 8.82 | Q12: 14.515 | R12: 1.395 | S12: 0.128 | T12: 0.14 | U12: 9.2472 | V12: 3.3114 | W12: 0.406 | X12: 2.867 | Y12: -0.915 | Z12: 9.625 | AA12: 1.039 | AB12: 0.436 | AC12: 0.195 | AD12: 0.029 | AE12: 2.06 | AF12: 1.063 | AG12: 3.296 | AH12: 0.619 | AI12: 6.923 | AJ12: 1.7425 | AK12: 6.4842 | AL12: 0.3 | AM12: 3.59 | AN12: 2.668 | AO12: 3.492 | AP12: 1.676 | AQ12: 6.66 | AR12: 12.48 | AS12: 0.94 | AT12: 3.412 | AU12: 14.309 | AV12: 22.529 | AW12: 10.124 | AX12: 0.475 | AY12: 7.741 | AZ12: 12.2808 | BA12: 8.214 | BB12: 8.352 | BC12: 21.378 | BD12: 23.723 | BE12: 21.4078 | BF12: 29.2537 | BG12: 25.13 | BH12: 8.239 | BI12: 40.898 | BK12: 13.21 | BL12: 72.26 | BM12: 26.6368 | BN12: 10.973 | BO12: 5.395 | BP12: 1.133 | BQ12: 4.256 | BR12: 0.893 | BS12: 1.124 | BT12: 2.131 | BU12: 3.463 | BV12: 0.285 | BW12: 1.498 | BX12: 3.434 | BY12: 7.104 | BZ12: 0.902 | CA12: 1.7738 | CB12: 4.8138 | CC12: 3.354 | CD12: 4.6602 | CE12: 2.636 | CF12: 10.2596 | CG12: 6.7147 | CH12: 24.9175 | CI12: 6.7818 | CJ12: 6.2274 | CK12: 5.276 | CL12: 5.8338 | CM12: 4.9032 | CN12: 4.7609 | CO12: 2.1495 | CP12: 3.0998 | CQ12: 12.7444 | CR12: 5.977 | CS12: 2.9274 | CT12: 6.7803 | CU12: =IFERROR(VLOOKUP(A12,'fat-01-24'!A:C,3,FALSE),"") -> 7.4436 | CV12: =IFERROR(VLOOKUP(A12,'fat-02-24'!A:C,3,FALSE),"") -> 4.7399 | CW12: =IFERROR(VLOOKUP(A12,'fat-03-24'!A:C,3,FALSE),"") -> 3.227 | CX12: =IFERROR(VLOOKUP(A12,'fat-04-24'!A:C,3,FALSE),"") -> 8.62799 | CY12: =IFERROR(VLOOKUP(A12,'fat-05-24'!A:C,3,FALSE),"") -> 10.2173 | CZ12: =IFERROR(VLOOKUP(A12,'fat-06-24'!A:C,3,FALSE),"") -> 4.7609 | DA12: =IFERROR(VLOOKUP(A12,'fat-07-24'!A:C,3,FALSE),"") -> 4.9385 | DB12: =IFERROR(VLOOKUP(A12,'fat-08-24'!A:D,3,FALSE),"") -> 9.0419 | DC12: =IFERROR(VLOOKUP(A12,'fat-09-24'!A:C,3,FALSE),"") -> 8.3887 | DD12: =IFERROR(VLOOKUP(A12,'fat-10-24'!A:C,3,FALSE),"") -> 13.4037 | DE12: =IFERROR(VLOOKUP(A12,'fat-11-24'!A:C,3,FALSE),"") -> 7.3144 | DF12: =IFERROR(VLOOKUP(A12,'fat-12-24'!A:D,3,FALSE),"") -> 7.7526 | DG12: =IFERROR(VLOOKUP(A12,'fat-01-25'!A:D,3,FALSE),"") -> 1.5067 | DH12: =IFERROR(VLOOKUP(A12,'fat-02-25'!A:D,3,FALSE),"") -> 10.5232 | DI12: =IFERROR(VLOOKUP(A12,'fat-03-25'!A:C,3,FALSE),"") -> 0.097 | DJ12: =IFERROR(VLOOKUP(A12,'fat-04-25'!A:C,3,FALSE),"") -> 6.6845 | DK12: =IFERROR(VLOOKUP(A12,'fat-02-25'!A:C,3,FALSE),"") -> 10.5232 | DL12: =IFERROR(VLOOKUP(A12,'fat-06-25'!A:C,3,FALSE),"") -> 7.9242 | DM12: =IFERROR(VLOOKUP(A12,'fat-05-25'!A:C,3,FALSE),"") -> 5.5293 | DN12: =IFERROR(VLOOKUP(A12,'fat-08-25'!A:C,3,FALSE),"") -> 3.5106 | DO12: =IFERROR(VLOOKUP(A12,'fat-09-25'!A:C,3,FALSE),"") -> 9.7847 | DP12: =IFERROR(VLOOKUP(A12,'fat-10-25'!A:C,3,FALSE),"") -> 4.137 | DQ12: =IFERROR(VLOOKUP(A12,'fat-11-25'!A:D,3,FALSE),"") -> 4.5247 | DR12: =IFERROR(VLOOKUP(A12,'fat-12-25'!A:D,3,FALSE),"") -> 3.2557 | DS12: =IFERROR(VLOOKUP(A12,'fat-01-26'!A:C,3,FALSE),"") -> 3.0116 | DT12: =IFERROR(VLOOKUP(A12,'fat-02-26'!A:C,3,FALSE),"") -> 13.8035 | DU12: =IFERROR(VLOOKUP(A12,'fat-03-26'!A:C,3,FALSE),"") -> 8.7864 | DV12: =IFERROR(VLOOKUP(A12,'fat-04-26'!A:C,3,FALSE),"") -> 3.362 | DW12: =IFERROR(VLOOKUP(A12,'fat-05-26'!A:C,3,FALSE),"") -> 2.8026 | DX12: =SUM(DR12:DW12)/6 -> 5.8369667 | DY12: =DX12/30*45 -> 8.75545 | EA12: =VLOOKUP(A12,Estoque!B:I,8,FALSE) -> 1.6597 | EB12: =VLOOKUP(A12,Estoque!B:N,13,FALSE) -> 5 | EC12: 40
A13: PRF10020 | B13: PERFIL U ENRIJ LQ 2,00 X 75 X 40 X 15 MM | C13: 10.0395 | D13: 20.6838 | E13: 42.6004 | F13: 28.8644 | G13: 5.436 | H13: 8.17 | I13: 14.8488 | J13: 10.841 | K13: 33.5726 | L13: 9.7562 | M13: 6.216 | N13: 4.072 | O13: 8.021 | P13: 7.2999 | Q13: 12.041 | R13: 0.327 | S13: 10.244 | T13: 4.544 | U13: 13.569 | V13: 9.979 | W13: 4.863 | X13: 11.816 | Y13: 13.121 | Z13: 0.886 | AA13: 22.801 | AB13: 2.6871 | AC13: 4.307 | AD13: 2.326 | AE13: 4.568 | AF13: 5.925 | AG13: 4.744 | AH13: 11.288 | AI13: 21.335 | AJ13: 15.372 | AK13: 12.964 | AL13: 9.162 | AM13: 13.364 | AN13: 18.7309 | AO13: 20.365 | AP13: 5.723 | AQ13: 10.7747 | AR13: 21.538 | AS13: 12.763 | AT13: 30.014 | AU13: 60.81 | AV13: 37.453 | AW13: 27.648 | AX13: 27.221 | AY13: 27.441 | AZ13: 21.776 | BA13: 59.237 | BB13: 39.342 | BC13: 34.496 | BD13: 49.978 | BE13: 27.688 | BF13: 45.433 | BG13: 102.263 | BH13: 29.5354 | BI13: 38.405 | BJ13: 80.201 | BK13: 106.115 | BL13: 46.366 | BM13: 42.633 | BN13: 28.0923 | BO13: 63.0904 | BP13: 59.324 | BQ13: 31.201 | BR13: 32.2971 | BS13: 29.4369 | BT13: 17.4299 | BU13: 14.768 | BV13: 19.4507 | BW13: 88.0218 | BX13: 42.816 | BY13: 41.5403 | BZ13: 17.002 | CA13: 23.084 | CB13: 48.457 | CC13: 18.7015 | CD13: 30.6018 | CE13: 60.78 | CF13: 69.954 | CG13: 39.1526 | CH13: 79.8729 | CI13: 55.017401 | CJ13: 11.4612 | CK13: 18.2402 | CL13: 25.1202 | CM13: 13.6146 | CN13: 14.7674 | CO13: 12.9231 | CP13: 46.6387 | CQ13: 34.7757 | CR13: 23.0289 | CS13: 37.6207 | CT13: 23.9017 | CU13: =IFERROR(VLOOKUP(A13,'fat-01-24'!A:C,3,FALSE),"") -> 26.3324 | CV13: =IFERROR(VLOOKUP(A13,'fat-02-24'!A:C,3,FALSE),"") -> 19.9657 | CW13: =IFERROR(VLOOKUP(A13,'fat-03-24'!A:C,3,FALSE),"") -> 34.8512 | CX13: =IFERROR(VLOOKUP(A13,'fat-04-24'!A:C,3,FALSE),"") -> 14.3273 | CY13: =IFERROR(VLOOKUP(A13,'fat-05-24'!A:C,3,FALSE),"") -> 26.4497 | CZ13: =IFERROR(VLOOKUP(A13,'fat-06-24'!A:C,3,FALSE),"") -> 14.7674 | DA13: =IFERROR(VLOOKUP(A13,'fat-07-24'!A:C,3,FALSE),"") -> 17.3697 | DB13: =IFERROR(VLOOKUP(A13,'fat-08-24'!A:D,3,FALSE),"") -> 20.0927 | DC13: =IFERROR(VLOOKUP(A13,'fat-09-24'!A:C,3,FALSE),"") -> 52.4029 | DD13: =IFERROR(VLOOKUP(A13,'fat-10-24'!A:C,3,FALSE),"") -> 27.8608 | DE13: =IFERROR(VLOOKUP(A13,'fat-11-24'!A:C,3,FALSE),"") -> 17.8887 | DF13: =IFERROR(VLOOKUP(A13,'fat-12-24'!A:D,3,FALSE),"") -> 6.9305 | DG13: =IFERROR(VLOOKUP(A13,'fat-01-25'!A:D,3,FALSE),"") -> 41.2182 | DH13: =IFERROR(VLOOKUP(A13,'fat-02-25'!A:D,3,FALSE),"") -> 18.944 | DI13: =IFERROR(VLOOKUP(A13,'fat-03-25'!A:C,3,FALSE),"") -> 15.949 | DJ13: =IFERROR(VLOOKUP(A13,'fat-04-25'!A:C,3,FALSE),"") -> 0.2058 | DK13: =IFERROR(VLOOKUP(A13,'fat-02-25'!A:C,3,FALSE),"") -> 18.944 | DL13: =IFERROR(VLOOKUP(A13,'fat-06-25'!A:C,3,FALSE),"") -> 21.022 | DM13: =IFERROR(VLOOKUP(A13,'fat-05-25'!A:C,3,FALSE),"") -> 24.7971 | DN13: =IFERROR(VLOOKUP(A13,'fat-08-25'!A:C,3,FALSE),"") -> 49.2417 | DO13: =IFERROR(VLOOKUP(A13,'fat-09-25'!A:C,3,FALSE),"") -> 40.7301 | DP13: =IFERROR(VLOOKUP(A13,'fat-10-25'!A:C,3,FALSE),"") -> 27.8852 | DQ13: =IFERROR(VLOOKUP(A13,'fat-11-25'!A:D,3,FALSE),"") -> 5.9969 | DR13: =IFERROR(VLOOKUP(A13,'fat-12-25'!A:D,3,FALSE),"") -> 6.6341 | DS13: =IFERROR(VLOOKUP(A13,'fat-01-26'!A:C,3,FALSE),"") -> 35.1389 | DT13: =IFERROR(VLOOKUP(A13,'fat-02-26'!A:C,3,FALSE),"") -> 16.3042 | DU13: =IFERROR(VLOOKUP(A13,'fat-03-26'!A:C,3,FALSE),"") -> 36.305 | DV13: =IFERROR(VLOOKUP(A13,'fat-04-26'!A:C,3,FALSE),"") -> 32.1003 | DW13: =IFERROR(VLOOKUP(A13,'fat-05-26'!A:C,3,FALSE),"") -> 34.7198 | DX13: =SUM(DR13:DW13)/6 -> 26.86705 | DY13: =DX13/30*45 -> 40.300575 | DZ13: 12 | EA13: =VLOOKUP(A13,Estoque!B:I,8,FALSE) -> 18.3426 | EB13: =VLOOKUP(A13,Estoque!B:N,13,FALSE) -> 20 | EC13: 70 | ED13: 70 | EE13: 70
A14: PRF10022 | B14: PERFIL U ENRIJ LQ 1,80 X 100 X 40 X 17 MM | D14: 12.725 | E14: 10.61 | F14: 7.53 | G14: 0.428 | H14: 3.405 | I14: 4.329 | J14: 0.49 | K14: 3.065 | N14: 1.08 | Q14: 2.065 | S14: 0.492 | T14: 0.34 | U14: 1.155 | V14: 2.266 | AC14: 1.685 | AD14: 2.06 | AE14: 5.189 | AF14: 2.084 | AG14: 3.99 | AI14: 12.21 | AJ14: 6.985 | AK14: 11.64 | AL14: 6.621 | AM14: 5.076 | AN14: 12.077 | AO14: 4.641 | AP14: 0.3 | AQ14: 8.485 | AR14: 3.74 | AS14: 9.695 | AT14: 27.878 | AU14: 13.416 | AV14: 11.26 | AW14: 0.868 | AX14: 4.476 | AY14: 8.246 | AZ14: 17.56 | BA14: 9.635 | BB14: 10.655 | BC14: 8.822 | BD14: 6.94 | BE14: 22.88 | BF14: 0.846 | BH14: 0.64 | BI14: 35.803 | BJ14: 29.415 | BK14: 14.225 | BL14: 3.146 | BM14: 22.935 | BN14: 4.635 | BO14: 2.725 | BP14: 15.013 | BQ14: 1.42 | BR14: 0.195 | BS14: 5.942 | BT14: 7.003 | BU14: 6.375 | BV14: 7.925 | BW14: 4.277 | BX14: 2.87 | BY14: 2.205 | BZ14: 20.884 | CA14: 3.186 | CB14: 2.436 | CC14: 0.875 | CD14: 9.611 | CE14: 12.268 | CF14: 1.217 | CG14: 17.498 | CH14: 20.16 | CI14: 4.944 | CJ14: 11.144 | CK14: 12.484 | CL14: 2.142 | CM14: 13.48 | CN14: 5.792 | CO14: 4.512 | CP14: 3.011 | CQ14: 8.427 | CR14: 13.509 | CS14: 14.671 | CT14: 12.095 | CU14: =IFERROR(VLOOKUP(A14,'fat-01-24'!A:C,3,FALSE),"") -> 0.3992 | CV14: =IFERROR(VLOOKUP(A14,'fat-02-24'!A:C,3,FALSE),"") -> 12.319 | CW14: =IFERROR(VLOOKUP(A14,'fat-03-24'!A:C,3,FALSE),"") -> 4.215 | CX14: =IFERROR(VLOOKUP(A14,'fat-04-24'!A:C,3,FALSE),"") -> 7.675 | CY14: =IFERROR(VLOOKUP(A14,'fat-05-24'!A:C,3,FALSE),"") -> 17.618 | CZ14: =IFERROR(VLOOKUP(A14,'fat-06-24'!A:C,3,FALSE),"") -> 5.792 | DA14: =IFERROR(VLOOKUP(A14,'fat-07-24'!A:C,3,FALSE),"") -> 22.708 | DB14: =IFERROR(VLOOKUP(A14,'fat-08-24'!A:D,3,FALSE),"") -> 19.151 | DC14: =IFERROR(VLOOKUP(A14,'fat-09-24'!A:C,3,FALSE),"") -> 5.64 | DD14: =IFERROR(VLOOKUP(A14,'fat-10-24'!A:C,3,FALSE),"") -> 36.634 | DE14: =IFERROR(VLOOKUP(A14,'fat-11-24'!A:C,3,FALSE),"") -> 17.451 | DF14: =IFERROR(VLOOKUP(A14,'fat-12-24'!A:D,3,FALSE),"") -> 18.722 | DG14: =IFERROR(VLOOKUP(A14,'fat-01-25'!A:D,3,FALSE),"") -> 28.914 | DH14: =IFERROR(VLOOKUP(A14,'fat-02-25'!A:D,3,FALSE),"") -> 26.941 | DI14: =IFERROR(VLOOKUP(A14,'fat-03-25'!A:C,3,FALSE),"") -> 28.716 | DJ14: =IFERROR(VLOOKUP(A14,'fat-04-25'!A:C,3,FALSE),"") -> 18.81 | DK14: =IFERROR(VLOOKUP(A14,'fat-02-25'!A:C,3,FALSE),"") -> 26.941 | DL14: =IFERROR(VLOOKUP(A14,'fat-06-25'!A:C,3,FALSE),"") -> 0.054 | DM14: =IFERROR(VLOOKUP(A14,'fat-05-25'!A:C,3,FALSE),"") -> 3.094 | DN14: =IFERROR(VLOOKUP(A14,'fat-08-25'!A:C,3,FALSE),"") -> 12.817 | DO14: =IFERROR(VLOOKUP(A14,'fat-09-25'!A:C,3,FALSE),"") -> 8.644 | DP14: =IFERROR(VLOOKUP(A14,'fat-10-25'!A:C,3,FALSE),"") -> 4.556 | DQ14: =IFERROR(VLOOKUP(A14,'fat-11-25'!A:D,3,FALSE),"") -> 19.966 | DR14: =IFERROR(VLOOKUP(A14,'fat-12-25'!A:D,3,FALSE),"") -> 8.52 | DS14: =IFERROR(VLOOKUP(A14,'fat-01-26'!A:C,3,FALSE),"") -> 19.214 | DT14: =IFERROR(VLOOKUP(A14,'fat-02-26'!A:C,3,FALSE),"") -> 9.417 | DU14: =IFERROR(VLOOKUP(A14,'fat-03-26'!A:C,3,FALSE),"") -> 14.4573 | DV14: =IFERROR(VLOOKUP(A14,'fat-04-26'!A:C,3,FALSE),"") -> 23.802 | DW14: =IFERROR(VLOOKUP(A14,'fat-05-26'!A:C,3,FALSE),"") -> 22.7414 | DX14: =SUM(DR14:DW14)/6 -> 16.358617 | DY14: =DX14/30*45 -> 24.537925 | EA14: =VLOOKUP(A14,Estoque!B:I,8,FALSE) -> -16.265 | EB14: =VLOOKUP(A14,Estoque!B:N,13,FALSE) -> 0 | EC14: 30 | ED14: 30
A15: PRF10030 | B15: PERFIL U ENRIJ LQ 2,00 X 100 X 50 X 17 MM | C15: 13.4377 | D15: 20.618 | E15: 18.119 | F15: 21.755 | G15: 4.967 | H15: 19.669 | I15: 4.375 | J15: 13.513 | K15: 10.6411 | L15: 10.108 | M15: 3.512 | N15: 15.134 | O15: 2.501 | P15: 12.3596 | Q15: 2.035 | R15: 1.495 | S15: 0.29 | T15: 5.45 | U15: 6.375 | V15: 7.234 | W15: 2.69 | X15: 6.829 | Y15: 11.853 | Z15: 2.955 | AA15: 6.334 | AB15: 23.314 | AC15: 2.912 | AD15: 0.64 | AE15: 2.904 | AF15: 6.199 | AG15: 3.82 | AH15: 5.562 | AI15: 9.974 | AJ15: 2.897 | AK15: 2.613 | AL15: 6.089 | AM15: 23.606 | AN15: 7.9806 | AO15: 2.9164 | AP15: 6.687 | AQ15: 14.699 | AR15: 9.502 | AS15: 5.505 | AT15: 7.572 | AU15: 13.83 | AV15: 8.571 | AW15: 22.033 | AX15: 8.393 | AY15: 1.626 | AZ15: 20.549 | BA15: 14.313 | BB15: 1.725 | BC15: 16.263 | BD15: 21.257 | BE15: 10.143 | BF15: 25.358 | BG15: 32.6771 | BH15: 6.883 | BI15: 29.146 | BJ15: 20.325 | BK15: 23.908 | BL15: 0.6354 | BM15: 16.0741 | BN15: 11.1534 | BO15: 33.694 | BP15: 6.17 | BQ15: 14.483 | BR15: 14.934 | BS15: 12.074 | BT15: 7.989 | BU15: 9.678 | BV15: 13.768 | BW15: 14.909 | BX15: 17.158 | BY15: 13.1766 | BZ15: 24.635 | CA15: 17.2002 | CB15: 13.9781 | CC15: 20.1324 | CD15: 0.1642 | CU15: =IFERROR(VLOOKUP(A15,'fat-01-24'!A:C,3,FALSE),"") | CV15: =IFERROR(VLOOKUP(A15,'fat-02-24'!A:C,3,FALSE),"") | CW15: =IFERROR(VLOOKUP(A15,'fat-03-24'!A:C,3,FALSE),"") | CX15: =IFERROR(VLOOKUP(A15,'fat-04-24'!A:C,3,FALSE),"") | CY15: =IFERROR(VLOOKUP(A15,'fat-05-24'!A:C,3,FALSE),"") | CZ15: =IFERROR(VLOOKUP(A15,'fat-06-24'!A:C,3,FALSE),"") | DA15: =IFERROR(VLOOKUP(A15,'fat-07-24'!A:C,3,FALSE),"") | DB15: =IFERROR(VLOOKUP(A15,'fat-08-24'!A:D,3,FALSE),"") | DC15: =IFERROR(VLOOKUP(A15,'fat-09-24'!A:C,3,FALSE),"") | DD15: =IFERROR(VLOOKUP(A15,'fat-10-24'!A:C,3,FALSE),"") | DE15: =IFERROR(VLOOKUP(A15,'fat-11-24'!A:C,3,FALSE),"") | DF15: =IFERROR(VLOOKUP(A15,'fat-12-24'!A:D,3,FALSE),"") | DG15: =IFERROR(VLOOKUP(A15,'fat-01-25'!A:D,3,FALSE),"") | DH15: =IFERROR(VLOOKUP(A15,'fat-02-25'!A:D,3,FALSE),"") | DI15: =IFERROR(VLOOKUP(A15,'fat-03-25'!A:C,3,FALSE),"") | DJ15: =IFERROR(VLOOKUP(A15,'fat-04-25'!A:C,3,FALSE),"") | DK15: =IFERROR(VLOOKUP(A15,'fat-02-25'!A:C,3,FALSE),"") | DL15: =IFERROR(VLOOKUP(A15,'fat-06-25'!A:C,3,FALSE),"") | DM15: =IFERROR(VLOOKUP(A15,'fat-05-25'!A:C,3,FALSE),"") | DN15: =IFERROR(VLOOKUP(A15,'fat-08-25'!A:C,3,FALSE),"") | DO15: =IFERROR(VLOOKUP(A15,'fat-09-25'!A:C,3,FALSE),"") | DP15: =IFERROR(VLOOKUP(A15,'fat-10-25'!A:C,3,FALSE),"") | DQ15: =IFERROR(VLOOKUP(A15,'fat-11-25'!A:D,3,FALSE),"") | DR15: =IFERROR(VLOOKUP(A15,'fat-12-25'!A:D,3,FALSE),"") | DS15: =IFERROR(VLOOKUP(A15,'fat-01-26'!A:C,3,FALSE),"") | DT15: =IFERROR(VLOOKUP(A15,'fat-02-26'!A:C,3,FALSE),"") | DU15: =IFERROR(VLOOKUP(A15,'fat-03-26'!A:C,3,FALSE),"") | DV15: =IFERROR(VLOOKUP(A15,'fat-04-26'!A:C,3,FALSE),"") | DW15: =IFERROR(VLOOKUP(A15,'fat-05-26'!A:C,3,FALSE),"") | DX15: =SUM(DR15:DW15)/6 -> 0 | DY15: =DX15/30*45 -> 0 | EB15: =VLOOKUP(A15,Estoque!B:N,13,FALSE) -> #N/A | EC15: 29 | ED15: 39
A16: PRF10032 | B16: PERFIL U ENRIJ LQ 2,00 X 100 X 50 X 17 MM | CD16: 6.9579 | CE16: 33.8945 | CF16: 21.369 | CG16: 19.503 | CH16: 14.227 | CI16: 15.5685 | CJ16: 23.191 | CK16: 32.414 | CL16: 42.4079 | CM16: 32.1625 | CN16: 20.3553 | CO16: 19.3873 | CP16: 18.939501 | CQ16: 18.4523 | CR16: 24.1305 | CS16: 16.8223 | CT16: 16.4346 | CU16: =IFERROR(VLOOKUP(A16,'fat-01-24'!A:C,3,FALSE),"") -> 14.0893 | CV16: =IFERROR(VLOOKUP(A16,'fat-02-24'!A:C,3,FALSE),"") -> 15.8775 | CW16: =IFERROR(VLOOKUP(A16,'fat-03-24'!A:C,3,FALSE),"") -> 9.805 | CX16: =IFERROR(VLOOKUP(A16,'fat-04-24'!A:C,3,FALSE),"") -> 22.436 | CY16: =IFERROR(VLOOKUP(A16,'fat-05-24'!A:C,3,FALSE),"") -> 12.394 | CZ16: =IFERROR(VLOOKUP(A16,'fat-06-24'!A:C,3,FALSE),"") -> 20.3553 | DA16: =IFERROR(VLOOKUP(A16,'fat-07-24'!A:C,3,FALSE),"") -> 32.578 | DB16: =IFERROR(VLOOKUP(A16,'fat-08-24'!A:D,3,FALSE),"") -> 7.3175 | DC16: =IFERROR(VLOOKUP(A16,'fat-09-24'!A:C,3,FALSE),"") -> 20.7935 | DD16: =IFERROR(VLOOKUP(A16,'fat-10-24'!A:C,3,FALSE),"") -> 15.2512 | DE16: =IFERROR(VLOOKUP(A16,'fat-11-24'!A:C,3,FALSE),"") -> 41.1898 | DF16: =IFERROR(VLOOKUP(A16,'fat-12-24'!A:D,3,FALSE),"") -> 14.9455 | DG16: =IFERROR(VLOOKUP(A16,'fat-01-25'!A:D,3,FALSE),"") -> 17.0965 | DH16: =IFERROR(VLOOKUP(A16,'fat-02-25'!A:D,3,FALSE),"") -> 16.1475 | DI16: =IFERROR(VLOOKUP(A16,'fat-03-25'!A:C,3,FALSE),"") -> 21.9315 | DJ16: =IFERROR(VLOOKUP(A16,'fat-04-25'!A:C,3,FALSE),"") -> 12.0025 | DK16: =IFERROR(VLOOKUP(A16,'fat-02-25'!A:C,3,FALSE),"") -> 16.1475 | DL16: =IFERROR(VLOOKUP(A16,'fat-06-25'!A:C,3,FALSE),"") -> 14.5945 | DM16: =IFERROR(VLOOKUP(A16,'fat-05-25'!A:C,3,FALSE),"") -> 15.77 | DN16: =IFERROR(VLOOKUP(A16,'fat-08-25'!A:C,3,FALSE),"") -> 10.2313 | DO16: =IFERROR(VLOOKUP(A16,'fat-09-25'!A:C,3,FALSE),"") -> 27.522 | DP16: =IFERROR(VLOOKUP(A16,'fat-10-25'!A:C,3,FALSE),"") -> 14.2885 | DQ16: =IFERROR(VLOOKUP(A16,'fat-11-25'!A:D,3,FALSE),"") -> 14.719 | DR16: =IFERROR(VLOOKUP(A16,'fat-12-25'!A:D,3,FALSE),"") -> 35.173 | DS16: =IFERROR(VLOOKUP(A16,'fat-01-26'!A:C,3,FALSE),"") -> 35.4804 | DT16: =IFERROR(VLOOKUP(A16,'fat-02-26'!A:C,3,FALSE),"") -> 27.7712 | DU16: =IFERROR(VLOOKUP(A16,'fat-03-26'!A:C,3,FALSE),"") -> 32.858 | DV16: =IFERROR(VLOOKUP(A16,'fat-04-26'!A:C,3,FALSE),"") -> 23.3148 | DW16: =IFERROR(VLOOKUP(A16,'fat-05-26'!A:C,3,FALSE),"") -> 58.3671 | DX16: =SUM(DR16:DW16)/6 -> 35.494083 | DY16: =DX16/30*45 -> 53.241125 | DZ16: 20 | EA16: =VLOOKUP(A16,Estoque!B:I,8,FALSE) -> -1.9119 | EB16: =VLOOKUP(A16,Estoque!B:N,13,FALSE) -> 45 | EC16: 30 | ED16: 40
A17: PRF10031 | B17: PERFIL U ENRIJ LQ 2,00 X 100 X 40 X 17 MM | C17: 4.906 | D17: 3.89 | E17: 7.172 | F17: 14.694 | G17: 6.555 | H17: 0.96 | I17: 10.143 | J17: 2.75 | K17: 0.38 | L17: 5.415 | M17: 0.623 | O17: 5.095 | P17: 0.836 | Q17: 4.8 | R17: 2.495 | S17: 3.956 | T17: 0.605 | U17: 5.87 | V17: 2.165 | W17: 13.852 | X17: 3.0442 | Y17: 1.624 | Z17: 3.401 | AA17: 0.55 | AB17: 1.571 | AD17: 0.965 | AE17: 1.16 | AF17: 0.929 | AG17: 5.204 | AH17: 5.017 | AI17: 7.837 | AJ17: 0.575 | AK17: 7.402 | AL17: 3.115 | AM17: 10.554 | AN17: 3.923 | AO17: 8.165 | AP17: 5.315 | AQ17: 8.2991 | AR17: 13.274 | AS17: 14.095 | AT17: 4.655 | AU17: 14.708 | AV17: 8.915 | AW17: 6.076 | AX17: 4.1276 | AY17: 17.089 | AZ17: 12.98 | BA17: 17.2736 | BB17: 14.549 | BC17: 21.696 | BD17: 12.865 | BE17: 16.778 | BF17: 25.732 | BG17: 33.438 | BH17: 1.511 | BI17: 44.173 | BJ17: 4.275 | BK17: 55.845 | BL17: 9.382 | BM17: 21.685 | BN17: 56.7004 | BO17: 20.977 | BP17: 15.2701 | BQ17: 20.429 | BR17: 22.698 | BS17: 8.936 | BT17: 10.98 | BU17: 7.161 | BV17: 12.55 | BW17: 16.709 | BX17: 15.0104 | BY17: 9.97 | BZ17: 17.695 | CA17: 24.48 | CB17: 12.624 | CC17: 7.845 | CD17: 44.5236 | CE17: 17.9208 | CF17: 14.4036 | CG17: 19.289 | CH17: 32.4444 | CI17: 25.4082 | CJ17: 11.8954 | CK17: 15.5686 | CL17: 20.3318 | CM17: 9.6628 | CN17: 9.536 | CO17: 5.5995 | CP17: 18.966 | CQ17: 21.2544 | CR17: 25.7868 | CS17: 25.0292 | CT17: 12.9191 | CU17: =IFERROR(VLOOKUP(A17,'fat-01-24'!A:C,3,FALSE),"") -> 15.1104 | CV17: =IFERROR(VLOOKUP(A17,'fat-02-24'!A:C,3,FALSE),"") -> 21.9397 | CW17: =IFERROR(VLOOKUP(A17,'fat-03-24'!A:C,3,FALSE),"") -> 13.8278 | CX17: =IFERROR(VLOOKUP(A17,'fat-04-24'!A:C,3,FALSE),"") -> 20.6722 | CY17: =IFERROR(VLOOKUP(A17,'fat-05-24'!A:C,3,FALSE),"") -> 15.5598 | CZ17: =IFERROR(VLOOKUP(A17,'fat-06-24'!A:C,3,FALSE),"") -> 9.536 | DA17: =IFERROR(VLOOKUP(A17,'fat-07-24'!A:C,3,FALSE),"") -> 27.7388 | DB17: =IFERROR(VLOOKUP(A17,'fat-08-24'!A:D,3,FALSE),"") -> 21.2696 | DC17: =IFERROR(VLOOKUP(A17,'fat-09-24'!A:C,3,FALSE),"") -> 17.0554 | DD17: =IFERROR(VLOOKUP(A17,'fat-10-24'!A:C,3,FALSE),"") -> 30.1826 | DE17: =IFERROR(VLOOKUP(A17,'fat-11-24'!A:C,3,FALSE),"") -> 22.7164 | DF17: =IFERROR(VLOOKUP(A17,'fat-12-24'!A:D,3,FALSE),"") -> 11.2486 | DG17: =IFERROR(VLOOKUP(A17,'fat-01-25'!A:D,3,FALSE),"") -> 33.2368 | DH17: =IFERROR(VLOOKUP(A17,'fat-02-25'!A:D,3,FALSE),"") -> 14.4178 | DI17: =IFERROR(VLOOKUP(A17,'fat-03-25'!A:C,3,FALSE),"") -> 13.128 | DJ17: =IFERROR(VLOOKUP(A17,'fat-04-25'!A:C,3,FALSE),"") -> 17.0078 | DK17: =IFERROR(VLOOKUP(A17,'fat-02-25'!A:C,3,FALSE),"") -> 14.4178 | DL17: =IFERROR(VLOOKUP(A17,'fat-06-25'!A:C,3,FALSE),"") -> 8.25332 | DM17: =IFERROR(VLOOKUP(A17,'fat-05-25'!A:C,3,FALSE),"") -> 11.877 | DN17: =IFERROR(VLOOKUP(A17,'fat-08-25'!A:C,3,FALSE),"") -> 4.8768 | DO17: =IFERROR(VLOOKUP(A17,'fat-09-25'!A:C,3,FALSE),"") -> 38.4666 | DP17: =IFERROR(VLOOKUP(A17,'fat-10-25'!A:C,3,FALSE),"") -> 4.2992 | DQ17: =IFERROR(VLOOKUP(A17,'fat-11-25'!A:D,3,FALSE),"") -> 27.8022 | DR17: =IFERROR(VLOOKUP(A17,'fat-12-25'!A:D,3,FALSE),"") -> 8.4872 | DS17: =IFERROR(VLOOKUP(A17,'fat-01-26'!A:C,3,FALSE),"") -> 12.6052 | DT17: =IFERROR(VLOOKUP(A17,'fat-02-26'!A:C,3,FALSE),"") -> 24.815 | DU17: =IFERROR(VLOOKUP(A17,'fat-03-26'!A:C,3,FALSE),"") -> 57.2584 | DV17: =IFERROR(VLOOKUP(A17,'fat-04-26'!A:C,3,FALSE),"") -> 20.743 | DW17: =IFERROR(VLOOKUP(A17,'fat-05-26'!A:C,3,FALSE),"") -> 25.6594 | DX17: =SUM(DR17:DW17)/6 -> 24.928033 | DY17: =DX17/30*45 -> 37.39205 | EA17: =VLOOKUP(A17,Estoque!B:I,8,FALSE) -> -6.6426 | EB17: =VLOOKUP(A17,Estoque!B:N,13,FALSE) -> 20 | EC17: 45 | ED17: 40
A18: PRF10040 | B18: PERFIL U ENRIJ LQ 2,00 X 127 X 50 X 17 MM | C18: 8.406 | D18: 2.945 | E18: 10.13 | F18: 3.585 | G18: 8.43 | H18: 2.715 | I18: 8.34 | J18: 3.535 | K18: 7.733 | L18: 13.671 | M18: 2.805 | N18: 3.159 | O18: 10.538 | P18: 7.136 | Q18: 3.48 | R18: 1.545 | S18: 15.939 | T18: 0.187 | U18: 2.854 | V18: 4.135 | W18: 1.762 | X18: 2.104 | Y18: 5.744 | Z18: 0.762 | AA18: 6.85 | AB18: 3.56 | AC18: 1.84 | AD18: 1.461 | AF18: 0.092 | AG18: 6.046 | AH18: 10.734 | AI18: 5.395 | AJ18: 0.325 | AK18: 7.124 | AL18: 8.012 | AM18: 9.857 | AN18: 2.084 | AO18: 9.106 | AP18: 2.22 | AQ18: 0.269 | AR18: 4.67 | AS18: 6.858 | AT18: 9.625 | AU18: 8.551 | AV18: 1.863 | AW18: 9.101 | AX18: 4.638 | AY18: 2.135 | AZ18: 9.754 | BA18: 5.778 | BB18: 0.09 | BC18: 3.885 | BD18: 0.73 | BE18: 3.214 | BF18: 3.96 | BG18: 7.335 | BH18: 21.12 | BI18: 1 | BJ18: 19.323 | BK18: 10.1449 | BL18: 18.662 | BM18: 45.985 | BN18: 4.933 | BO18: 7.324 | BP18: 8.774 | BQ18: 37.791 | BR18: 23.034 | BS18: 7.7789 | BT18: 8.058 | BU18: 15.152 | BV18: 17.7765 | BW18: 33.4634 | BX18: 12.635 | BY18: 43.814 | BZ18: 21.908 | CA18: 16.19 | CB18: 16.057 | CC18: 16.1712 | CD18: 12.8071 | CE18: 11.4579 | CF18: 39.1403 | CG18: 9.7247 | CH18: 30.1499 | CI18: 36.3434 | CJ18: 8.2707 | CK18: 16.9277 | CL18: 4.4188 | CM18: 6.5662 | CN18: 17.1164 | CO18: 6.3298 | CP18: 12.145 | CQ18: 8.3088 | CR18: 17.6574 | CS18: 15.5893 | CT18: 15.2804 | CU18: =IFERROR(VLOOKUP(A18,'fat-01-24'!A:C,3,FALSE),"") -> 5.1187 | CV18: =IFERROR(VLOOKUP(A18,'fat-02-24'!A:C,3,FALSE),"") -> 26.0798 | CW18: =IFERROR(VLOOKUP(A18,'fat-03-24'!A:C,3,FALSE),"") -> 4.192 | CX18: =IFERROR(VLOOKUP(A18,'fat-04-24'!A:C,3,FALSE),"") -> 30.7787 | CY18: =IFERROR(VLOOKUP(A18,'fat-05-24'!A:C,3,FALSE),"") -> 22.0374 | CZ18: =IFERROR(VLOOKUP(A18,'fat-06-24'!A:C,3,FALSE),"") -> 17.1164 | DA18: =IFERROR(VLOOKUP(A18,'fat-07-24'!A:C,3,FALSE),"") -> 17.2623 | DB18: =IFERROR(VLOOKUP(A18,'fat-08-24'!A:D,3,FALSE),"") -> 10.0335 | DC18: =IFERROR(VLOOKUP(A18,'fat-09-24'!A:C,3,FALSE),"") -> 27.4401 | DD18: =IFERROR(VLOOKUP(A18,'fat-10-24'!A:C,3,FALSE),"") -> 29.354 | DE18: =IFERROR(VLOOKUP(A18,'fat-11-24'!A:C,3,FALSE),"") -> 23.5494 | DF18: =IFERROR(VLOOKUP(A18,'fat-12-24'!A:D,3,FALSE),"") -> 32.6057 | DG18: =IFERROR(VLOOKUP(A18,'fat-01-25'!A:D,3,FALSE),"") -> 15.6259 | DH18: =IFERROR(VLOOKUP(A18,'fat-02-25'!A:D,3,FALSE),"") -> 25.8476 | DI18: =IFERROR(VLOOKUP(A18,'fat-03-25'!A:C,3,FALSE),"") -> 32.8549 | DJ18: =IFERROR(VLOOKUP(A18,'fat-04-25'!A:C,3,FALSE),"") -> 8.8242 | DK18: =IFERROR(VLOOKUP(A18,'fat-02-25'!A:C,3,FALSE),"") -> 25.8476 | DL18: =IFERROR(VLOOKUP(A18,'fat-06-25'!A:C,3,FALSE),"") -> 25.9701 | DM18: =IFERROR(VLOOKUP(A18,'fat-05-25'!A:C,3,FALSE),"") -> -0.04389924 | DN18: =IFERROR(VLOOKUP(A18,'fat-08-25'!A:C,3,FALSE),"") -> 17.9799 | DO18: =IFERROR(VLOOKUP(A18,'fat-09-25'!A:C,3,FALSE),"") -> 1.1416 | DP18: =IFERROR(VLOOKUP(A18,'fat-10-25'!A:C,3,FALSE),"") -> 33.8424 | DQ18: =IFERROR(VLOOKUP(A18,'fat-11-25'!A:D,3,FALSE),"") -> 16.1992 | DR18: =IFERROR(VLOOKUP(A18,'fat-12-25'!A:D,3,FALSE),"") -> 12.1753 | DS18: =IFERROR(VLOOKUP(A18,'fat-01-26'!A:C,3,FALSE),"") -> 16.3635 | DT18: =IFERROR(VLOOKUP(A18,'fat-02-26'!A:C,3,FALSE),"") -> 33.7117 | DU18: =IFERROR(VLOOKUP(A18,'fat-03-26'!A:C,3,FALSE),"") -> 6.0747 | DV18: =IFERROR(VLOOKUP(A18,'fat-04-26'!A:C,3,FALSE),"") -> 20.4807 | DW18: =IFERROR(VLOOKUP(A18,'fat-05-26'!A:C,3,FALSE),"") -> 25.5918 | DX18: =SUM(DR18:DW18)/6 -> 19.066283 | DY18: =DX18/30*45 -> 28.599425 | EA18: =VLOOKUP(A18,Estoque!B:I,8,FALSE) -> 45.1763 | EB18: =VLOOKUP(A18,Estoque!B:N,13,FALSE) -> 0 | EC18: 10 | ED18: 10
A19: PRF10050 | B19: PERFIL U ENRIJ LQ 2,00 X 150 X 60 X 20 MM | C19: 2.578 | D19: 7.785 | E19: 52.0155 | F19: 18.963 | G19: 0.864 | H19: 2.365 | I19: 16.814 | J19: 8.145 | K19: 4.2501 | L19: 8.648 | M19: 4.72 | N19: 8.577 | O19: 16.779 | P19: 17.597 | Q19: 13.291 | R19: 8.11 | S19: 1.9157 | T19: 3.937 | U19: 18.133 | V19: 4.12 | W19: 0.768 | X19: 9.417 | Y19: 3.476 | Z19: 7.957 | AA19: 6.4361 | AB19: 17.154 | AC19: 7.995 | AD19: 2.614 | AE19: 2.485 | AF19: 0.972 | AG19: 1.879 | AH19: 13.405 | AI19: 7.811 | AJ19: 5.508 | AK19: 4.461 | AL19: 6.651 | AM19: 14.69 | AN19: 14.632 | AO19: 12.754 | AP19: 9.111 | AQ19: 9.352 | AR19: 10.186 | AS19: 4.349 | AT19: 15.433 | AU19: 11.431 | AV19: 24.787 | AW19: 10.995 | AX19: 12.83 | AY19: 12.4777 | AZ19: 9.983 | BA19: 28.041 | BB19: 8.843 | BC19: 18.498 | BD19: 15.749 | BE19: 13.9938 | BF19: 17.741 | BG19: 37.5205 | BH19: 60.4731 | BI19: 2.158 | BJ19: 22.19 | BK19: 14.658 | BL19: 27.816 | BM19: 16.984 | BN19: 20.565 | BO19: 25.374 | BP19: 23.04 | BQ19: 31.428 | BR19: 24.44 | BS19: 12.722 | BT19: 23.388 | BU19: 12.087 | BV19: 27.239 | BW19: 51.391 | BX19: 15.776 | BY19: 27.143 | BZ19: 39.19 | CA19: 36.963 | CB19: 33.344 | CC19: 24.301 | CD19: 25.8574 | CE19: 36.8722 | CF19: 39.3992 | CG19: 17.9018 | CH19: 21.6596 | CI19: 25.1686 | CJ19: 10.598 | CK19: 51.2922 | CL19: 50.7692 | CM19: 15.7342 | CN19: 21.8506 | CO19: 41.6828 | CP19: 41.4914 | CQ19: 32.8674 | CR19: 37.0642 | CS19: 23.2348 | CT19: 21.0095 | CU19: =IFERROR(VLOOKUP(A19,'fat-01-24'!A:C,3,FALSE),"") -> 34.6566 | CV19: =IFERROR(VLOOKUP(A19,'fat-02-24'!A:C,3,FALSE),"") -> 7.375 | CW19: =IFERROR(VLOOKUP(A19,'fat-03-24'!A:C,3,FALSE),"") -> 27.7428 | CX19: =IFERROR(VLOOKUP(A19,'fat-04-24'!A:C,3,FALSE),"") -> 17.2548 | CY19: =IFERROR(VLOOKUP(A19,'fat-05-24'!A:C,3,FALSE),"") -> 9.249 | CZ19: =IFERROR(VLOOKUP(A19,'fat-06-24'!A:C,3,FALSE),"") -> 21.8506 | DA19: =IFERROR(VLOOKUP(A19,'fat-07-24'!A:C,3,FALSE),"") -> 28.4998 | DB19: =IFERROR(VLOOKUP(A19,'fat-08-24'!A:D,3,FALSE),"") -> 32.4524 | DC19: =IFERROR(VLOOKUP(A19,'fat-09-24'!A:C,3,FALSE),"") -> 38.4668 | DD19: =IFERROR(VLOOKUP(A19,'fat-10-24'!A:C,3,FALSE),"") -> 39.818 | DE19: =IFERROR(VLOOKUP(A19,'fat-11-24'!A:C,3,FALSE),"") -> 15.5028 | DF19: =IFERROR(VLOOKUP(A19,'fat-12-24'!A:D,3,FALSE),"") -> 10.1202 | DG19: =IFERROR(VLOOKUP(A19,'fat-01-25'!A:D,3,FALSE),"") -> 28.983 | DH19: =IFERROR(VLOOKUP(A19,'fat-02-25'!A:D,3,FALSE),"") -> 30.544 | DI19: =IFERROR(VLOOKUP(A19,'fat-03-25'!A:C,3,FALSE),"") -> 6.21 | DJ19: =IFERROR(VLOOKUP(A19,'fat-04-25'!A:C,3,FALSE),"") -> 34.7714 | DK19: =IFERROR(VLOOKUP(A19,'fat-02-25'!A:C,3,FALSE),"") -> 30.544 | DL19: =IFERROR(VLOOKUP(A19,'fat-06-25'!A:C,3,FALSE),"") -> 6.1786 | DM19: =IFERROR(VLOOKUP(A19,'fat-05-25'!A:C,3,FALSE),"") -> 15.9584 | DN19: =IFERROR(VLOOKUP(A19,'fat-08-25'!A:C,3,FALSE),"") -> 22.9866 | DO19: =IFERROR(VLOOKUP(A19,'fat-09-25'!A:C,3,FALSE),"") -> 33.2868 | DP19: =IFERROR(VLOOKUP(A19,'fat-10-25'!A:C,3,FALSE),"") -> 7.8648 | DQ19: =IFERROR(VLOOKUP(A19,'fat-11-25'!A:D,3,FALSE),"") -> 29.8076 | DR19: =IFERROR(VLOOKUP(A19,'fat-12-25'!A:D,3,FALSE),"") -> 25.6766 | DS19: =IFERROR(VLOOKUP(A19,'fat-01-26'!A:C,3,FALSE),"") -> 39.9128 | DT19: =IFERROR(VLOOKUP(A19,'fat-02-26'!A:C,3,FALSE),"") -> 29.5872 | DU19: =IFERROR(VLOOKUP(A19,'fat-03-26'!A:C,3,FALSE),"") -> 34.246 | DV19: =IFERROR(VLOOKUP(A19,'fat-04-26'!A:C,3,FALSE),"") -> 47.2026 | DW19: =IFERROR(VLOOKUP(A19,'fat-05-26'!A:C,3,FALSE),"") -> 27.3752 | DX19: =SUM(DR19:DW19)/6 -> 34.000067 | DY19: =DX19/30*45 -> 51.0001 | DZ19: 20 | EA19: =VLOOKUP(A19,Estoque!B:I,8,FALSE) -> 28.0492 | EB19: =VLOOKUP(A19,Estoque!B:N,13,FALSE) -> 20 | EC19: 40
A20: PRF10051 | B20: PERFIL U ENRIJ LQ 2,00 X 150 X 50 X 20 MM | AU20: 8.642 | AV20: 6.923 | AW20: 6.03 | AX20: 3.1 | AY20: 5.272 | AZ20: 0.935 | BA20: 13.221 | BB20: 1.6678 | BC20: 6.73 | BD20: 1.741 | BE20: 4.775 | BG20: 27.079 | BH20: 46.416 | BI20: 7.1486 | BJ20: 7.664 | BK20: 6.986 | BL20: 14.942 | BM20: 3.383 | BN20: 2.37 | BO20: 2.64 | BP20: 4.781 | BQ20: 17.237 | BR20: 16.841 | BT20: 6.17 | BU20: 2.175 | BV20: 4.344 | BW20: 1.298 | BX20: 2.712 | BY20: 7.863 | BZ20: 6.555 | CA20: 6.14 | CB20: 3.94 | CC20: 4.615 | CD20: 12.183 | CE20: 7.183 | CF20: 17.029 | CG20: 6.942 | CH20: 12.794 | CI20: 1.794 | CJ20: 13.726 | CK20: 5.194 | CL20: 12.452 | CM20: 6.9278 | CN20: 8.045 | CO20: 1.376 | CP20: 12.734 | CQ20: 26.408 | CR20: 5.789 | CS20: 7.474 | CT20: 16.0872 | CU20: =IFERROR(VLOOKUP(A20,'fat-01-24'!A:C,3,FALSE),"") -> 3.559 | CV20: =IFERROR(VLOOKUP(A20,'fat-02-24'!A:C,3,FALSE),"") -> 13.9073 | CW20: =IFERROR(VLOOKUP(A20,'fat-03-24'!A:C,3,FALSE),"") -> 1.491 | CX20: =IFERROR(VLOOKUP(A20,'fat-04-24'!A:C,3,FALSE),"") -> 10.088 | CY20: =IFERROR(VLOOKUP(A20,'fat-05-24'!A:C,3,FALSE),"") -> 3.0708 | CZ20: =IFERROR(VLOOKUP(A20,'fat-06-24'!A:C,3,FALSE),"") -> 8.045 | DA20: =IFERROR(VLOOKUP(A20,'fat-07-24'!A:C,3,FALSE),"") -> 20.336 | DB20: =IFERROR(VLOOKUP(A20,'fat-08-24'!A:D,3,FALSE),"") -> 21.155 | DC20: =IFERROR(VLOOKUP(A20,'fat-09-24'!A:C,3,FALSE),"") -> 24.272 | DD20: =IFERROR(VLOOKUP(A20,'fat-10-24'!A:C,3,FALSE),"") -> 10.324 | DE20: =IFERROR(VLOOKUP(A20,'fat-11-24'!A:C,3,FALSE),"") -> 6.038 | DF20: =IFERROR(VLOOKUP(A20,'fat-12-24'!A:D,3,FALSE),"") -> 21.082 | DG20: =IFERROR(VLOOKUP(A20,'fat-01-25'!A:D,3,FALSE),"") -> 16.791 | DH20: =IFERROR(VLOOKUP(A20,'fat-02-25'!A:D,3,FALSE),"") -> 10.1 | DI20: =IFERROR(VLOOKUP(A20,'fat-03-25'!A:C,3,FALSE),"") -> 16.026 | DJ20: =IFERROR(VLOOKUP(A20,'fat-04-25'!A:C,3,FALSE),"") -> 25.0578 | DK20: =IFERROR(VLOOKUP(A20,'fat-02-25'!A:C,3,FALSE),"") -> 10.1 | DL20: =IFERROR(VLOOKUP(A20,'fat-06-25'!A:C,3,FALSE),"") -> 2.157 | DM20: =IFERROR(VLOOKUP(A20,'fat-05-25'!A:C,3,FALSE),"") -> 7.955 | DN20: =IFERROR(VLOOKUP(A20,'fat-08-25'!A:C,3,FALSE),"") -> 4.8222 | DO20: =IFERROR(VLOOKUP(A20,'fat-09-25'!A:C,3,FALSE),"") -> 15.757 | DP20: =IFERROR(VLOOKUP(A20,'fat-10-25'!A:C,3,FALSE),"") -> 16.245 | DQ20: =IFERROR(VLOOKUP(A20,'fat-11-25'!A:D,3,FALSE),"") -> 7.908 | DR20: =IFERROR(VLOOKUP(A20,'fat-12-25'!A:D,3,FALSE),"") -> 6.122 | DS20: =IFERROR(VLOOKUP(A20,'fat-01-26'!A:C,3,FALSE),"") -> 6.136 | DT20: =IFERROR(VLOOKUP(A20,'fat-02-26'!A:C,3,FALSE),"") -> 10.634 | DU20: =IFERROR(VLOOKUP(A20,'fat-03-26'!A:C,3,FALSE),"") -> 3.42 | DV20: =IFERROR(VLOOKUP(A20,'fat-04-26'!A:C,3,FALSE),"") -> 23.462 | DW20: =IFERROR(VLOOKUP(A20,'fat-05-26'!A:C,3,FALSE),"") -> 2.01 | DX20: =SUM(DR20:DW20)/6 -> 8.6306667 | DY20: =DX20/30*45 -> 12.946 | EA20: =VLOOKUP(A20,Estoque!B:I,8,FALSE) -> -10.7693 | EB20: =VLOOKUP(A20,Estoque!B:N,13,FALSE) -> 0 | EC20: 15
A21: PRF10060 | B21: PERFIL U ENRIJ LQ 2,00 X 200 X 75 X 20 MM | K21: 5.745 | Q21: 13.51 | R21: 6.838 | S21: 5.65 | V21: 5.333 | W21: 5.326 | X21: 6.645 | Y21: 28.135 | Z21: 2.0657 | AA21: 25.178 | AB21: 15.477 | AC21: 4.562 | AD21: 1.163 | AE21: 0.727 | AF21: 4.58 | AH21: 1.462 | AI21: 9.262 | AJ21: 2.465 | AK21: 5.461 | AL21: 9.504 | AM21: 1.783 | AN21: 2.117 | AO21: 6.659 | AP21: 7.073 | AQ21: 4.459 | AR21: 8.935 | AS21: 8.418 | AT21: 10.687 | AU21: 9.636 | AV21: 13.6252 | AW21: 2.785 | AX21: 30.395 | AY21: 7.007 | AZ21: 3.877 | BA21: 19.852 | BB21: 15.691 | BC21: 29.955 | BD21: 30.318 | BE21: -1.193 | BF21: 15.757 | BG21: 34.905 | BH21: 62.104 | BI21: 37.904 | BJ21: 10.8401 | BL21: 32.443 | BM21: 23.796 | BN21: 18.169 | BO21: 33.792 | BP21: 42.492 | BQ21: 34.158 | BR21: 25.296 | BS21: 8.77 | BT21: 15.205 | BU21: 6.047 | BV21: 7.987 | BW21: 13.763 | BX21: 25.344 | BY21: 8.441 | BZ21: 7.8281 | CA21: 9.2701 | CB21: 11.659 | CC21: 7.86162 | CD21: 28.298 | CE21: 47.0335 | CF21: 14.2692 | CG21: 29.2144 | CH21: 41.7912 | CI21: 0.4368 | CJ21: 8.1376 | CK21: 12.2297 | CL21: 7.9888 | CM21: 19.9941 | CN21: 23.464 | CO21: 12.6268 | CP21: 5.583 | CQ21: 5.9634 | CR21: 7.916 | CS21: 20.0612 | CT21: 11.5388 | CU21: =IFERROR(VLOOKUP(A21,'fat-01-24'!A:C,3,FALSE),"") -> 16.0524 | CV21: =IFERROR(VLOOKUP(A21,'fat-02-24'!A:C,3,FALSE),"") -> 10.6766 | CW21: =IFERROR(VLOOKUP(A21,'fat-03-24'!A:C,3,FALSE),"") -> 13.7592 | CX21: =IFERROR(VLOOKUP(A21,'fat-04-24'!A:C,3,FALSE),"") -> 30.386 | CY21: =IFERROR(VLOOKUP(A21,'fat-05-24'!A:C,3,FALSE),"") -> 3.2008 | CZ21: =IFERROR(VLOOKUP(A21,'fat-06-24'!A:C,3,FALSE),"") -> 23.464 | DA21: =IFERROR(VLOOKUP(A21,'fat-07-24'!A:C,3,FALSE),"") -> 25.137653 | DB21: =IFERROR(VLOOKUP(A21,'fat-08-24'!A:D,3,FALSE),"") -> 5.1562 | DC21: =IFERROR(VLOOKUP(A21,'fat-09-24'!A:C,3,FALSE),"") -> 19.6774 | DD21: =IFERROR(VLOOKUP(A21,'fat-10-24'!A:C,3,FALSE),"") -> 15.8458 | DE21: =IFERROR(VLOOKUP(A21,'fat-11-24'!A:C,3,FALSE),"") -> 39.1194 | DF21: =IFERROR(VLOOKUP(A21,'fat-12-24'!A:D,3,FALSE),"") -> 15.9918 | DG21: =IFERROR(VLOOKUP(A21,'fat-01-25'!A:D,3,FALSE),"") -> 83.5348 | DH21: =IFERROR(VLOOKUP(A21,'fat-02-25'!A:D,3,FALSE),"") -> 2.9486 | DI21: =IFERROR(VLOOKUP(A21,'fat-03-25'!A:C,3,FALSE),"") -> 0 | DJ21: =IFERROR(VLOOKUP(A21,'fat-04-25'!A:C,3,FALSE),"") -> 25.1786 | DK21: =IFERROR(VLOOKUP(A21,'fat-02-25'!A:C,3,FALSE),"") -> 2.9486 | DL21: =IFERROR(VLOOKUP(A21,'fat-06-25'!A:C,3,FALSE),"") -> 11.3308 | DM21: =IFERROR(VLOOKUP(A21,'fat-05-25'!A:C,3,FALSE),"") -> 2.0448 | DN21: =IFERROR(VLOOKUP(A21,'fat-08-25'!A:C,3,FALSE),"") -> 14.7238 | DO21: =IFERROR(VLOOKUP(A21,'fat-09-25'!A:C,3,FALSE),"") -> 36.457 | DP21: =IFERROR(VLOOKUP(A21,'fat-10-25'!A:C,3,FALSE),"") -> 25.016 | DQ21: =IFERROR(VLOOKUP(A21,'fat-11-25'!A:D,3,FALSE),"") -> 6.1927 | DR21: =IFERROR(VLOOKUP(A21,'fat-12-25'!A:D,3,FALSE),"") -> 42.1196 | DS21: =IFERROR(VLOOKUP(A21,'fat-01-26'!A:C,3,FALSE),"") -> -18.4642 | DT21: =IFERROR(VLOOKUP(A21,'fat-02-26'!A:C,3,FALSE),"") -> 24.1128 | DU21: =IFERROR(VLOOKUP(A21,'fat-03-26'!A:C,3,FALSE),"") -> 35.8468 | DV21: =IFERROR(VLOOKUP(A21,'fat-04-26'!A:C,3,FALSE),"") -> 17.3264 | DW21: =IFERROR(VLOOKUP(A21,'fat-05-26'!A:C,3,FALSE),"") -> 1.9314 | DX21: =SUM(DR21:DW21)/6 -> 17.145467 | DY21: =DX21/30*45 -> 25.7182 | EA21: =VLOOKUP(A21,Estoque!B:I,8,FALSE) -> 29.505 | EB21: =VLOOKUP(A21,Estoque!B:N,13,FALSE) -> 0 | EC21: 40
A22: PRF10061 | B22: PERFIL U ENRIJ LQ 1,80 X 200 X 60 X 20 MM | F22: 1.049 | N22: 1.43 | AS22: 2.57 | AT22: 2.192 | BY22: 2.015 | CC22: 0.683 | CD22: 1 | CK22: 0.302 | CT22: 2 | CU22: =IFERROR(VLOOKUP(A22,'fat-01-24'!A:C,3,FALSE),"") | CV22: =IFERROR(VLOOKUP(A22,'fat-02-24'!A:C,3,FALSE),"") -> 1.13 | CW22: =IFERROR(VLOOKUP(A22,'fat-03-24'!A:C,3,FALSE),"") -> 3.385 | CX22: =IFERROR(VLOOKUP(A22,'fat-04-24'!A:C,3,FALSE),"") | CY22: =IFERROR(VLOOKUP(A22,'fat-05-24'!A:C,3,FALSE),"") -> 2.25 | CZ22: =IFERROR(VLOOKUP(A22,'fat-06-24'!A:C,3,FALSE),"") | DA22: =IFERROR(VLOOKUP(A22,'fat-07-24'!A:C,3,FALSE),"") | DB22: =IFERROR(VLOOKUP(A22,'fat-08-24'!A:D,3,FALSE),"") -> 5.466 | DC22: =IFERROR(VLOOKUP(A22,'fat-09-24'!A:C,3,FALSE),"") -> 4.329 | DD22: =IFERROR(VLOOKUP(A22,'fat-10-24'!A:C,3,FALSE),"") -> 3.711 | DE22: =IFERROR(VLOOKUP(A22,'fat-11-24'!A:C,3,FALSE),"") -> 9.48 | DF22: =IFERROR(VLOOKUP(A22,'fat-12-24'!A:D,3,FALSE),"") -> 2.314 | DG22: =IFERROR(VLOOKUP(A22,'fat-01-25'!A:D,3,FALSE),"") -> 0 | DH22: =IFERROR(VLOOKUP(A22,'fat-02-25'!A:D,3,FALSE),"") -> 8.014 | DI22: =IFERROR(VLOOKUP(A22,'fat-03-25'!A:C,3,FALSE),"") -> 1.524 | DJ22: =IFERROR(VLOOKUP(A22,'fat-04-25'!A:C,3,FALSE),"") -> 1.015 | DK22: =IFERROR(VLOOKUP(A22,'fat-02-25'!A:C,3,FALSE),"") -> 8.014 | DL22: =IFERROR(VLOOKUP(A22,'fat-06-25'!A:C,3,FALSE),"") -> 0 | DM22: =IFERROR(VLOOKUP(A22,'fat-05-25'!A:C,3,FALSE),"") -> 0 | DN22: =IFERROR(VLOOKUP(A22,'fat-08-25'!A:C,3,FALSE),"") -> 4.618 | DO22: =IFERROR(VLOOKUP(A22,'fat-09-25'!A:C,3,FALSE),"") -> 0 | DP22: =IFERROR(VLOOKUP(A22,'fat-10-25'!A:C,3,FALSE),"") -> 1 | DQ22: =IFERROR(VLOOKUP(A22,'fat-11-25'!A:D,3,FALSE),"") -> 0.174 | DR22: =IFERROR(VLOOKUP(A22,'fat-12-25'!A:D,3,FALSE),"") -> 3.024 | DS22: =IFERROR(VLOOKUP(A22,'fat-01-26'!A:C,3,FALSE),"") -> 2.204 | DT22: =IFERROR(VLOOKUP(A22,'fat-02-26'!A:C,3,FALSE),"") -> 10.148 | DU22: =IFERROR(VLOOKUP(A22,'fat-03-26'!A:C,3,FALSE),"") -> 6.012 | DV22: =IFERROR(VLOOKUP(A22,'fat-04-26'!A:C,3,FALSE),"") | DW22: =IFERROR(VLOOKUP(A22,'fat-05-26'!A:C,3,FALSE),"") -> 7.33 | DX22: =SUM(DR22:DW22)/6 -> 4.7863333 | DY22: =DX22/30*45 -> 7.1795 | EA22: =VLOOKUP(A22,Estoque!B:I,8,FALSE) -> 12.406 | EB22: =VLOOKUP(A22,Estoque!B:N,13,FALSE) -> 0
A23: PRF10062 | B23: PERFIL U ENRIJ LQ 2,00 X 200 X 60 X 20 MM | C23: 5.949 | D23: 0.649 | E23: 8.628 | F23: 8.552 | G23: 3.085 | H23: 0.605 | I23: 0.832 | J23: 1.11 | K23: 7.11 | L23: 2.34 | M23: 2.36 | Q23: 8.07 | R23: 12.275 | T23: 0.065 | U23: 0.795 | V23: 0.414 | W23: 0.734 | X23: 1.29 | AC23: 1.78 | AF23: 1.75 | AG23: 2.495 | AH23: 6.675 | AI23: 0.845 | AJ23: 1.525 | AK23: 0.912 | AM23: 2.905 | AN23: 4.785 | AO23: 13.307 | AP23: 4.127 | AR23: 8.4824 | AS23: 2.78 | AV23: -0.21 | AW23: 0.905 | AY23: 4.661 | BA23: 0.23 | BB23: 2.58 | BC23: 4.94 | BE23: 3.53 | BJ23: 11.97 | BK23: 0.66 | BL23: 0.96 | BN23: 6.664 | BO23: 15.924 | BP23: 33.23 | BQ23: 8.149 | BR23: 0.751 | BS23: 5.635 | BT23: 44.124 | BU23: 2.76 | BV23: 10.61 | BW23: 5.323 | BX23: 1.547 | BY23: 8.601 | CB23: 5.828 | CC23: 30.048 | CD23: 13.778 | CE23: 9.771 | CF23: 5.44 | CG23: 5.635 | CH23: 16.2089 | CI23: 21.146 | CJ23: 2.133 | CK23: 9.751 | CL23: 6.9388 | CM23: 7.7117 | CN23: 2.592 | CO23: 2.624 | CP23: 7.551 | CQ23: 21.068 | CR23: 6.247 | CS23: 3.36 | CT23: 9.8592 | CU23: =IFERROR(VLOOKUP(A23,'fat-01-24'!A:C,3,FALSE),"") -> 6.966 | CV23: =IFERROR(VLOOKUP(A23,'fat-02-24'!A:C,3,FALSE),"") -> 6.5152 | CW23: =IFERROR(VLOOKUP(A23,'fat-03-24'!A:C,3,FALSE),"") -> 9.987 | CX23: =IFERROR(VLOOKUP(A23,'fat-04-24'!A:C,3,FALSE),"") -> 6.348 | CY23: =IFERROR(VLOOKUP(A23,'fat-05-24'!A:C,3,FALSE),"") -> 2.052 | CZ23: =IFERROR(VLOOKUP(A23,'fat-06-24'!A:C,3,FALSE),"") -> 2.592 | DA23: =IFERROR(VLOOKUP(A23,'fat-07-24'!A:C,3,FALSE),"") -> 9.624 | DB23: =IFERROR(VLOOKUP(A23,'fat-08-24'!A:D,3,FALSE),"") -> 1.495 | DC23: =IFERROR(VLOOKUP(A23,'fat-09-24'!A:C,3,FALSE),"") -> 10.681 | DD23: =IFERROR(VLOOKUP(A23,'fat-10-24'!A:C,3,FALSE),"") -> 9.288 | DE23: =IFERROR(VLOOKUP(A23,'fat-11-24'!A:C,3,FALSE),"") -> 4.537 | DF23: =IFERROR(VLOOKUP(A23,'fat-12-24'!A:D,3,FALSE),"") -> 1.856 | DG23: =IFERROR(VLOOKUP(A23,'fat-01-25'!A:D,3,FALSE),"") -> 1.79 | DH23: =IFERROR(VLOOKUP(A23,'fat-02-25'!A:D,3,FALSE),"") -> 4.553 | DI23: =IFERROR(VLOOKUP(A23,'fat-03-25'!A:C,3,FALSE),"") -> 23.5578 | DJ23: =IFERROR(VLOOKUP(A23,'fat-04-25'!A:C,3,FALSE),"") -> 4.991 | DK23: =IFERROR(VLOOKUP(A23,'fat-02-25'!A:C,3,FALSE),"") -> 4.553 | DL23: =IFERROR(VLOOKUP(A23,'fat-06-25'!A:C,3,FALSE),"") -> 2.138 | DM23: =IFERROR(VLOOKUP(A23,'fat-05-25'!A:C,3,FALSE),"") -> 2.236 | DN23: =IFERROR(VLOOKUP(A23,'fat-08-25'!A:C,3,FALSE),"") -> 2.464 | DO23: =IFERROR(VLOOKUP(A23,'fat-09-25'!A:C,3,FALSE),"") -> 1.12 | DP23: =IFERROR(VLOOKUP(A23,'fat-10-25'!A:C,3,FALSE),"") -> 5.11 | DQ23: =IFERROR(VLOOKUP(A23,'fat-11-25'!A:D,3,FALSE),"") -> 8.4812 | DR23: =IFERROR(VLOOKUP(A23,'fat-12-25'!A:D,3,FALSE),"") -> 0 | DS23: =IFERROR(VLOOKUP(A23,'fat-01-26'!A:C,3,FALSE),"") -> 7.248 | DT23: =IFERROR(VLOOKUP(A23,'fat-02-26'!A:C,3,FALSE),"") -> 6.47 | DU23: =IFERROR(VLOOKUP(A23,'fat-03-26'!A:C,3,FALSE),"") | DV23: =IFERROR(VLOOKUP(A23,'fat-04-26'!A:C,3,FALSE),"") | DW23: =IFERROR(VLOOKUP(A23,'fat-05-26'!A:C,3,FALSE),"") -> 12.839 | DX23: =SUM(DR23:DW23)/6 -> 4.4261667 | DY23: =DX23/30*45 -> 6.63925 | EA23: =VLOOKUP(A23,Estoque!B:I,8,FALSE) -> 6.4486 | EB23: =VLOOKUP(A23,Estoque!B:N,13,FALSE) -> 15 | EC23: 10
A24: PRF10063 | B24: PERFIL U ENRIJ LQ 1,80 X 210 X 30 X 15 MM | L24: 0.94 | Q24: 2.415 | R24: -1.205 | U24: 4.6 | Z24: 0.895 | AA24: 2.1401 | AB24: 1.87 | CU24: =IFERROR(VLOOKUP(A24,'fat-01-24'!A:C,3,FALSE),"") | CV24: =IFERROR(VLOOKUP(A24,'fat-02-24'!A:C,3,FALSE),"") -> 2.03 | CW24: =IFERROR(VLOOKUP(A24,'fat-03-24'!A:C,3,FALSE),"") | CX24: =IFERROR(VLOOKUP(A24,'fat-04-24'!A:C,3,FALSE),"") | CY24: =IFERROR(VLOOKUP(A24,'fat-05-24'!A:C,3,FALSE),"") | CZ24: =IFERROR(VLOOKUP(A24,'fat-06-24'!A:C,3,FALSE),"") | DA24: =IFERROR(VLOOKUP(A24,'fat-07-24'!A:C,3,FALSE),"") -> 0.6804 | DB24: =IFERROR(VLOOKUP(A24,'fat-08-24'!A:D,3,FALSE),"") | DC24: =IFERROR(VLOOKUP(A24,'fat-09-24'!A:C,3,FALSE),"") | DD24: =IFERROR(VLOOKUP(A24,'fat-10-24'!A:C,3,FALSE),"") | DE24: =IFERROR(VLOOKUP(A24,'fat-11-24'!A:C,3,FALSE),"") | DF24: =IFERROR(VLOOKUP(A24,'fat-12-24'!A:D,3,FALSE),"") -> 0 | DG24: =IFERROR(VLOOKUP(A24,'fat-01-25'!A:D,3,FALSE),"") -> 1.9926 | DH24: =IFERROR(VLOOKUP(A24,'fat-02-25'!A:D,3,FALSE),"") -> 1.518 | DI24: =IFERROR(VLOOKUP(A24,'fat-03-25'!A:C,3,FALSE),"") -> 0 | DJ24: =IFERROR(VLOOKUP(A24,'fat-04-25'!A:C,3,FALSE),"") -> 0 | DK24: =IFERROR(VLOOKUP(A24,'fat-02-25'!A:C,3,FALSE),"") -> 1.518 | DL24: =IFERROR(VLOOKUP(A24,'fat-06-25'!A:C,3,FALSE),"") -> 2.015 | DM24: =IFERROR(VLOOKUP(A24,'fat-05-25'!A:C,3,FALSE),"") -> 1.02 | DN24: =IFERROR(VLOOKUP(A24,'fat-08-25'!A:C,3,FALSE),"") -> 0.99 | DO24: =IFERROR(VLOOKUP(A24,'fat-09-25'!A:C,3,FALSE),"") -> 0.7776 | DP24: =IFERROR(VLOOKUP(A24,'fat-10-25'!A:C,3,FALSE),"") -> 0.214 | DQ24: =IFERROR(VLOOKUP(A24,'fat-11-25'!A:D,3,FALSE),"") -> 0.58 | DR24: =IFERROR(VLOOKUP(A24,'fat-12-25'!A:D,3,FALSE),"") -> 0 | DS24: =IFERROR(VLOOKUP(A24,'fat-01-26'!A:C,3,FALSE),"") | DT24: =IFERROR(VLOOKUP(A24,'fat-02-26'!A:C,3,FALSE),"") | DU24: =IFERROR(VLOOKUP(A24,'fat-03-26'!A:C,3,FALSE),"") | DV24: =IFERROR(VLOOKUP(A24,'fat-04-26'!A:C,3,FALSE),"") | DW24: =IFERROR(VLOOKUP(A24,'fat-05-26'!A:C,3,FALSE),"") | DX24: =SUM(DR24:DW24)/6 -> 0 | DY24: =DX24/30*45 -> 0 | EA24: =VLOOKUP(A24,Estoque!B:I,8,FALSE) -> 0.0238 | EB24: =VLOOKUP(A24,Estoque!B:N,13,FALSE) -> 0
A25: PRF10065 | B25: PERFIL U ENRIJ LQ 2,00 X 210 X 30 X 15 MM | M25: 3.15 | T25: 0.51 | U25: 1.36 | V25: 0.08 | W25: 23.1 | Y25: 1.97 | AM25: 23.79 | AN25: 1.6 | AT25: 0.37 | AU25: 0.285 | BA25: 0.35 | BD25: 1.52 | BI25: 5.8 | BJ25: 2.745 | BK25: 0.965 | BM25: 1.18 | BP25: 3.674 | BU25: 5.011 | BW25: 4.1333 | BX25: 1.275 | BY25: 8.59 | CB25: 0.54 | CD25: 1.674 | CI25: 0.108 | CJ25: 9.072 | CK25: 3.186 | CL25: 0.54 | CM25: 7.561 | CO25: 3.078 | CP25: 1.809 | CQ25: 0.216 | CR25: 1.188 | CS25: 1.846 | CU25: =IFERROR(VLOOKUP(A25,'fat-01-24'!A:C,3,FALSE),"") -> 3.495 | CV25: =IFERROR(VLOOKUP(A25,'fat-02-24'!A:C,3,FALSE),"") -> 7.641 | CW25: =IFERROR(VLOOKUP(A25,'fat-03-24'!A:C,3,FALSE),"") -> 4 | CX25: =IFERROR(VLOOKUP(A25,'fat-04-24'!A:C,3,FALSE),"") -> 0.756 | CY25: =IFERROR(VLOOKUP(A25,'fat-05-24'!A:C,3,FALSE),"") -> 0.108 | CZ25: =IFERROR(VLOOKUP(A25,'fat-06-24'!A:C,3,FALSE),"") | DA25: =IFERROR(VLOOKUP(A25,'fat-07-24'!A:C,3,FALSE),"") -> 0.081 | DB25: =IFERROR(VLOOKUP(A25,'fat-08-24'!A:D,3,FALSE),"") | DC25: =IFERROR(VLOOKUP(A25,'fat-09-24'!A:C,3,FALSE),"") -> 0.2 | DD25: =IFERROR(VLOOKUP(A25,'fat-10-24'!A:C,3,FALSE),"") -> 0.155 | DE25: =IFERROR(VLOOKUP(A25,'fat-11-24'!A:C,3,FALSE),"") -> 0.156 | DF25: =IFERROR(VLOOKUP(A25,'fat-12-24'!A:D,3,FALSE),"") -> 6.678 | DG25: =IFERROR(VLOOKUP(A25,'fat-01-25'!A:D,3,FALSE),"") -> 0 | DH25: =IFERROR(VLOOKUP(A25,'fat-02-25'!A:D,3,FALSE),"") -> 11.286 | DI25: =IFERROR(VLOOKUP(A25,'fat-03-25'!A:C,3,FALSE),"") -> 0 | DJ25: =IFERROR(VLOOKUP(A25,'fat-04-25'!A:C,3,FALSE),"") -> 0.162 | DK25: =IFERROR(VLOOKUP(A25,'fat-02-25'!A:C,3,FALSE),"") -> 11.286 | DL25: =IFERROR(VLOOKUP(A25,'fat-06-25'!A:C,3,FALSE),"") -> 2.7 | DM25: =IFERROR(VLOOKUP(A25,'fat-05-25'!A:C,3,FALSE),"") -> 8.032 | DN25: =IFERROR(VLOOKUP(A25,'fat-08-25'!A:C,3,FALSE),"") -> 13.554 | DO25: =IFERROR(VLOOKUP(A25,'fat-09-25'!A:C,3,FALSE),"") -> 8.991 | DP25: =IFERROR(VLOOKUP(A25,'fat-10-25'!A:C,3,FALSE),"") -> 15.66 | DQ25: =IFERROR(VLOOKUP(A25,'fat-11-25'!A:D,3,FALSE),"") -> 0 | DR25: =IFERROR(VLOOKUP(A25,'fat-12-25'!A:D,3,FALSE),"") -> 15.828 | DS25: =IFERROR(VLOOKUP(A25,'fat-01-26'!A:C,3,FALSE),"") -> 2.25 | DT25: =IFERROR(VLOOKUP(A25,'fat-02-26'!A:C,3,FALSE),"") | DU25: =IFERROR(VLOOKUP(A25,'fat-03-26'!A:C,3,FALSE),"") -> 2.646 | DV25: =IFERROR(VLOOKUP(A25,'fat-04-26'!A:C,3,FALSE),"") -> 5.751 | DW25: =IFERROR(VLOOKUP(A25,'fat-05-26'!A:C,3,FALSE),"") -> 8.088 | DX25: =SUM(DR25:DW25)/6 -> 5.7605 | DY25: =DX25/30*45 -> 8.64075 | EA25: =VLOOKUP(A25,Estoque!B:I,8,FALSE) -> 14.947 | EB25: =VLOOKUP(A25,Estoque!B:N,13,FALSE) -> 0 | EC25: 10
A26: PRF10070 | B26: PERFIL U ENRIJ LQ 2,25 X 50 X 25 X 10 MM | J26: 0.034 | M26: 1.355 | N26: 0.023 | O26: 0.685 | P26: 1.0959 | Q26: 1.056 | S26: 0.265 | U26: 0.551 | AD26: 0.057 | AN26: 0.21 | AO26: 0.782 | AP26: 0.455 | AQ26: 0.465 | AU26: 0.011 | AW26: 0.405 | AZ26: 0.205 | BA26: 2.165 | BD26: 1.58 | BL26: 0.12 | BN26: 1.16 | BO26: 1.43 | BP26: 0.795 | BQ26: 0.28 | BS26: 0.585 | BU26: 0.83 | BV26: 1.17 | CB26: 0.0208 | CD26: 2.782 | CF26: 0.7895 | CG26: 1.0805 | CH26: 2 | CI26: 0.184 | CJ26: 1.725 | CK26: 1.2825 | CL26: 0.11 | CM26: 2.692 | CN26: 0.126 | CO26: 0.6435 | CP26: 0.322 | CQ26: 1.258 | CR26: 2.065 | CS26: 1.123 | CT26: 0.194 | CU26: =IFERROR(VLOOKUP(A26,'fat-01-24'!A:C,3,FALSE),"") -> 2.281 | CV26: =IFERROR(VLOOKUP(A26,'fat-02-24'!A:C,3,FALSE),"") -> 0.5 | CW26: =IFERROR(VLOOKUP(A26,'fat-03-24'!A:C,3,FALSE),"") -> 0.614 | CX26: =IFERROR(VLOOKUP(A26,'fat-04-24'!A:C,3,FALSE),"") -> 13.662 | CY26: =IFERROR(VLOOKUP(A26,'fat-05-24'!A:C,3,FALSE),"") | CZ26: =IFERROR(VLOOKUP(A26,'fat-06-24'!A:C,3,FALSE),"") -> 0.126 | DA26: =IFERROR(VLOOKUP(A26,'fat-07-24'!A:C,3,FALSE),"") -> 1.036 | DB26: =IFERROR(VLOOKUP(A26,'fat-08-24'!A:D,3,FALSE),"") -> 13.547 | DC26: =IFERROR(VLOOKUP(A26,'fat-09-24'!A:C,3,FALSE),"") -> 12.6845 | DD26: =IFERROR(VLOOKUP(A26,'fat-10-24'!A:C,3,FALSE),"") -> 0.3105 | DE26: =IFERROR(VLOOKUP(A26,'fat-11-24'!A:C,3,FALSE),"") -> 13.372 | DF26: =IFERROR(VLOOKUP(A26,'fat-12-24'!A:D,3,FALSE),"") -> 0.402 | DG26: =IFERROR(VLOOKUP(A26,'fat-01-25'!A:D,3,FALSE),"") -> 0.598 | DH26: =IFERROR(VLOOKUP(A26,'fat-02-25'!A:D,3,FALSE),"") -> 0.253 | DI26: =IFERROR(VLOOKUP(A26,'fat-03-25'!A:C,3,FALSE),"") -> 0 | DJ26: =IFERROR(VLOOKUP(A26,'fat-04-25'!A:C,3,FALSE),"") -> 1.115 | DK26: =IFERROR(VLOOKUP(A26,'fat-02-25'!A:C,3,FALSE),"") -> 0.253 | DL26: =IFERROR(VLOOKUP(A26,'fat-06-25'!A:C,3,FALSE),"") -> 0.667 | DM26: =IFERROR(VLOOKUP(A26,'fat-05-25'!A:C,3,FALSE),"") -> 0 | DN26: =IFERROR(VLOOKUP(A26,'fat-08-25'!A:C,3,FALSE),"") -> 6.5435 | DO26: =IFERROR(VLOOKUP(A26,'fat-09-25'!A:C,3,FALSE),"") -> 4.9607 | DP26: =IFERROR(VLOOKUP(A26,'fat-10-25'!A:C,3,FALSE),"") -> 0 | DQ26: =IFERROR(VLOOKUP(A26,'fat-11-25'!A:D,3,FALSE),"") -> 0 | DR26: =IFERROR(VLOOKUP(A26,'fat-12-25'!A:D,3,FALSE),"") -> 0.485 | DS26: =IFERROR(VLOOKUP(A26,'fat-01-26'!A:C,3,FALSE),"") | DT26: =IFERROR(VLOOKUP(A26,'fat-02-26'!A:C,3,FALSE),"") -> 0.8145 | DU26: =IFERROR(VLOOKUP(A26,'fat-03-26'!A:C,3,FALSE),"") -> 0.291 | DV26: =IFERROR(VLOOKUP(A26,'fat-04-26'!A:C,3,FALSE),"") -> 0.575 | DW26: =IFERROR(VLOOKUP(A26,'fat-05-26'!A:C,3,FALSE),"") -> 0.851 | DX26: =SUM(DR26:DW26)/6 -> 0.50275 | DY26: =DX26/30*45 -> 0.754125 | EA26: =VLOOKUP(A26,Estoque!B:I,8,FALSE) -> 7.9555 | EB26: =VLOOKUP(A26,Estoque!B:N,13,FALSE) -> 10
A27: PRF10080 | B27: PERFIL U ENRIJ LQ 2,25 X 75 X 40 X 15 MM | C27: 9.85 | D27: 5.115 | E27: 0.53 | F27: 5.665 | G27: 5.58 | H27: 1.015 | I27: 1.447 | J27: 9.318 | K27: 2.28 | L27: 0.262 | O27: 6.169 | Q27: 8.363 | S27: 2.03 | T27: 3.872 | U27: 2.792 | X27: 3.66 | Y27: 7.77 | Z27: 4.342 | AA27: 2.179 | AB27: 2.821 | AG27: 3.32 | AH27: 7.234 | AI27: 6.285 | AJ27: 3.131 | AK27: 2.652 | AL27: 2.412 | AM27: 3.013 | AN27: 3.366 | AO27: 4.554 | AP27: 9.177 | AQ27: 4.22 | AR27: 1.114 | AS27: 2.29 | AT27: 4.564 | AU27: 2.308 | AW27: 2.445 | AX27: 1.285 | AY27: 0.335 | AZ27: 7.921 | BB27: 7.415 | BC27: 1.711 | BD27: 6.14 | BE27: 0.233 | BF27: 3.458 | BG27: 4.165 | BH27: 0.11 | BI27: 1.138 | BJ27: 18.44 | BK27: 5.293 | BM27: 7.1332 | BN27: 1.493 | BO27: 7.443 | BP27: 0.948 | BQ27: 23.8858 | BR27: 0.14 | BS27: 4.25 | BT27: 7.892 | BU27: 3.625 | BV27: 1.84 | BW27: 3.976 | BX27: 2.22 | BY27: 8.0795 | BZ27: 1.4178 | CA27: 10.3915 | CB27: 3.284 | CC27: 9.6096 | CD27: 6.965 | CE27: 10.58 | CF27: 11.629 | CG27: 5.919 | CH27: 10.224 | CI27: 3.762 | CJ27: 11.892 | CK27: 4.9752 | CL27: 6.568 | CM27: 2.649 | CN27: 6.071 | CO27: 13.642 | CP27: 7.162 | CQ27: 11.612 | CR27: 23.447 | CS27: 8.103 | CT27: 12.538 | CU27: =IFERROR(VLOOKUP(A27,'fat-01-24'!A:C,3,FALSE),"") -> 5.817 | CV27: =IFERROR(VLOOKUP(A27,'fat-02-24'!A:C,3,FALSE),"") -> 4.211 | CW27: =IFERROR(VLOOKUP(A27,'fat-03-24'!A:C,3,FALSE),"") -> 10.611 | CX27: =IFERROR(VLOOKUP(A27,'fat-04-24'!A:C,3,FALSE),"") -> 11.9384 | CY27: =IFERROR(VLOOKUP(A27,'fat-05-24'!A:C,3,FALSE),"") -> 10.025 | CZ27: =IFERROR(VLOOKUP(A27,'fat-06-24'!A:C,3,FALSE),"") -> 6.071 | DA27: =IFERROR(VLOOKUP(A27,'fat-07-24'!A:C,3,FALSE),"") -> 10.918 | DB27: =IFERROR(VLOOKUP(A27,'fat-08-24'!A:D,3,FALSE),"") -> 6.438 | DC27: =IFERROR(VLOOKUP(A27,'fat-09-24'!A:C,3,FALSE),"") -> 7.46 | DD27: =IFERROR(VLOOKUP(A27,'fat-10-24'!A:C,3,FALSE),"") -> 10.329 | DE27: =IFERROR(VLOOKUP(A27,'fat-11-24'!A:C,3,FALSE),"") -> 10.558 | DF27: =IFERROR(VLOOKUP(A27,'fat-12-24'!A:D,3,FALSE),"") -> 10.44 | DG27: =IFERROR(VLOOKUP(A27,'fat-01-25'!A:D,3,FALSE),"") -> 1.504 | DH27: =IFERROR(VLOOKUP(A27,'fat-02-25'!A:D,3,FALSE),"") -> 1.584 | DI27: =IFERROR(VLOOKUP(A27,'fat-03-25'!A:C,3,FALSE),"") -> 16.958 | DJ27: =IFERROR(VLOOKUP(A27,'fat-04-25'!A:C,3,FALSE),"") -> 7.231 | DK27: =IFERROR(VLOOKUP(A27,'fat-02-25'!A:C,3,FALSE),"") -> 1.584 | DL27: =IFERROR(VLOOKUP(A27,'fat-06-25'!A:C,3,FALSE),"") -> 9.175 | DM27: =IFERROR(VLOOKUP(A27,'fat-05-25'!A:C,3,FALSE),"") -> 5.63 | DN27: =IFERROR(VLOOKUP(A27,'fat-08-25'!A:C,3,FALSE),"") -> 6.066 | DO27: =IFERROR(VLOOKUP(A27,'fat-09-25'!A:C,3,FALSE),"") -> 4.518 | DP27: =IFERROR(VLOOKUP(A27,'fat-10-25'!A:C,3,FALSE),"") -> 8.838 | DQ27: =IFERROR(VLOOKUP(A27,'fat-11-25'!A:D,3,FALSE),"") -> 10.827 | DR27: =IFERROR(VLOOKUP(A27,'fat-12-25'!A:D,3,FALSE),"") -> 4.908 | DS27: =IFERROR(VLOOKUP(A27,'fat-01-26'!A:C,3,FALSE),"") -> 3.758 | DT27: =IFERROR(VLOOKUP(A27,'fat-02-26'!A:C,3,FALSE),"") -> 6.678 | DU27: =IFERROR(VLOOKUP(A27,'fat-03-26'!A:C,3,FALSE),"") -> 10.568 | DV27: =IFERROR(VLOOKUP(A27,'fat-04-26'!A:C,3,FALSE),"") -> 16.556 | DW27: =IFERROR(VLOOKUP(A27,'fat-05-26'!A:C,3,FALSE),"") -> 13.912 | DX27: =SUM(DR27:DW27)/6 -> 9.3966667 | DY27: =DX27/30*45 -> 14.095 | EA27: =VLOOKUP(A27,Estoque!B:I,8,FALSE) -> 5.328 | EB27: =VLOOKUP(A27,Estoque!B:N,13,FALSE) -> 0
A28: PRF10090 | B28: PERFIL U ENRIJ LQ 2,25 X 100 X 50 X 17 MM | D28: 0.737 | E28: 7.631 | F28: 4.38 | H28: 3.075 | I28: 2.98 | J28: 0.09 | K28: 16.087 | L28: 2.125 | M28: 5.015 | N28: 6.052 | O28: 3.595 | P28: 0.114 | Q28: 0.272 | S28: 3.012 | T28: 4.465 | U28: 0.83 | V28: 2.586 | W28: 10.557 | X28: 10.046 | Z28: 3.335 | AA28: 6.675 | AB28: 9.76 | AC28: 0.3 | AD28: 3.34 | AE28: 0.775 | AF28: 2.285 | AG28: 6.045 | AH28: 3.267 | AI28: 4.97 | AJ28: 5.015 | AK28: 1.455 | AL28: 2.752 | AM28: 5.388 | AN28: 3.122 | AO28: 0.529 | AP28: 0.765 | AQ28: 0.311 | AR28: 7.8828 | AS28: 0.807 | AT28: 0.4 | AU28: 2.246 | AV28: 2.671 | AW28: 5.705 | AX28: 4.46 | AY28: 2.426 | AZ28: 4.949 | BA28: 2.969 | BB28: 2.609 | BC28: 3.952 | BD28: 2.259 | BE28: 3.53 | BF28: 30.517 | BG28: 10.199 | BH28: 1.207 | BI28: 5.295 | BJ28: 11.133 | BK28: 7.701 | BL28: 7.985 | BM28: 3.565 | BN28: 1.058 | BO28: 7.285 | BP28: 13.933 | BQ28: 7.253 | BR28: 3.512 | BS28: 1.496 | BT28: 1.723 | BU28: 2.187 | BV28: 3.179 | BW28: 7.884 | BX28: 4.878 | BY28: 10.092 | BZ28: 22.765 | CA28: 10.765 | CB28: 9.798 | CC28: 25.872 | CD28: 10.372 | CE28: 14.95 | CF28: 11.086 | CG28: 4.671 | CH28: 20.04 | CI28: 10.215 | CJ28: 7.334 | CK28: 9.364 | CM28: 14.674 | CN28: 1.265 | CO28: 6.634 | CP28: 6.762 | CQ28: 17.2124 | CR28: 5.63 | CS28: 15.5378 | CT28: 8.303 | CU28: =IFERROR(VLOOKUP(A28,'fat-01-24'!A:C,3,FALSE),"") -> 10.996 | CV28: =IFERROR(VLOOKUP(A28,'fat-02-24'!A:C,3,FALSE),"") -> 17.287 | CW28: =IFERROR(VLOOKUP(A28,'fat-03-24'!A:C,3,FALSE),"") -> 6.9334 | CX28: =IFERROR(VLOOKUP(A28,'fat-04-24'!A:C,3,FALSE),"") -> 5.174 | CY28: =IFERROR(VLOOKUP(A28,'fat-05-24'!A:C,3,FALSE),"") -> 4.286 | CZ28: =IFERROR(VLOOKUP(A28,'fat-06-24'!A:C,3,FALSE),"") -> 1.265 | DA28: =IFERROR(VLOOKUP(A28,'fat-07-24'!A:C,3,FALSE),"") -> 4.204 | DB28: =IFERROR(VLOOKUP(A28,'fat-08-24'!A:D,3,FALSE),"") -> 10.85 | DC28: =IFERROR(VLOOKUP(A28,'fat-09-24'!A:C,3,FALSE),"") -> 5.668 | DD28: =IFERROR(VLOOKUP(A28,'fat-10-24'!A:C,3,FALSE),"") -> 5.877 | DE28: =IFERROR(VLOOKUP(A28,'fat-11-24'!A:C,3,FALSE),"") -> 17.06 | DF28: =IFERROR(VLOOKUP(A28,'fat-12-24'!A:D,3,FALSE),"") -> 3.703 | DG28: =IFERROR(VLOOKUP(A28,'fat-01-25'!A:D,3,FALSE),"") -> 11.369 | DH28: =IFERROR(VLOOKUP(A28,'fat-02-25'!A:D,3,FALSE),"") -> 2.954 | DI28: =IFERROR(VLOOKUP(A28,'fat-03-25'!A:C,3,FALSE),"") -> 13.777 | DJ28: =IFERROR(VLOOKUP(A28,'fat-04-25'!A:C,3,FALSE),"") -> 1.311 | DK28: =IFERROR(VLOOKUP(A28,'fat-02-25'!A:C,3,FALSE),"") -> 2.954 | DL28: =IFERROR(VLOOKUP(A28,'fat-06-25'!A:C,3,FALSE),"") -> 1.38 | DM28: =IFERROR(VLOOKUP(A28,'fat-05-25'!A:C,3,FALSE),"") -> 0.644 | DN28: =IFERROR(VLOOKUP(A28,'fat-08-25'!A:C,3,FALSE),"") -> 20.434 | DO28: =IFERROR(VLOOKUP(A28,'fat-09-25'!A:C,3,FALSE),"") -> 12.5194 | DP28: =IFERROR(VLOOKUP(A28,'fat-10-25'!A:C,3,FALSE),"") -> 3.151 | DQ28: =IFERROR(VLOOKUP(A28,'fat-11-25'!A:D,3,FALSE),"") -> 1.288 | DR28: =IFERROR(VLOOKUP(A28,'fat-12-25'!A:D,3,FALSE),"") -> 9.752 | DS28: =IFERROR(VLOOKUP(A28,'fat-01-26'!A:C,3,FALSE),"") -> 7.39 | DT28: =IFERROR(VLOOKUP(A28,'fat-02-26'!A:C,3,FALSE),"") -> 4.474 | DU28: =IFERROR(VLOOKUP(A28,'fat-03-26'!A:C,3,FALSE),"") -> 5.606 | DV28: =IFERROR(VLOOKUP(A28,'fat-04-26'!A:C,3,FALSE),"") -> 3.402 | DW28: =IFERROR(VLOOKUP(A28,'fat-05-26'!A:C,3,FALSE),"") -> 3.3 | DX28: =SUM(DR28:DW28)/6 -> 5.654 | DY28: =DX28/30*45 -> 8.481 | DZ28: 5 | EA28: =VLOOKUP(A28,Estoque!B:I,8,FALSE) -> -0.2984 | EB28: =VLOOKUP(A28,Estoque!B:N,13,FALSE) -> 15
A29: PRF10091 | B29: PERFIL U ENRIJ LQ 2,25 X 100 X 40 X 17 MM | C29: 5.984 | D29: 2.975 | E29: 2.655 | F29: 1.745 | G29: 5.151 | I29: 2.92 | J29: 0.52 | K29: 0.286 | L29: 4.16 | M29: 0.964 | O29: 1.582 | T29: 0.024 | W29: 0.726 | X29: 0.102 | AA29: 8.92 | AC29: 2.22 | AE29: 4.47 | AG29: 1.556 | AH29: 1.67 | AI29: 0.54 | AJ29: 0.088 | AK29: 0.31 | AL29: 2.25 | AM29: 3.375 | AN29: 3.32 | AO29: 0.705 | AP29: 3.738 | AS29: 0.392 | AT29: 1.557 | AU29: 28.985 | AV29: 0.63 | AW29: 1.507 | AX29: 1.606 | AY29: 6.42 | AZ29: 1.494 | BA29: 0.331 | BB29: 6.395 | BD29: 1.335 | BE29: 3.47 | BG29: 5.205 | BH29: 0.375 | BI29: 10.655 | BK29: 3.995 | BL29: 4.46 | BM29: 2.639 | BO29: 0.24 | BP29: 1.68 | BQ29: 0.2 | BR29: 3.639 | BS29: 2.795 | BT29: 0.34 | BU29: 3.545 | BW29: 3.08 | BY29: 4.415 | BZ29: 3.768 | CA29: 6.13 | CB29: 3.62 | CD29: 3.6155 | CG29: 15.711 | CH29: 13.028 | CI29: 7.1621 | CJ29: 8.2196 | CK29: 8.656 | CL29: 4.4943 | CM29: 5.7505 | CN29: 4.6008 | CO29: 9.1377 | CP29: 0.7439 | CQ29: 15.1526 | CR29: 9.2097 | CS29: 8.7264 | CT29: 13.0791 | CU29: =IFERROR(VLOOKUP(A29,'fat-01-24'!A:C,3,FALSE),"") -> 0.51 | CV29: =IFERROR(VLOOKUP(A29,'fat-02-24'!A:C,3,FALSE),"") -> 6.7823 | CW29: =IFERROR(VLOOKUP(A29,'fat-03-24'!A:C,3,FALSE),"") -> 11.9234 | CX29: =IFERROR(VLOOKUP(A29,'fat-04-24'!A:C,3,FALSE),"") -> 2.7051 | CY29: =IFERROR(VLOOKUP(A29,'fat-05-24'!A:C,3,FALSE),"") -> 1.4191 | CZ29: =IFERROR(VLOOKUP(A29,'fat-06-24'!A:C,3,FALSE),"") -> 4.6008 | DA29: =IFERROR(VLOOKUP(A29,'fat-07-24'!A:C,3,FALSE),"") -> 12.1359 | DB29: =IFERROR(VLOOKUP(A29,'fat-08-24'!A:D,3,FALSE),"") -> 14.6645 | DC29: =IFERROR(VLOOKUP(A29,'fat-09-24'!A:C,3,FALSE),"") -> 6.3048 | DD29: =IFERROR(VLOOKUP(A29,'fat-10-24'!A:C,3,FALSE),"") -> 9.8857 | DE29: =IFERROR(VLOOKUP(A29,'fat-11-24'!A:C,3,FALSE),"") -> 1.334 | DF29: =IFERROR(VLOOKUP(A29,'fat-12-24'!A:D,3,FALSE),"") -> 3.8406 | DG29: =IFERROR(VLOOKUP(A29,'fat-01-25'!A:D,3,FALSE),"") -> 5.8788 | DH29: =IFERROR(VLOOKUP(A29,'fat-02-25'!A:D,3,FALSE),"") -> 0.852 | DI29: =IFERROR(VLOOKUP(A29,'fat-03-25'!A:C,3,FALSE),"") -> 0 | DJ29: =IFERROR(VLOOKUP(A29,'fat-04-25'!A:C,3,FALSE),"") -> 0 | DK29: =IFERROR(VLOOKUP(A29,'fat-02-25'!A:C,3,FALSE),"") -> 0.852 | DL29: =IFERROR(VLOOKUP(A29,'fat-06-25'!A:C,3,FALSE),"") -> 0.6816 | DM29: =IFERROR(VLOOKUP(A29,'fat-05-25'!A:C,3,FALSE),"") -> 0.639 | DN29: =IFERROR(VLOOKUP(A29,'fat-08-25'!A:C,3,FALSE),"") -> 0.9372 | DO29: =IFERROR(VLOOKUP(A29,'fat-09-25'!A:C,3,FALSE),"") -> 0.1806 | DP29: =IFERROR(VLOOKUP(A29,'fat-10-25'!A:C,3,FALSE),"") -> 0 | DQ29: =IFERROR(VLOOKUP(A29,'fat-11-25'!A:D,3,FALSE),"") -> 2.982 | DR29: =IFERROR(VLOOKUP(A29,'fat-12-25'!A:D,3,FALSE),"") -> 1.0224 | DS29: =IFERROR(VLOOKUP(A29,'fat-01-26'!A:C,3,FALSE),"") | DT29: =IFERROR(VLOOKUP(A29,'fat-02-26'!A:C,3,FALSE),"") -> 0.9798 | DU29: =IFERROR(VLOOKUP(A29,'fat-03-26'!A:C,3,FALSE),"") -> 7.4028 | DV29: =IFERROR(VLOOKUP(A29,'fat-04-26'!A:C,3,FALSE),"") -> 2.5773 | DW29: =IFERROR(VLOOKUP(A29,'fat-05-26'!A:C,3,FALSE),"") -> 19.7591 | DX29: =SUM(DR29:DW29)/6 -> 5.2902333 | DY29: =DX29/30*45 -> 7.93535 | DZ29: 5 | EA29: =VLOOKUP(A29,Estoque!B:I,8,FALSE) -> -19.5871 | EB29: =VLOOKUP(A29,Estoque!B:N,13,FALSE) -> 10 | ED29: 20
A30: PRF10100 | B30: PERFIL U ENRIJ LQ 2,25 X 127 X 50 X 17 MM | C30: 0.922 | D30: 2.69 | E30: 1.776 | F30: 1.205 | G30: 1.42 | H30: 4.82 | I30: 5.2 | J30: 1 | K30: 12.83 | L30: 2.455 | N30: 1.97 | O30: 1.048 | P30: 1.495 | Q30: 2.67 | R30: 2.6 | S30: 0.47 | T30: 3.236 | U30: 2.2348 | V30: 5.403 | W30: 1.215 | X30: 15.877 | Y30: 2.111 | Z30: 7.462 | AA30: 6.529 | AB30: 0.735 | AC30: 0.535 | AD30: 1.731 | AE30: 0.742 | AF30: 0.158 | AG30: 8.545 | AH30: 1.57 | AI30: 4.982 | AJ30: 3.595 | AK30: 2.305 | AL30: 1.284 | AM30: 2.3 | AN30: 6.215 | AO30: 3.575 | AP30: 6.415 | AQ30: 3.065 | AR30: 9.219 | AS30: 3.3182 | AT30: 6.995 | AU30: 1.26 | AV30: 2.258 | AW30: 0.9326 | AX30: 1.565 | AY30: 1.099 | AZ30: 0.7973 | BA30: 6.17 | BB30: 0.053 | BC30: 2.627 | BD30: 0.386 | BE30: 0.24 | BF30: 4.729 | BH30: 0.8576 | BI30: 0.19 | BK30: 8.44 | BL30: 0.875 | BM30: 4.28 | BN30: 3.275 | BO30: 2.741 | BP30: 4.108 | BQ30: 18.628 | BR30: 3.04 | BS30: 8.881 | BT30: 6.36 | BU30: 6.8826 | BV30: 1.49 | BW30: 4.175 | BX30: 38.254 | BY30: 7.555 | BZ30: 8.273 | CA30: 15.735 | CB30: 11.042 | CC30: 5.504 | CD30: 9.6999 | CE30: 19.5047 | CF30: 25.1057 | CG30: 0.7105 | CH30: 24.9576 | CI30: 39.0667 | CJ30: 11.4632 | CK30: 2.3667 | CL30: 16.9879 | CM30: 10.6715 | CN30: 6.1803 | CO30: 16.987 | CP30: 6.8193 | CQ30: 18.9745 | CR30: 22.8772 | CS30: 6.4928 | CT30: 15.9828 | CU30: =IFERROR(VLOOKUP(A30,'fat-01-24'!A:C,3,FALSE),"") -> 11.4644 | CV30: =IFERROR(VLOOKUP(A30,'fat-02-24'!A:C,3,FALSE),"") -> 7.741 | CW30: =IFERROR(VLOOKUP(A30,'fat-03-24'!A:C,3,FALSE),"") -> 7.4429 | CX30: =IFERROR(VLOOKUP(A30,'fat-04-24'!A:C,3,FALSE),"") -> 14.887 | CY30: =IFERROR(VLOOKUP(A30,'fat-05-24'!A:C,3,FALSE),"") -> 6.9816 | CZ30: =IFERROR(VLOOKUP(A30,'fat-06-24'!A:C,3,FALSE),"") -> 6.1803 | DA30: =IFERROR(VLOOKUP(A30,'fat-07-24'!A:C,3,FALSE),"") -> 4.6259 | DB30: =IFERROR(VLOOKUP(A30,'fat-08-24'!A:D,3,FALSE),"") -> 19.3001 | DC30: =IFERROR(VLOOKUP(A30,'fat-09-24'!A:C,3,FALSE),"") -> 6.8967 | DD30: =IFERROR(VLOOKUP(A30,'fat-10-24'!A:C,3,FALSE),"") -> 13.1907 | DE30: =IFERROR(VLOOKUP(A30,'fat-11-24'!A:C,3,FALSE),"") -> 3.1245 | DF30: =IFERROR(VLOOKUP(A30,'fat-12-24'!A:D,3,FALSE),"") -> 8.942 | DG30: =IFERROR(VLOOKUP(A30,'fat-01-25'!A:D,3,FALSE),"") -> 7.1542 | DH30: =IFERROR(VLOOKUP(A30,'fat-02-25'!A:D,3,FALSE),"") -> 16.2271 | DI30: =IFERROR(VLOOKUP(A30,'fat-03-25'!A:C,3,FALSE),"") -> 26.2638 | DJ30: =IFERROR(VLOOKUP(A30,'fat-04-25'!A:C,3,FALSE),"") -> 2.4814 | DK30: =IFERROR(VLOOKUP(A30,'fat-02-25'!A:C,3,FALSE),"") -> 16.2271 | DL30: =IFERROR(VLOOKUP(A30,'fat-06-25'!A:C,3,FALSE),"") -> 14.6263 | DM30: =IFERROR(VLOOKUP(A30,'fat-05-25'!A:C,3,FALSE),"") -> 0.0526 | DN30: =IFERROR(VLOOKUP(A30,'fat-08-25'!A:C,3,FALSE),"") -> 21.5967 | DO30: =IFERROR(VLOOKUP(A30,'fat-09-25'!A:C,3,FALSE),"") -> 5.7135 | DP30: =IFERROR(VLOOKUP(A30,'fat-10-25'!A:C,3,FALSE),"") -> 25.8904 | DQ30: =IFERROR(VLOOKUP(A30,'fat-11-25'!A:D,3,FALSE),"") -> 25.54 | DR30: =IFERROR(VLOOKUP(A30,'fat-12-25'!A:D,3,FALSE),"") -> 4.2456 | DS30: =IFERROR(VLOOKUP(A30,'fat-01-26'!A:C,3,FALSE),"") -> 9.3798 | DT30: =IFERROR(VLOOKUP(A30,'fat-02-26'!A:C,3,FALSE),"") -> 0.3588 | DU30: =IFERROR(VLOOKUP(A30,'fat-03-26'!A:C,3,FALSE),"") -> 12.2817 | DV30: =IFERROR(VLOOKUP(A30,'fat-04-26'!A:C,3,FALSE),"") -> 11.3036 | DW30: =IFERROR(VLOOKUP(A30,'fat-05-26'!A:C,3,FALSE),"") -> 11.6308 | DX30: =SUM(DR30:DW30)/6 -> 8.20005 | DY30: =DX30/30*45 -> 12.300075 | DZ30: 20 | EA30: =VLOOKUP(A30,Estoque!B:I,8,FALSE) -> 2.3768 | EB30: =VLOOKUP(A30,Estoque!B:N,13,FALSE) -> 0 | EC30: 20 | ED30: 15
A31: PRF10110 | B31: PERFIL U ENRIJ LQ 2,25 X 150 X 60 X 20 MM | C31: 7.083 | D31: 4.771 | E31: 9.384 | F31: 10.425 | G31: 8.43 | H31: 0.06 | I31: 4.72 | J31: 1.885 | K31: 10.103 | L31: 13.145 | M31: 0.364 | N31: 1.346 | P31: 5.15 | Q31: 16.825 | R31: 1.767 | S31: 0.916 | T31: 0.57 | U31: 2.915 | V31: 0.159 | W31: 13.229 | Y31: 5.39 | Z31: 0.72 | AA31: 15.91 | AB31: 2.969 | AD31: 2.89 | AE31: 2.114 | AF31: 2.1604 | AG31: 5.15 | AH31: 3.37 | AI31: 3.292 | AJ31: 0.125 | AL31: 1.155 | AM31: 8.825 | AN31: 3.246 | AO31: 4.587 | AP31: 9.7868 | AQ31: 1.78 | AR31: 0.21 | AS31: 0.655 | AT31: 13.175 | AU31: 0.679 | AV31: 3.5857 | AW31: 0.413 | AX31: 4.184 | AY31: 4.8321 | AZ31: 3.719 | BA31: 4.51 | BB31: 0.47 | BC31: 4.035 | BD31: 2.867 | BE31: 3.71 | BF31: 11.06 | BG31: 1.748 | BH31: 32.548 | BI31: 3.962 | BJ31: 9.97 | BK31: 3.13 | BL31: 3.6694 | BM31: 0.12 | BN31: 7.45 | BO31: 5.419 | BQ31: 7.25 | BR31: 3.5869 | BS31: 5.731 | BT31: 29.771 | BU31: 7.531 | BV31: 16.2384 | BW31: 18.804 | BX31: 25.86 | BY31: 24.093 | BZ31: 3.517 | CA31: 4.96 | CB31: 11.367 | CC31: 11.5062 | CD31: 31.9184 | CE31: 13.3948 | CF31: 26.1784 | CG31: 0.477 | CH31: 21.81 | CI31: 20.2738 | CJ31: 21.0296 | CK31: 14.3418 | CL31: 7.4386 | CM31: 0.1908 | CN31: 3.8166 | CO31: 18.3408 | CP31: 24.0152 | CQ31: 16.1456 | CR31: 4.6602 | CS31: 17.0448 | CT31: 7.632 | CU31: =IFERROR(VLOOKUP(A31,'fat-01-24'!A:C,3,FALSE),"") -> 21.775 | CV31: =IFERROR(VLOOKUP(A31,'fat-02-24'!A:C,3,FALSE),"") -> 3.0528 | CW31: =IFERROR(VLOOKUP(A31,'fat-03-24'!A:C,3,FALSE),"") -> 24.3541 | CX31: =IFERROR(VLOOKUP(A31,'fat-04-24'!A:C,3,FALSE),"") -> 19.0502 | CY31: =IFERROR(VLOOKUP(A31,'fat-05-24'!A:C,3,FALSE),"") -> 6.7424 | CZ31: =IFERROR(VLOOKUP(A31,'fat-06-24'!A:C,3,FALSE),"") -> 3.8166 | DA31: =IFERROR(VLOOKUP(A31,'fat-07-24'!A:C,3,FALSE),"") -> 25.6594 | DB31: =IFERROR(VLOOKUP(A31,'fat-08-24'!A:D,3,FALSE),"") -> 22.1278 | DC31: =IFERROR(VLOOKUP(A31,'fat-09-24'!A:C,3,FALSE),"") -> 17.4986 | DD31: =IFERROR(VLOOKUP(A31,'fat-10-24'!A:C,3,FALSE),"") -> 22.3418 | DE31: =IFERROR(VLOOKUP(A31,'fat-11-24'!A:C,3,FALSE),"") -> 3.1524 | DF31: =IFERROR(VLOOKUP(A31,'fat-12-24'!A:D,3,FALSE),"") -> 5.3072 | DG31: =IFERROR(VLOOKUP(A31,'fat-01-25'!A:D,3,FALSE),"") -> 2.2724 | DH31: =IFERROR(VLOOKUP(A31,'fat-02-25'!A:D,3,FALSE),"") -> 8.4512 | DI31: =IFERROR(VLOOKUP(A31,'fat-03-25'!A:C,3,FALSE),"") -> 18.6646 | DJ31: =IFERROR(VLOOKUP(A31,'fat-04-25'!A:C,3,FALSE),"") -> 11.13 | DK31: =IFERROR(VLOOKUP(A31,'fat-02-25'!A:C,3,FALSE),"") -> 8.4512 | DL31: =IFERROR(VLOOKUP(A31,'fat-06-25'!A:C,3,FALSE),"") -> 8.8774 | DM31: =IFERROR(VLOOKUP(A31,'fat-05-25'!A:C,3,FALSE),"") -> 0 | DN31: =IFERROR(VLOOKUP(A31,'fat-08-25'!A:C,3,FALSE),"") -> 8.149 | DO31: =IFERROR(VLOOKUP(A31,'fat-09-25'!A:C,3,FALSE),"") -> 9.6438 | DP31: =IFERROR(VLOOKUP(A31,'fat-10-25'!A:C,3,FALSE),"") -> 0 | DQ31: =IFERROR(VLOOKUP(A31,'fat-11-25'!A:D,3,FALSE),"") -> 24.6796 | DR31: =IFERROR(VLOOKUP(A31,'fat-12-25'!A:D,3,FALSE),"") -> 0 | DS31: =IFERROR(VLOOKUP(A31,'fat-01-26'!A:C,3,FALSE),"") -> 3.021 | DT31: =IFERROR(VLOOKUP(A31,'fat-02-26'!A:C,3,FALSE),"") -> 0.3624 | DU31: =IFERROR(VLOOKUP(A31,'fat-03-26'!A:C,3,FALSE),"") -> 8.0148 | DV31: =IFERROR(VLOOKUP(A31,'fat-04-26'!A:C,3,FALSE),"") -> 8.321 | DW31: =IFERROR(VLOOKUP(A31,'fat-05-26'!A:C,3,FALSE),"") -> 7.5776 | DX31: =SUM(DR31:DW31)/6 -> 4.5494667 | DY31: =DX31/30*45 -> 6.8242 | DZ31: 25 | EA31: =VLOOKUP(A31,Estoque!B:I,8,FALSE) -> 13.3476 | EB31: =VLOOKUP(A31,Estoque!B:N,13,FALSE) -> 0 | EC31: 10 | ED31: 10
A32: PRF10111 | B32: PERFIL U ENRIJ LQ 2,25 X 150 X 50 X 20 MM | AY32: 3.77 | AZ32: 8.885 | BB32: 3.46 | BC32: 0.4 | BD32: 1.46 | BE32: 0.78 | BF32: 1.766 | BG32: 0.06 | BH32: 0.615 | BJ32: 12.107 | BK32: 0.69 | BL32: 2.008 | BO32: 1.662 | BQ32: 1.32 | BR32: 0.565 | BW32: 0.605 | BX32: 1.375 | BY32: 1.204 | BZ32: 2.524 | CA32: 2.049 | CB32: 0.924 | CD32: 1.276 | CH32: 0.623 | CI32: 10.44 | CJ32: 2.575 | CK32: 8.495 | CL32: 3.656 | CO32: 3.335 | CP32: 5.046 | CQ32: 0.203 | CR32: 0.962 | CS32: 0.667 | CT32: 1.595 | CU32: =IFERROR(VLOOKUP(A32,'fat-01-24'!A:C,3,FALSE),"") -> 2.566 | CV32: =IFERROR(VLOOKUP(A32,'fat-02-24'!A:C,3,FALSE),"") -> 0.11 | CW32: =IFERROR(VLOOKUP(A32,'fat-03-24'!A:C,3,FALSE),"") -> 0.524 | CX32: =IFERROR(VLOOKUP(A32,'fat-04-24'!A:C,3,FALSE),"") -> 6.931 | CY32: =IFERROR(VLOOKUP(A32,'fat-05-24'!A:C,3,FALSE),"") -> 8.1244 | CZ32: =IFERROR(VLOOKUP(A32,'fat-06-24'!A:C,3,FALSE),"") | DA32: =IFERROR(VLOOKUP(A32,'fat-07-24'!A:C,3,FALSE),"") -> 13.784 | DB32: =IFERROR(VLOOKUP(A32,'fat-08-24'!A:D,3,FALSE),"") -> 1.827 | DC32: =IFERROR(VLOOKUP(A32,'fat-09-24'!A:C,3,FALSE),"") -> 5.191 | DD32: =IFERROR(VLOOKUP(A32,'fat-10-24'!A:C,3,FALSE),"") -> 3.7483 | DE32: =IFERROR(VLOOKUP(A32,'fat-11-24'!A:C,3,FALSE),"") -> 2.7205 | DF32: =IFERROR(VLOOKUP(A32,'fat-12-24'!A:D,3,FALSE),"") -> 3.4393 | DG32: =IFERROR(VLOOKUP(A32,'fat-01-25'!A:D,3,FALSE),"") -> 3.161 | DH32: =IFERROR(VLOOKUP(A32,'fat-02-25'!A:D,3,FALSE),"") -> 3.6416 | DI32: =IFERROR(VLOOKUP(A32,'fat-03-25'!A:C,3,FALSE),"") -> 0 | DJ32: =IFERROR(VLOOKUP(A32,'fat-04-25'!A:C,3,FALSE),"") -> 9.27 | DK32: =IFERROR(VLOOKUP(A32,'fat-02-25'!A:C,3,FALSE),"") -> 3.6416 | DL32: =IFERROR(VLOOKUP(A32,'fat-06-25'!A:C,3,FALSE),"") -> 1.653 | DM32: =IFERROR(VLOOKUP(A32,'fat-05-25'!A:C,3,FALSE),"") -> 3.518 | DN32: =IFERROR(VLOOKUP(A32,'fat-08-25'!A:C,3,FALSE),"") -> 3.335 | DO32: =IFERROR(VLOOKUP(A32,'fat-09-25'!A:C,3,FALSE),"") -> 3.19 | DP32: =IFERROR(VLOOKUP(A32,'fat-10-25'!A:C,3,FALSE),"") -> 0.348 | DQ32: =IFERROR(VLOOKUP(A32,'fat-11-25'!A:D,3,FALSE),"") -> 2.718 | DR32: =IFERROR(VLOOKUP(A32,'fat-12-25'!A:D,3,FALSE),"") -> 1.27 | DS32: =IFERROR(VLOOKUP(A32,'fat-01-26'!A:C,3,FALSE),"") -> 8.062 | DT32: =IFERROR(VLOOKUP(A32,'fat-02-26'!A:C,3,FALSE),"") -> 3.722 | DU32: =IFERROR(VLOOKUP(A32,'fat-03-26'!A:C,3,FALSE),"") -> 2.186 | DV32: =IFERROR(VLOOKUP(A32,'fat-04-26'!A:C,3,FALSE),"") -> 1.03 | DW32: =IFERROR(VLOOKUP(A32,'fat-05-26'!A:C,3,FALSE),"") -> 2.204 | DX32: =SUM(DR32:DW32)/6 -> 3.079 | DY32: =DX32/30*45 -> 4.6185 | DZ32: 7 | EA32: =VLOOKUP(A32,Estoque!B:I,8,FALSE) -> 7.714 | EB32: =VLOOKUP(A32,Estoque!B:N,13,FALSE) -> 0
A33: PRF10120 | B33: PERFIL U ENRIJ LQ 2,25 X 200 X 75 X 20 MM | J33: 7.765 | K33: 2.375 | L33: 1.695 | N33: 2.105 | O33: 0.04 | Q33: 2.855 | T33: 1.67 | U33: 2.312 | V33: 6.533 | W33: 1.6738 | X33: 6.19 | Y33: 12.323 | Z33: 3.625 | AB33: 2.718 | AD33: 5.986 | AF33: 4.51 | AG33: 2.815 | AH33: 2.01 | AI33: 4.182 | AJ33: 2.204 | AK33: 2.688 | AL33: 10.775 | AM33: 1.041 | AO33: 6.458 | AP33: 0.333 | AQ33: 1.457 | AR33: 2.42 | AS33: 1.249 | AT33: 0.2 | AU33: 2.95 | AX33: 0.042 | AY33: 2.175 | AZ33: 1.65 | BA33: 0.558 | BB33: 1.166 | BE33: 8.6 | BF33: 7.246 | BG33: 4.981 | BJ33: 0.957 | BK33: 10.8378 | BL33: 21.1652 | BM33: 3.105 | BN33: 4.97 | BO33: 17.324 | BP33: 3.985 | BQ33: 23.946 | BR33: 94.905 | BS33: 20.933 | BT33: 2.238 | BU33: 0.78 | BV33: 13.118 | BW33: 11.979 | BX33: 0.69 | BY33: 4.941 | CA33: 3.1363 | CB33: 14.27 | CC33: 3.516 | CD33: 2.0012 | CE33: 10.2582 | CF33: 6.7848 | CG33: 6.7617 | CH33: 11.0511 | CI33: 18.0892 | CK33: 6.9198 | CL33: 0.2919 | CM33: 4.8311993 | CN33: 12.6968 | CO33: 5.6295 | CP33: 0.191 | CQ33: 4.4748 | CR33: 3.0024 | CS33: 6.7863 | CT33: 4.939 | CU33: =IFERROR(VLOOKUP(A33,'fat-01-24'!A:C,3,FALSE),"") -> 4.6207 | CV33: =IFERROR(VLOOKUP(A33,'fat-02-24'!A:C,3,FALSE),"") -> 5.3793 | CW33: =IFERROR(VLOOKUP(A33,'fat-03-24'!A:C,3,FALSE),"") -> 4.8789 | CX33: =IFERROR(VLOOKUP(A33,'fat-04-24'!A:C,3,FALSE),"") -> 8.5485 | CY33: =IFERROR(VLOOKUP(A33,'fat-05-24'!A:C,3,FALSE),"") -> 9.0589 | CZ33: =IFERROR(VLOOKUP(A33,'fat-06-24'!A:C,3,FALSE),"") -> 12.6968 | DA33: =IFERROR(VLOOKUP(A33,'fat-07-24'!A:C,3,FALSE),"") -> 4.161 | DB33: =IFERROR(VLOOKUP(A33,'fat-08-24'!A:D,3,FALSE),"") -> 22.2176 | DC33: =IFERROR(VLOOKUP(A33,'fat-09-24'!A:C,3,FALSE),"") -> 9.2478 | DD33: =IFERROR(VLOOKUP(A33,'fat-10-24'!A:C,3,FALSE),"") -> 2.0848 | DE33: =IFERROR(VLOOKUP(A33,'fat-11-24'!A:C,3,FALSE),"") -> 16.2714 | DF33: =IFERROR(VLOOKUP(A33,'fat-12-24'!A:D,3,FALSE),"") -> 4.9063 | DG33: =IFERROR(VLOOKUP(A33,'fat-01-25'!A:D,3,FALSE),"") -> 10.1473 | DH33: =IFERROR(VLOOKUP(A33,'fat-02-25'!A:D,3,FALSE),"") -> 10.7372 | DI33: =IFERROR(VLOOKUP(A33,'fat-03-25'!A:C,3,FALSE),"") -> 2.4345 | DJ33: =IFERROR(VLOOKUP(A33,'fat-04-25'!A:C,3,FALSE),"") -> 22.3428 | DK33: =IFERROR(VLOOKUP(A33,'fat-02-25'!A:C,3,FALSE),"") -> 10.7372 | DL33: =IFERROR(VLOOKUP(A33,'fat-06-25'!A:C,3,FALSE),"") -> 11.9205 | DM33: =IFERROR(VLOOKUP(A33,'fat-05-25'!A:C,3,FALSE),"") -> 5.3021 | DN33: =IFERROR(VLOOKUP(A33,'fat-08-25'!A:C,3,FALSE),"") -> 13.5912 | DO33: =IFERROR(VLOOKUP(A33,'fat-09-25'!A:C,3,FALSE),"") -> 5.2612 | DP33: =IFERROR(VLOOKUP(A33,'fat-10-25'!A:C,3,FALSE),"") -> 12.9102 | DQ33: =IFERROR(VLOOKUP(A33,'fat-11-25'!A:D,3,FALSE),"") -> 22.3531 | DR33: =IFERROR(VLOOKUP(A33,'fat-12-25'!A:D,3,FALSE),"") -> 3.5862 | DS33: =IFERROR(VLOOKUP(A33,'fat-01-26'!A:C,3,FALSE),"") | DT33: =IFERROR(VLOOKUP(A33,'fat-02-26'!A:C,3,FALSE),"") -> 2.2935 | DU33: =IFERROR(VLOOKUP(A33,'fat-03-26'!A:C,3,FALSE),"") -> 8.0344 | DV33: =IFERROR(VLOOKUP(A33,'fat-04-26'!A:C,3,FALSE),"") -> 12.8436 | DW33: =IFERROR(VLOOKUP(A33,'fat-05-26'!A:C,3,FALSE),"") | DX33: =SUM(DR33:DW33)/6 -> 4.4596167 | DY33: =DX33/30*45 -> 6.689425 | DZ33: 18 | EA33: =VLOOKUP(A33,Estoque!B:I,8,FALSE) -> 6.0362 | EB33: =VLOOKUP(A33,Estoque!B:N,13,FALSE) -> 10 | ED33: 10
A34: PRF10121 | B34: PERFIL U ENRIJ LQ 2,25 X 200 X 60 X 20 MM | C34: 1.365 | D34: 0.108 | E34: 3.985 | F34: 7.205 | I34: 1.04 | J34: 1.227 | K34: 5.77 | M34: 3.058 | N34: 3.193 | R34: 5.015 | S34: 2.814 | W34: 0.55 | AB34: 0.76 | AO34: 5.945 | AS34: 0.43 | AT34: 1.355 | AV34: 1.625 | AY34: 0.022 | AZ34: 4.376 | BA34: 2.68 | BD34: 0.14 | CI34: 6.12 | CP34: 2.16 | CQ34: 2.34 | CR34: 0.0364 | CU34: =IFERROR(VLOOKUP(A34,'fat-01-24'!A:C,3,FALSE),"") -> 0.963 | CV34: =IFERROR(VLOOKUP(A34,'fat-02-24'!A:C,3,FALSE),"") -> 1.152 | CW34: =IFERROR(VLOOKUP(A34,'fat-03-24'!A:C,3,FALSE),"") | CX34: =IFERROR(VLOOKUP(A34,'fat-04-24'!A:C,3,FALSE),"") | CY34: =IFERROR(VLOOKUP(A34,'fat-05-24'!A:C,3,FALSE),"") | CZ34: =IFERROR(VLOOKUP(A34,'fat-06-24'!A:C,3,FALSE),"") | DA34: =IFERROR(VLOOKUP(A34,'fat-07-24'!A:C,3,FALSE),"") | DB34: =IFERROR(VLOOKUP(A34,'fat-08-24'!A:D,3,FALSE),"") -> 1.877 | DC34: =IFERROR(VLOOKUP(A34,'fat-09-24'!A:C,3,FALSE),"") -> 0.432 | DD34: =IFERROR(VLOOKUP(A34,'fat-10-24'!A:C,3,FALSE),"") -> 0 | DE34: =IFERROR(VLOOKUP(A34,'fat-11-24'!A:C,3,FALSE),"") -> 1.296 | DF34: =IFERROR(VLOOKUP(A34,'fat-12-24'!A:D,3,FALSE),"") -> 0 | DG34: =IFERROR(VLOOKUP(A34,'fat-01-25'!A:D,3,FALSE),"") -> 0 | DH34: =IFERROR(VLOOKUP(A34,'fat-02-25'!A:D,3,FALSE),"") -> 0.468 | DI34: =IFERROR(VLOOKUP(A34,'fat-03-25'!A:C,3,FALSE),"") -> 0 | DJ34: =IFERROR(VLOOKUP(A34,'fat-04-25'!A:C,3,FALSE),"") -> 0 | DK34: =IFERROR(VLOOKUP(A34,'fat-02-25'!A:C,3,FALSE),"") -> 0.468 | DL34: =IFERROR(VLOOKUP(A34,'fat-06-25'!A:C,3,FALSE),"") -> 0.54 | DM34: =IFERROR(VLOOKUP(A34,'fat-05-25'!A:C,3,FALSE),"") -> 0 | DN34: =IFERROR(VLOOKUP(A34,'fat-08-25'!A:C,3,FALSE),"") -> 0.608 | DO34: =IFERROR(VLOOKUP(A34,'fat-09-25'!A:C,3,FALSE),"") -> 5.436 | DP34: =IFERROR(VLOOKUP(A34,'fat-10-25'!A:C,3,FALSE),"") -> 1.04 | DQ34: =IFERROR(VLOOKUP(A34,'fat-11-25'!A:D,3,FALSE),"") -> 0 | DR34: =IFERROR(VLOOKUP(A34,'fat-12-25'!A:D,3,FALSE),"") -> 7.056 | DS34: =IFERROR(VLOOKUP(A34,'fat-01-26'!A:C,3,FALSE),"") -> 0.9 | DT34: =IFERROR(VLOOKUP(A34,'fat-02-26'!A:C,3,FALSE),"") -> -0.716 | DU34: =IFERROR(VLOOKUP(A34,'fat-03-26'!A:C,3,FALSE),"") -> 0.828 | DV34: =IFERROR(VLOOKUP(A34,'fat-04-26'!A:C,3,FALSE),"") | DW34: =IFERROR(VLOOKUP(A34,'fat-05-26'!A:C,3,FALSE),"") -> 6.94 | DX34: =SUM(DR34:DW34)/6 -> 2.5013333 | DY34: =DX34/30*45 -> 3.752 | EA34: =VLOOKUP(A34,Estoque!B:I,8,FALSE) -> 13.263 | EB34: =VLOOKUP(A34,Estoque!B:N,13,FALSE) -> 0 | ED34: 10
A35: PRF10130 | B35: PERFIL U ENRIJ LQ 2,65 X 50 X 25 X 10 MM | C35: 0.0264 | D35: 1.275 | F35: 0.6042 | G35: 0.042 | I35: 1.23 | L35: 0.64 | M35: 6.157 | O35: 1 | Q35: 1.858 | R35: 0.08 | S35: 0.119 | T35: 3.546 | U35: 0.25 | V35: 1.98 | W35: 0.8272 | X35: 0.7282 | Z35: 0.1732 | AB35: 0.15 | AD35: 0.495 | AF35: 0.262 | AH35: 1.528 | AI35: 1.265 | AJ35: 0.354 | AL35: 0.119 | AM35: 0.528 | AN35: 0.15 | AO35: 1.009 | AP35: 0.141 | AQ35: 0.6145 | AR35: 0.065 | AS35: 1.753 | AT35: 0.505 | AU35: 1.215 | AV35: 0.7 | AW35: 0.895 | AX35: 0.675 | AY35: 0.933 | AZ35: 0.242 | BA35: 0.115 | BB35: 1.09 | BC35: 0.268 | BD35: 0.115 | BF35: 0.349 | BG35: 0.1175 | BH35: 0.762 | BI35: 5.78 | BJ35: 0.025 | BK35: 2.13 | BL35: 0.26 | BN35: 0.05 | BO35: 1.415 | BP35: 0.995 | BR35: 1.99 | BS35: 2.5 | BT35: 0.63 | BU35: 0.305 | BV35: 0.647 | BW35: 3.0632 | BX35: 0.2 | BY35: 2.643 | BZ35: 1.905 | CA35: 0.897 | CB35: 0.56 | CC35: 12.8656 | CD35: 5.478 | CF35: 0.264 | CG35: 4.6324 | CH35: 2.971 | CI35: 0.2244 | CJ35: 2.4296 | CK35: 15.47 | CL35: 1.241 | CM35: 1.9939 | CN35: 1.782 | CO35: 3.0344 | CP35: 2.1062 | CQ35: 15.1638 | CS35: 3.784 | CU35: =IFERROR(VLOOKUP(A35,'fat-01-24'!A:C,3,FALSE),"") -> 1.624 | CV35: =IFERROR(VLOOKUP(A35,'fat-02-24'!A:C,3,FALSE),"") -> 2.6282 | CW35: =IFERROR(VLOOKUP(A35,'fat-03-24'!A:C,3,FALSE),"") -> 3.8142 | CX35: =IFERROR(VLOOKUP(A35,'fat-04-24'!A:C,3,FALSE),"") -> 7.0246 | CY35: =IFERROR(VLOOKUP(A35,'fat-05-24'!A:C,3,FALSE),"") -> 7.3392 | CZ35: =IFERROR(VLOOKUP(A35,'fat-06-24'!A:C,3,FALSE),"") -> 1.782 | DA35: =IFERROR(VLOOKUP(A35,'fat-07-24'!A:C,3,FALSE),"") -> 0.0792 | DB35: =IFERROR(VLOOKUP(A35,'fat-08-24'!A:D,3,FALSE),"") -> 2.984 | DC35: =IFERROR(VLOOKUP(A35,'fat-09-24'!A:C,3,FALSE),"") -> 1.2412 | DD35: =IFERROR(VLOOKUP(A35,'fat-10-24'!A:C,3,FALSE),"") -> 2.688 | DE35: =IFERROR(VLOOKUP(A35,'fat-11-24'!A:C,3,FALSE),"") -> 1.646 | DF35: =IFERROR(VLOOKUP(A35,'fat-12-24'!A:D,3,FALSE),"") -> 1.5284 | DG35: =IFERROR(VLOOKUP(A35,'fat-01-25'!A:D,3,FALSE),"") -> 0.4488 | DH35: =IFERROR(VLOOKUP(A35,'fat-02-25'!A:D,3,FALSE),"") -> 4.8938 | DI35: =IFERROR(VLOOKUP(A35,'fat-03-25'!A:C,3,FALSE),"") -> 1.4884 | DJ35: =IFERROR(VLOOKUP(A35,'fat-04-25'!A:C,3,FALSE),"") -> 0.1848 | DK35: =IFERROR(VLOOKUP(A35,'fat-02-25'!A:C,3,FALSE),"") -> 4.8938 | DL35: =IFERROR(VLOOKUP(A35,'fat-06-25'!A:C,3,FALSE),"") -> 0 | DM35: =IFERROR(VLOOKUP(A35,'fat-05-25'!A:C,3,FALSE),"") -> 0.7524 | DN35: =IFERROR(VLOOKUP(A35,'fat-08-25'!A:C,3,FALSE),"") -> 5.3308 | DO35: =IFERROR(VLOOKUP(A35,'fat-09-25'!A:C,3,FALSE),"") -> 19.6512 | DP35: =IFERROR(VLOOKUP(A35,'fat-10-25'!A:C,3,FALSE),"") -> 0.1584 | DQ35: =IFERROR(VLOOKUP(A35,'fat-11-25'!A:D,3,FALSE),"") -> 0.4884 | DR35: =IFERROR(VLOOKUP(A35,'fat-12-25'!A:D,3,FALSE),"") -> 0.821 | DS35: =IFERROR(VLOOKUP(A35,'fat-01-26'!A:C,3,FALSE),"") -> 0.396 | DT35: =IFERROR(VLOOKUP(A35,'fat-02-26'!A:C,3,FALSE),"") -> 4.701 | DU35: =IFERROR(VLOOKUP(A35,'fat-03-26'!A:C,3,FALSE),"") -> 0.838 | DV35: =IFERROR(VLOOKUP(A35,'fat-04-26'!A:C,3,FALSE),"") -> 2.119 | DW35: =IFERROR(VLOOKUP(A35,'fat-05-26'!A:C,3,FALSE),"") | DX35: =SUM(DR35:DW35)/6 -> 1.4791667 | DY35: =DX35/30*45 -> 2.21875 | EA35: =VLOOKUP(A35,Estoque!B:I,8,FALSE) -> 8.1594 | EB35: =VLOOKUP(A35,Estoque!B:N,13,FALSE) -> 10 | EC35: 20
A36: PRF10140 | B36: PERFIL U ENRIJ LQ 2,65 X 75 X 40 X 15 MM | C36: 3.0383 | D36: 8.2207 | E36: 9.1103 | F36: 3.3944 | G36: 15.884 | H36: 2.04 | I36: 4.731 | J36: 5.949 | K36: 5.5154 | L36: 2.832 | N36: 0.93 | O36: 18.44 | P36: 4.868 | Q36: 9.681 | R36: 5.574 | S36: 1.641 | T36: 4.083 | U36: 4.17 | V36: 10.934 | W36: 5.033 | X36: 0.146 | Y36: 6.164 | Z36: 0.356 | AA36: 7.288 | AB36: 5.357 | AC36: 2.981 | AD36: 2.603 | AE36: 5.795 | AF36: 0.635 | AG36: 2.958 | AH36: 14.337 | AI36: 4.995 | AJ36: 1.235 | AK36: 4.61 | AL36: 1.325 | AM36: 3.972 | AN36: 6.527 | AO36: 13.96 | AP36: 3.888 | AQ36: 27.109 | AR36: 6.913 | AS36: 10.631 | AT36: 2.768 | AU36: 10.283 | AV36: 5.936 | AW36: 2.718 | AX36: 12.346 | AY36: 5.053 | AZ36: 5.84 | BA36: 18.999 | BB36: 16.472 | BC36: 7.302 | BD36: 8.837 | BE36: 15.519 | BF36: 19.563 | BG36: 15.5727 | BH36: 3.812 | BI36: 13.798 | BJ36: 14.579 | BK36: 23.642 | BL36: 22.873 | BM36: 4.56 | BN36: 42.55 | BO36: 11.814 | BP36: 5.337 | BQ36: 24.009 | BR36: 10.455 | BS36: 7.41 | BT36: 1.286 | BU36: 7.735 | BV36: 17.688 | BW36: 15.222 | BX36: 7.588 | BY36: 11.5747 | BZ36: 14.7067 | CA36: 10.2999 | CB36: 15.532 | CC36: 9.1 | CD36: 14.928 | CE36: 18.136 | CF36: 21.5046 | CG36: 21.4874 | CH36: 6.3882 | CI36: 17.7513 | CJ36: 8.1312 | CK36: 12.5977 | CL36: 19.5959 | CM36: 4.7 | CN36: 8.5808 | CO36: 23.0615 | CP36: 13.7573 | CQ36: 8.3142 | CR36: 14.2931 | CS36: 11.6484 | CT36: 11.388 | CU36: =IFERROR(VLOOKUP(A36,'fat-01-24'!A:C,3,FALSE),"") -> 15.7253 | CV36: =IFERROR(VLOOKUP(A36,'fat-02-24'!A:C,3,FALSE),"") -> 3.3118 | CW36: =IFERROR(VLOOKUP(A36,'fat-03-24'!A:C,3,FALSE),"") -> 27.922 | CX36: =IFERROR(VLOOKUP(A36,'fat-04-24'!A:C,3,FALSE),"") -> 27.7821 | CY36: =IFERROR(VLOOKUP(A36,'fat-05-24'!A:C,3,FALSE),"") -> 16.4066 | CZ36: =IFERROR(VLOOKUP(A36,'fat-06-24'!A:C,3,FALSE),"") -> 8.5808 | DA36: =IFERROR(VLOOKUP(A36,'fat-07-24'!A:C,3,FALSE),"") -> 5.9503 | DB36: =IFERROR(VLOOKUP(A36,'fat-08-24'!A:D,3,FALSE),"") -> 5.9692 | DC36: =IFERROR(VLOOKUP(A36,'fat-09-24'!A:C,3,FALSE),"") -> 17.0879 | DD36: =IFERROR(VLOOKUP(A36,'fat-10-24'!A:C,3,FALSE),"") -> 18.6773 | DE36: =IFERROR(VLOOKUP(A36,'fat-11-24'!A:C,3,FALSE),"") -> 26.1646 | DF36: =IFERROR(VLOOKUP(A36,'fat-12-24'!A:D,3,FALSE),"") -> 33.2389 | DG36: =IFERROR(VLOOKUP(A36,'fat-01-25'!A:D,3,FALSE),"") -> 8.4382 | DH36: =IFERROR(VLOOKUP(A36,'fat-02-25'!A:D,3,FALSE),"") -> 7.4248 | DI36: =IFERROR(VLOOKUP(A36,'fat-03-25'!A:C,3,FALSE),"") -> 16.2523 | DJ36: =IFERROR(VLOOKUP(A36,'fat-04-25'!A:C,3,FALSE),"") -> 2.4871 | DK36: =IFERROR(VLOOKUP(A36,'fat-02-25'!A:C,3,FALSE),"") -> 7.4248 | DL36: =IFERROR(VLOOKUP(A36,'fat-06-25'!A:C,3,FALSE),"") -> 13.3067 | DM36: =IFERROR(VLOOKUP(A36,'fat-05-25'!A:C,3,FALSE),"") -> 37.165 | DN36: =IFERROR(VLOOKUP(A36,'fat-08-25'!A:C,3,FALSE),"") -> 21.4524 | DO36: =IFERROR(VLOOKUP(A36,'fat-09-25'!A:C,3,FALSE),"") -> 22.0411 | DP36: =IFERROR(VLOOKUP(A36,'fat-10-25'!A:C,3,FALSE),"") -> 5.7296214 | DQ36: =IFERROR(VLOOKUP(A36,'fat-11-25'!A:D,3,FALSE),"") -> 1.502 | DR36: =IFERROR(VLOOKUP(A36,'fat-12-25'!A:D,3,FALSE),"") -> 20.3449 | DS36: =IFERROR(VLOOKUP(A36,'fat-01-26'!A:C,3,FALSE),"") -> 15.8671 | DT36: =IFERROR(VLOOKUP(A36,'fat-02-26'!A:C,3,FALSE),"") -> 8.1112 | DU36: =IFERROR(VLOOKUP(A36,'fat-03-26'!A:C,3,FALSE),"") -> 10.5292 | DV36: =IFERROR(VLOOKUP(A36,'fat-04-26'!A:C,3,FALSE),"") -> 35.6676 | DW36: =IFERROR(VLOOKUP(A36,'fat-05-26'!A:C,3,FALSE),"") -> 16.2455 | DX36: =SUM(DR36:DW36)/6 -> 17.79425 | DY36: =DX36/30*45 -> 26.691375 | DZ36: 25 | EA36: =VLOOKUP(A36,Estoque!B:I,8,FALSE) -> 6.5056 | EB36: =VLOOKUP(A36,Estoque!B:N,13,FALSE) -> 20
A37: PRF10150 | B37: PERFIL U ENRIJ LQ 2,65 X 100 X 50 X 17 MM | C37: 5.68 | D37: 8.5018 | E37: 4.417 | F37: 6.979 | G37: 1.837 | H37: 15.235 | I37: 1.485 | J37: 5.225 | K37: 1.71 | L37: 4.256 | M37: 18.794 | N37: 9.081 | O37: 10.6612 | P37: 4.907 | Q37: 5.441 | R37: 6.002 | S37: 6.126 | T37: 4.372 | U37: 22.565 | V37: 8.641 | W37: 3.88 | X37: 7.755 | Y37: 9.6656 | Z37: 5.139 | AA37: 10.61 | AB37: 14.736 | AC37: 4.792 | AD37: 8.096 | AE37: 10.484 | AF37: 4.144 | AG37: 24.9 | AH37: 21.496 | AI37: 3.028 | AJ37: 2.912 | AK37: 12.86 | AL37: 19.606 | AM37: 2.394 | AN37: 7.515 | AO37: 9.538 | AP37: 3.07 | AQ37: 14.766 | AR37: 5.5144 | AS37: 8.462 | AT37: 20.716 | AU37: 22.401 | AV37: 5.1507 | AW37: 6.594 | AX37: 15.801 | AY37: 4.369 | AZ37: 13.25 | BA37: 10 | BB37: 3.719 | BC37: 8.111 | BD37: 4.784 | BE37: 31.257 | BF37: 24.654 | BG37: 25.0514 | BH37: 17.0361 | BI37: 11.2114 | BJ37: 2.878 | BK37: 18.5682 | BL37: -0.929 | BM37: 36.9583 | BN37: 9.233 | BO37: 8.2625 | BP37: 12.072 | BQ37: 14.72 | BR37: 9.0611 | BS37: 4.22 | BT37: 9.168 | BU37: 15.26 | BV37: 14.692 | BW37: 13.942 | BX37: 8.097 | BY37: 13.293 | BZ37: 8.012 | CA37: 15.9974 | CB37: 12.77 | CC37: 2.16 | CD37: 11.253 | CE37: 13.9202 | CF37: 3.9194 | CG37: 16.2178 | CH37: 24.6312 | CI37: 31.946 | CJ37: 21.8088 | CK37: 29.5742 | CL37: 19.9394 | CM37: 4.7956 | CN37: 17.9406 | CO37: 9.2834 | CP37: 13.6638 | CQ37: 13.2996 | CR37: 14.2806 | CS37: 33.8898 | CT37: 11.3674 | CU37: =IFERROR(VLOOKUP(A37,'fat-01-24'!A:C,3,FALSE),"") -> 27.0196 | CV37: =IFERROR(VLOOKUP(A37,'fat-02-24'!A:C,3,FALSE),"") -> 13.5308 | CW37: =IFERROR(VLOOKUP(A37,'fat-03-24'!A:C,3,FALSE),"") -> 11.0138 | CX37: =IFERROR(VLOOKUP(A37,'fat-04-24'!A:C,3,FALSE),"") -> 18.1181 | CY37: =IFERROR(VLOOKUP(A37,'fat-05-24'!A:C,3,FALSE),"") -> 9.9737 | CZ37: =IFERROR(VLOOKUP(A37,'fat-06-24'!A:C,3,FALSE),"") -> 17.9406 | DA37: =IFERROR(VLOOKUP(A37,'fat-07-24'!A:C,3,FALSE),"") -> 52.167 | DB37: =IFERROR(VLOOKUP(A37,'fat-08-24'!A:D,3,FALSE),"") -> 11.678 | DC37: =IFERROR(VLOOKUP(A37,'fat-09-24'!A:C,3,FALSE),"") -> 24.3414 | DD37: =IFERROR(VLOOKUP(A37,'fat-10-24'!A:C,3,FALSE),"") -> 2.1406 | DE37: =IFERROR(VLOOKUP(A37,'fat-11-24'!A:C,3,FALSE),"") -> 28.3634 | DF37: =IFERROR(VLOOKUP(A37,'fat-12-24'!A:D,3,FALSE),"") -> 18.3636 | DG37: =IFERROR(VLOOKUP(A37,'fat-01-25'!A:D,3,FALSE),"") -> 27.1228 | DH37: =IFERROR(VLOOKUP(A37,'fat-02-25'!A:D,3,FALSE),"") -> 1.8178 | DI37: =IFERROR(VLOOKUP(A37,'fat-03-25'!A:C,3,FALSE),"") -> 28.9362 | DJ37: =IFERROR(VLOOKUP(A37,'fat-04-25'!A:C,3,FALSE),"") -> 16.416 | DK37: =IFERROR(VLOOKUP(A37,'fat-02-25'!A:C,3,FALSE),"") -> 1.8178 | DL37: =IFERROR(VLOOKUP(A37,'fat-06-25'!A:C,3,FALSE),"") -> 22.157 | DM37: =IFERROR(VLOOKUP(A37,'fat-05-25'!A:C,3,FALSE),"") -> 7.6194 | DN37: =IFERROR(VLOOKUP(A37,'fat-08-25'!A:C,3,FALSE),"") -> 11.1756 | DO37: =IFERROR(VLOOKUP(A37,'fat-09-25'!A:C,3,FALSE),"") -> 18.9586 | DP37: =IFERROR(VLOOKUP(A37,'fat-10-25'!A:C,3,FALSE),"") -> 6.5886 | DQ37: =IFERROR(VLOOKUP(A37,'fat-11-25'!A:D,3,FALSE),"") -> 1.3344 | DR37: =IFERROR(VLOOKUP(A37,'fat-12-25'!A:D,3,FALSE),"") -> 19.2066 | DS37: =IFERROR(VLOOKUP(A37,'fat-01-26'!A:C,3,FALSE),"") -> 7.1724 | DT37: =IFERROR(VLOOKUP(A37,'fat-02-26'!A:C,3,FALSE),"") -> 57.0978 | DU37: =IFERROR(VLOOKUP(A37,'fat-03-26'!A:C,3,FALSE),"") -> 21.2386 | DV37: =IFERROR(VLOOKUP(A37,'fat-04-26'!A:C,3,FALSE),"") -> 32.4294 | DW37: =IFERROR(VLOOKUP(A37,'fat-05-26'!A:C,3,FALSE),"") -> 19.577 | DX37: =SUM(DR37:DW37)/6 -> 26.1203 | DY37: =DX37/30*45 -> 39.18045 | DZ37: 16 | EA37: =VLOOKUP(A37,Estoque!B:I,8,FALSE) -> -8.5454 | EB37: =VLOOKUP(A37,Estoque!B:N,13,FALSE) -> 15
A38: PRF10151 | B38: PERFIL U ENRIJ LQ 2,65 X 100 X 40 X 17 MM | C38: 0.79 | D38: 10.5746 | E38: 0.315 | F38: 8.158 | G38: 0.245 | H38: 4.28 | I38: 2.315 | J38: 8.505 | K38: 0.485 | L38: 2.242 | M38: 3.2 | O38: 0.405 | Q38: 1.865 | R38: 1.385 | AE38: 2.8107 | AF38: 0.44 | AH38: 2.212 | AI38: 2.744 | AJ38: 3.074 | AK38: 0.197 | AL38: 4.0438 | AM38: 0.44 | AN38: 0.667 | AO38: 7.435 | AP38: 1.898 | AQ38: 7.156 | AR38: 2.4 | AS38: 4.031 | AT38: 7.548 | AU38: 1.948 | AV38: 11.739 | AW38: 5.1926 | AX38: 1.727 | AY38: 12.142 | AZ38: 7.05 | BA38: 3.261 | BB38: 8.011 | BC38: 16.964 | BD38: 11.972 | BE38: 8.775 | BF38: 25.645 | BG38: 29.472 | BH38: 1.48 | BI38: 14.712 | BJ38: 5.157 | BK38: 15.355 | BL38: 2.1 | BM38: 29.075 | BN38: 4.253 | BO38: 11.325 | BP38: 7.217 | BQ38: 4.232 | BR38: 13.28 | BS38: 13.421 | BT38: 12.693 | BU38: 3.205 | BV38: 0.305 | BW38: 31.594 | BX38: 19.11 | BY38: 35.775 | BZ38: 19.355 | CA38: 16.015 | CB38: 20.135 | CC38: 18.993 | CD38: 51.0742 | CE38: 28.601 | CF38: 14.907201 | CG38: 35.7606 | CH38: 52.5854 | CI38: 24.9402 | CJ38: 4.1866 | CK38: 34.9296 | CL38: 25.3526 | CM38: 38.6924 | CN38: 29.2592 | CO38: 34.4008 | CP38: 34.9238 | CQ38: 17.2302 | CR38: 13.2394 | CS38: 23.7464 | CT38: 23.6966 | CU38: =IFERROR(VLOOKUP(A38,'fat-01-24'!A:C,3,FALSE),"") -> 34.6964 | CV38: =IFERROR(VLOOKUP(A38,'fat-02-24'!A:C,3,FALSE),"") -> 18.1238 | CW38: =IFERROR(VLOOKUP(A38,'fat-03-24'!A:C,3,FALSE),"") -> 56.8188 | CX38: =IFERROR(VLOOKUP(A38,'fat-04-24'!A:C,3,FALSE),"") -> 22.0242 | CY38: =IFERROR(VLOOKUP(A38,'fat-05-24'!A:C,3,FALSE),"") -> 19.3372 | CZ38: =IFERROR(VLOOKUP(A38,'fat-06-24'!A:C,3,FALSE),"") -> 29.2592 | DA38: =IFERROR(VLOOKUP(A38,'fat-07-24'!A:C,3,FALSE),"") -> 18.7462 | DB38: =IFERROR(VLOOKUP(A38,'fat-08-24'!A:D,3,FALSE),"") -> 22.0128 | DC38: =IFERROR(VLOOKUP(A38,'fat-09-24'!A:C,3,FALSE),"") -> 11.8134 | DD38: =IFERROR(VLOOKUP(A38,'fat-10-24'!A:C,3,FALSE),"") -> 30.341 | DE38: =IFERROR(VLOOKUP(A38,'fat-11-24'!A:C,3,FALSE),"") -> 30.513 | DF38: =IFERROR(VLOOKUP(A38,'fat-12-24'!A:D,3,FALSE),"") -> 13.3184 | DG38: =IFERROR(VLOOKUP(A38,'fat-01-25'!A:D,3,FALSE),"") -> 31.4876 | DH38: =IFERROR(VLOOKUP(A38,'fat-02-25'!A:D,3,FALSE),"") -> 14.9748 | DI38: =IFERROR(VLOOKUP(A38,'fat-03-25'!A:C,3,FALSE),"") -> 4.353 | DJ38: =IFERROR(VLOOKUP(A38,'fat-04-25'!A:C,3,FALSE),"") -> 16.978 | DK38: =IFERROR(VLOOKUP(A38,'fat-02-25'!A:C,3,FALSE),"") -> 14.9748 | DL38: =IFERROR(VLOOKUP(A38,'fat-06-25'!A:C,3,FALSE),"") -> 16.4738 | DM38: =IFERROR(VLOOKUP(A38,'fat-05-25'!A:C,3,FALSE),"") -> 35.7708 | DN38: =IFERROR(VLOOKUP(A38,'fat-08-25'!A:C,3,FALSE),"") -> 16.9902 | DO38: =IFERROR(VLOOKUP(A38,'fat-09-25'!A:C,3,FALSE),"") -> 44.5506 | DP38: =IFERROR(VLOOKUP(A38,'fat-10-25'!A:C,3,FALSE),"") -> 13.9868 | DQ38: =IFERROR(VLOOKUP(A38,'fat-11-25'!A:D,3,FALSE),"") -> 12.1476 | DR38: =IFERROR(VLOOKUP(A38,'fat-12-25'!A:D,3,FALSE),"") -> 19.2088 | DS38: =IFERROR(VLOOKUP(A38,'fat-01-26'!A:C,3,FALSE),"") -> 26.4678 | DT38: =IFERROR(VLOOKUP(A38,'fat-02-26'!A:C,3,FALSE),"") -> 24.4752 | DU38: =IFERROR(VLOOKUP(A38,'fat-03-26'!A:C,3,FALSE),"") -> 34.6592 | DV38: =IFERROR(VLOOKUP(A38,'fat-04-26'!A:C,3,FALSE),"") -> 21.471 | DW38: =IFERROR(VLOOKUP(A38,'fat-05-26'!A:C,3,FALSE),"") -> 20.5266 | DX38: =SUM(DR38:DW38)/6 -> 24.4681 | DY38: =DX38/30*45 -> 36.70215 | DZ38: 20 | EA38: =VLOOKUP(A38,Estoque!B:I,8,FALSE) -> -3.8644 | EB38: =VLOOKUP(A38,Estoque!B:N,13,FALSE) -> 40
A39: PRF10160 | B39: PERFIL U ENRIJ LQ 2,65 X 127 X 50 X 17 MM | C39: 5.553 | D39: 5.405 | E39: 15.44 | F39: 7.095 | G39: 10.79 | H39: 15.165 | I39: 0.558 | J39: 4.572 | K39: 18.351 | L39: 1.429 | M39: 7.241 | N39: 6.56 | O39: 4.8776 | P39: 0.44 | Q39: 1.9955 | R39: 10.1509 | S39: 5.219 | T39: 10.38 | U39: 25.743 | V39: 23.735 | W39: 0.8787 | X39: 10.3041 | Y39: 5.0398 | Z39: 3.98 | AA39: 5.882 | AB39: 7.082 | AC39: 5.16 | AD39: 11.3574 | AE39: 2.762 | AG39: 6.69 | AH39: 9.3934 | AI39: 22.9216 | AJ39: 17.599 | AK39: 9.48 | AL39: 3.086 | AM39: 6.96 | AN39: 11.593 | AO39: 4.209 | AP39: 11.087 | AQ39: 13.13 | AR39: 20.426 | AS39: 5.768 | AT39: 10.902 | AU39: 12.69 | AV39: 10.166 | AW39: 1.398 | AX39: 5.099 | AY39: 10.832 | AZ39: 4.763 | BA39: 24.867 | BC39: 13.713 | BD39: 10.702 | BE39: 30.962 | BF39: 19.7595 | BG39: 30.178 | BH39: 31.17 | BI39: 10.795 | BJ39: 30.317 | BK39: 18.061 | BL39: 11.32 | BM39: 23.548 | BN39: 13.273 | BO39: 44.383 | BP39: 22.92 | BQ39: 28.337 | BR39: 12.777 | BS39: 5.063 | BT39: 19.3825 | BU39: 32.463 | BV39: 26.706 | BW39: 19.295 | BX39: 6.024 | BY39: 32.9472 | BZ39: 17.5624 | CA39: 20.597 | CB39: 22.702 | CC39: 32.477 | CD39: 21.4761 | CE39: 24.0963 | CF39: 20.1264 | CG39: 4.6283 | CH39: 24.507 | CI39: 33.4868 | CJ39: 26.0476 | CK39: 54.7919 | CL39: 15.1601 | CM39: 8.2738 | CN39: 34.0653 | CO39: 47.101 | CP39: 40.0648 | CQ39: 36.1324 | CR39: 43.5098 | CS39: 13.3677 | CT39: 66.9089 | CU39: =IFERROR(VLOOKUP(A39,'fat-01-24'!A:C,3,FALSE),"") -> 13.4748 | CV39: =IFERROR(VLOOKUP(A39,'fat-02-24'!A:C,3,FALSE),"") -> 30.4378 | CW39: =IFERROR(VLOOKUP(A39,'fat-03-24'!A:C,3,FALSE),"") -> 17.5012 | CX39: =IFERROR(VLOOKUP(A39,'fat-04-24'!A:C,3,FALSE),"") -> 38.2181 | CY39: =IFERROR(VLOOKUP(A39,'fat-05-24'!A:C,3,FALSE),"") -> 14.9127 | CZ39: =IFERROR(VLOOKUP(A39,'fat-06-24'!A:C,3,FALSE),"") -> 34.0653 | DA39: =IFERROR(VLOOKUP(A39,'fat-07-24'!A:C,3,FALSE),"") -> 46.2525 | DB39: =IFERROR(VLOOKUP(A39,'fat-08-24'!A:D,3,FALSE),"") -> 24.514 | DC39: =IFERROR(VLOOKUP(A39,'fat-09-24'!A:C,3,FALSE),"") -> 17.2035 | DD39: =IFERROR(VLOOKUP(A39,'fat-10-24'!A:C,3,FALSE),"") -> 39.6673 | DE39: =IFERROR(VLOOKUP(A39,'fat-11-24'!A:C,3,FALSE),"") -> 87.7865 | DF39: =IFERROR(VLOOKUP(A39,'fat-12-24'!A:D,3,FALSE),"") -> 3.1806 | DG39: =IFERROR(VLOOKUP(A39,'fat-01-25'!A:D,3,FALSE),"") -> 35.6748 | DH39: =IFERROR(VLOOKUP(A39,'fat-02-25'!A:D,3,FALSE),"") -> 33.1975 | DI39: =IFERROR(VLOOKUP(A39,'fat-03-25'!A:C,3,FALSE),"") -> 46.4169 | DJ39: =IFERROR(VLOOKUP(A39,'fat-04-25'!A:C,3,FALSE),"") -> 41.2009 | DK39: =IFERROR(VLOOKUP(A39,'fat-02-25'!A:C,3,FALSE),"") -> 33.1975 | DL39: =IFERROR(VLOOKUP(A39,'fat-06-25'!A:C,3,FALSE),"") -> 17.486 | DM39: =IFERROR(VLOOKUP(A39,'fat-05-25'!A:C,3,FALSE),"") -> 27.8311 | DN39: =IFERROR(VLOOKUP(A39,'fat-08-25'!A:C,3,FALSE),"") -> 22.0163 | DO39: =IFERROR(VLOOKUP(A39,'fat-09-25'!A:C,3,FALSE),"") -> 27.8273 | DP39: =IFERROR(VLOOKUP(A39,'fat-10-25'!A:C,3,FALSE),"") -> 43.034 | DQ39: =IFERROR(VLOOKUP(A39,'fat-11-25'!A:D,3,FALSE),"") -> 25.6534 | DR39: =IFERROR(VLOOKUP(A39,'fat-12-25'!A:D,3,FALSE),"") -> 40.7692 | DS39: =IFERROR(VLOOKUP(A39,'fat-01-26'!A:C,3,FALSE),"") -> 27.2536 | DT39: =IFERROR(VLOOKUP(A39,'fat-02-26'!A:C,3,FALSE),"") -> 66.5748 | DU39: =IFERROR(VLOOKUP(A39,'fat-03-26'!A:C,3,FALSE),"") -> 39.1891 | DV39: =IFERROR(VLOOKUP(A39,'fat-04-26'!A:C,3,FALSE),"") -> 72.4852 | DW39: =IFERROR(VLOOKUP(A39,'fat-05-26'!A:C,3,FALSE),"") -> 16.6351 | DX39: =SUM(DR39:DW39)/6 -> 43.817833 | DY39: =DX39/30*45 -> 65.72675 | DZ39: 50 | EA39: =VLOOKUP(A39,Estoque!B:I,8,FALSE) -> 83.3183 | EB39: =VLOOKUP(A39,Estoque!B:N,13,FALSE) -> 0 | ED39: 30 | EE39: 20
A40: PRF10170 | B40: PERFIL U ENRIJ LQ 2,65 X 150 X 60 X 20 MM | C40: 17.12 | D40: 17.5372 | E40: 54.588 | F40: 11.26 | G40: 1.46 | H40: 0.25 | I40: 7.785 | J40: 3.973 | K40: 9.993 | L40: 6.7471 | M40: 10.979 | N40: 0.79 | O40: 20.703 | P40: 7.155 | Q40: 7.34 | R40: 14.395 | S40: 1.862 | T40: 14.482 | U40: 11.811 | V40: 9.936 | W40: 2.872 | X40: 23.915 | Y40: 9.0455 | Z40: 22.275 | AA40: 21.192 | AB40: 19.153 | AC40: 5.395 | AD40: 6.705 | AE40: 14.545 | AF40: 8.956 | AG40: 1.175 | AH40: 25.796 | AI40: 14.208 | AJ40: 29.034 | AK40: 17.068 | AL40: 10.709 | AM40: 20.1075 | AN40: 13.701 | AO40: 31.6 | AP40: 18.317 | AQ40: 11.024 | AR40: 15.292 | AS40: 10.32 | AT40: 12.88 | AU40: 11.566 | AV40: 6.909 | AW40: 7.087 | AX40: 22.6862 | AY40: 29.904 | AZ40: 13.4348 | BA40: 20.782 | BB40: 7.666 | BC40: 14.615 | BD40: 15.429 | BE40: 31.555 | BF40: 24.3831 | BG40: 18.012 | BH40: 66.82 | BI40: 13.456 | BJ40: 44.313 | BK40: 42.1553 | BL40: 20.5527 | BM40: 33.586 | BN40: 30.7602 | BO40: 51.326 | BP40: 19.6295 | BQ40: 32.62 | BR40: 25.335 | BS40: 23.8514 | BT40: 35.386 | BU40: 46.784 | BV40: 22.623 | BW40: 31.2701 | BX40: 28.061 | BY40: 39.4797 | BZ40: 38.1932 | CA40: 51.904 | CB40: 52.571 | CC40: 21.866 | CD40: 66.4487 | CE40: 12.243 | CF40: 28.889 | CG40: 41.094 | CH40: 25.086 | CI40: 20.739 | CJ40: 53.115 | CK40: 43.755 | CL40: 33.234 | CM40: 19.476 | CN40: 47.446 | CO40: 52.165 | CP40: 50.3241 | CQ40: 22.698 | CR40: 31.3379 | CS40: 31.347 | CT40: 25.801 | CU40: =IFERROR(VLOOKUP(A40,'fat-01-24'!A:C,3,FALSE),"") -> 44.158 | CV40: =IFERROR(VLOOKUP(A40,'fat-02-24'!A:C,3,FALSE),"") -> 1.015 | CW40: =IFERROR(VLOOKUP(A40,'fat-03-24'!A:C,3,FALSE),"") -> 38.8896 | CX40: =IFERROR(VLOOKUP(A40,'fat-04-24'!A:C,3,FALSE),"") -> 45.169 | CY40: =IFERROR(VLOOKUP(A40,'fat-05-24'!A:C,3,FALSE),"") -> 44.054 | CZ40: =IFERROR(VLOOKUP(A40,'fat-06-24'!A:C,3,FALSE),"") -> 47.446 | DA40: =IFERROR(VLOOKUP(A40,'fat-07-24'!A:C,3,FALSE),"") -> 31.391 | DB40: =IFERROR(VLOOKUP(A40,'fat-08-24'!A:D,3,FALSE),"") -> 21.468 | DC40: =IFERROR(VLOOKUP(A40,'fat-09-24'!A:C,3,FALSE),"") -> 25.069 | DD40: =IFERROR(VLOOKUP(A40,'fat-10-24'!A:C,3,FALSE),"") -> 34.775 | DE40: =IFERROR(VLOOKUP(A40,'fat-11-24'!A:C,3,FALSE),"") -> 22.9723 | DF40: =IFERROR(VLOOKUP(A40,'fat-12-24'!A:D,3,FALSE),"") -> 60.202 | DG40: =IFERROR(VLOOKUP(A40,'fat-01-25'!A:D,3,FALSE),"") -> 12.78 | DH40: =IFERROR(VLOOKUP(A40,'fat-02-25'!A:D,3,FALSE),"") -> 49.384 | DI40: =IFERROR(VLOOKUP(A40,'fat-03-25'!A:C,3,FALSE),"") -> 7.13 | DJ40: =IFERROR(VLOOKUP(A40,'fat-04-25'!A:C,3,FALSE),"") -> 55.08 | DK40: =IFERROR(VLOOKUP(A40,'fat-02-25'!A:C,3,FALSE),"") -> 49.384 | DL40: =IFERROR(VLOOKUP(A40,'fat-06-25'!A:C,3,FALSE),"") -> 11.831 | DM40: =IFERROR(VLOOKUP(A40,'fat-05-25'!A:C,3,FALSE),"") -> 25.15 | DN40: =IFERROR(VLOOKUP(A40,'fat-08-25'!A:C,3,FALSE),"") -> 41.29 | DO40: =IFERROR(VLOOKUP(A40,'fat-09-25'!A:C,3,FALSE),"") -> 52.751 | DP40: =IFERROR(VLOOKUP(A40,'fat-10-25'!A:C,3,FALSE),"") -> 5.2435 | DQ40: =IFERROR(VLOOKUP(A40,'fat-11-25'!A:D,3,FALSE),"") -> 37.095 | DR40: =IFERROR(VLOOKUP(A40,'fat-12-25'!A:D,3,FALSE),"") -> 12.636 | DS40: =IFERROR(VLOOKUP(A40,'fat-01-26'!A:C,3,FALSE),"") -> 25.8 | DT40: =IFERROR(VLOOKUP(A40,'fat-02-26'!A:C,3,FALSE),"") -> 33.398 | DU40: =IFERROR(VLOOKUP(A40,'fat-03-26'!A:C,3,FALSE),"") -> 24.3332 | DV40: =IFERROR(VLOOKUP(A40,'fat-04-26'!A:C,3,FALSE),"") -> 21.484 | DW40: =IFERROR(VLOOKUP(A40,'fat-05-26'!A:C,3,FALSE),"") -> 21.968 | DX40: =SUM(DR40:DW40)/6 -> 23.269867 | DY40: =DX40/30*45 -> 34.9048 | DZ40: 30 | EA40: =VLOOKUP(A40,Estoque!B:I,8,FALSE) -> 27.836 | EB40: =VLOOKUP(A40,Estoque!B:N,13,FALSE) -> 30 | EC40: 15 | ED40: 20
A41: prf10180 | B41: PERFIL U ENRIJ LQ 2,65 X 200 X 75 X 20 MM | I41: 0.235 | J41: 6.6 | L41: 3.835 | M41: 4.675 | N41: 7.304 | O41: 10.078 | P41: 4.951 | Q41: 1.24 | R41: 4.118 | S41: 1.27 | T41: 17.035 | U41: 7.52 | V41: 0.344 | W41: 7.263 | X41: 10.449 | Y41: 6.412 | Z41: 12.757 | AB41: 2.905 | AC41: 7.501 | AD41: 4.401 | AE41: 6.805 | AF41: 2.66 | AG41: 9.038 | AH41: 14.924 | AI41: 3.373 | AJ41: 8.708 | AK41: 5.129 | AL41: 12.415 | AM41: 16.861 | AN41: 0.147 | AO41: 39.144 | AP41: 21.009 | AQ41: 0.8832 | AR41: 8.9368 | AS41: 2.572 | AT41: 11.972 | AU41: 4.376 | AV41: 33.53 | AW41: 21.931 | AX41: 38.109 | AY41: 9.852 | AZ41: 15.159 | BA41: 6.747 | BB41: 7.037 | BC41: 16.5306 | BD41: 14.612 | BE41: 20.442 | BF41: 30.664 | BG41: 17.593 | BH41: 41.96 | BI41: 21.697 | BJ41: 26.711 | BK41: 7.385 | BL41: 27.161 | BM41: 51.6826 | BN41: 5.8224 | BO41: 35.0352 | BP41: 23.513 | BQ41: 30.1138 | BR41: 20.603 | BS41: 27.8886 | BT41: 14.7044 | BU41: 39.819 | BV41: 16.535 | BW41: 39.532 | BX41: 17.8186 | BY41: 23.178 | BZ41: 18.5528 | CA41: 42.6168 | CB41: 10.753 | CC41: 23.0681 | CD41: 30.6577 | CF41: 18.9776 | CG41: 15.128 | CH41: 68.3936 | CI41: 40.455 | CJ41: 3.3782 | CK41: 56.2232 | CL41: 32.8962 | CM41: 17.151 | CN41: 19.6186 | CO41: 21.6424 | CP41: 19.5384 | CQ41: 57.7902 | CR41: 22.4712 | CS41: 10.35 | CT41: 12.3286 | CU41: =IFERROR(VLOOKUP(A41,'fat-01-24'!A:C,3,FALSE),"") -> 12.636 | CV41: =IFERROR(VLOOKUP(A41,'fat-02-24'!A:C,3,FALSE),"") -> 44.22572 | CW41: =IFERROR(VLOOKUP(A41,'fat-03-24'!A:C,3,FALSE),"") -> 4.63 | CX41: =IFERROR(VLOOKUP(A41,'fat-04-24'!A:C,3,FALSE),"") -> 45.749 | CY41: =IFERROR(VLOOKUP(A41,'fat-05-24'!A:C,3,FALSE),"") -> 17.0504 | CZ41: =IFERROR(VLOOKUP(A41,'fat-06-24'!A:C,3,FALSE),"") -> 19.6186 | DA41: =IFERROR(VLOOKUP(A41,'fat-07-24'!A:C,3,FALSE),"") -> 26.4196 | DB41: =IFERROR(VLOOKUP(A41,'fat-08-24'!A:D,3,FALSE),"") -> 38.1464 | DC41: =IFERROR(VLOOKUP(A41,'fat-09-24'!A:C,3,FALSE),"") -> 27.838 | DD41: =IFERROR(VLOOKUP(A41,'fat-10-24'!A:C,3,FALSE),"") -> 42.2083 | DE41: =IFERROR(VLOOKUP(A41,'fat-11-24'!A:C,3,FALSE),"") -> 15.1472 | DF41: =IFERROR(VLOOKUP(A41,'fat-12-24'!A:D,3,FALSE),"") -> 21.5704 | DG41: =IFERROR(VLOOKUP(A41,'fat-01-25'!A:D,3,FALSE),"") -> 8.4264 | DH41: =IFERROR(VLOOKUP(A41,'fat-02-25'!A:D,3,FALSE),"") -> 15.2204 | DI41: =IFERROR(VLOOKUP(A41,'fat-03-25'!A:C,3,FALSE),"") -> 12.535 | DJ41: =IFERROR(VLOOKUP(A41,'fat-04-25'!A:C,3,FALSE),"") -> 27.3678 | DK41: =IFERROR(VLOOKUP(A41,'fat-02-25'!A:C,3,FALSE),"") -> 15.2204 | DL41: =IFERROR(VLOOKUP(A41,'fat-06-25'!A:C,3,FALSE),"") -> 12.8576 | DM41: =IFERROR(VLOOKUP(A41,'fat-05-25'!A:C,3,FALSE),"") -> 11.5596 | DN41: =IFERROR(VLOOKUP(A41,'fat-08-25'!A:C,3,FALSE),"") -> 6.8208 | DO41: =IFERROR(VLOOKUP(A41,'fat-09-25'!A:C,3,FALSE),"") -> 15.9052 | DP41: =IFERROR(VLOOKUP(A41,'fat-10-25'!A:C,3,FALSE),"") -> 25.434 | DQ41: =IFERROR(VLOOKUP(A41,'fat-11-25'!A:D,3,FALSE),"") -> 20.283 | DR41: =IFERROR(VLOOKUP(A41,'fat-12-25'!A:D,3,FALSE),"") -> 14.1388 | DS41: =IFERROR(VLOOKUP(A41,'fat-01-26'!A:C,3,FALSE),"") -> 20.1616 | DT41: =IFERROR(VLOOKUP(A41,'fat-02-26'!A:C,3,FALSE),"") -> 1.8416 | DU41: =IFERROR(VLOOKUP(A41,'fat-03-26'!A:C,3,FALSE),"") -> 10.9182 | DV41: =IFERROR(VLOOKUP(A41,'fat-04-26'!A:C,3,FALSE),"") -> 34.501 | DW41: =IFERROR(VLOOKUP(A41,'fat-05-26'!A:C,3,FALSE),"") -> 24.6938 | DX41: =SUM(DR41:DW41)/6 -> 17.709167 | DY41: =DX41/30*45 -> 26.56375 | DZ41: 35 | EA41: =VLOOKUP(A41,Estoque!B:I,8,FALSE) -> -0.67 | EB41: =VLOOKUP(A41,Estoque!B:N,13,FALSE) -> 20 | EC41: 15 | ED41: 20
A42: PRF10181 | B42: PERFIL U ENRIJ LQ 2,65 X 200 X 60 X 20 MM | C42: 1.25 | D42: 1.54 | E42: 0.085 | F42: 11.387 | G42: 3.555 | H42: 2.76 | I42: 3.373 | J42: 2.9525 | K42: 1.998 | P42: 0.391 | R42: 0.05 | S42: 0.5069 | T42: 2.422 | U42: 0.765 | V42: 2.635 | W42: 2.32 | Z42: 3.592 | AA42: 0.169 | AB42: 0.3784 | AC42: 0.858 | AD42: 0.29 | AG42: 0.63 | AH42: 5.31 | AJ42: 0.62 | AM42: 1.115 | AN42: 6.897 | AO42: 5.865 | AP42: 4.205 | AQ42: 4.55 | AR42: 0.175 | AS42: 1.27 | AT42: 4.269 | AU42: 1.771 | AV42: 0.161 | BD42: 0.55 | BG42: 0.253 | BI42: 0.098 | BY42: 2.556 | BZ42: 0.906 | CA42: 17.914 | CC42: 0.653 | CD42: 21.1002 | CE42: 11.8468 | CF42: 3.2924 | CG42: 0.6768 | CH42: 5.2029 | CI42: 7.3846 | CJ42: 3.5122 | CK42: 7.8152 | CL42: 1.4478 | CM42: 3.2253 | CN42: 1.017 | CO42: 2.6521 | CP42: 1.6929 | CQ42: 8.595 | CR42: 10.0563 | CS42: 6.0003 | CT42: 1.015 | CU42: =IFERROR(VLOOKUP(A42,'fat-01-24'!A:C,3,FALSE),"") -> 2.4625 | CV42: =IFERROR(VLOOKUP(A42,'fat-02-24'!A:C,3,FALSE),"") -> 1.2638 | CW42: =IFERROR(VLOOKUP(A42,'fat-03-24'!A:C,3,FALSE),"") -> 6.4064 | CX42: =IFERROR(VLOOKUP(A42,'fat-04-24'!A:C,3,FALSE),"") -> 0.592 | CY42: =IFERROR(VLOOKUP(A42,'fat-05-24'!A:C,3,FALSE),"") -> 0.2115 | CZ42: =IFERROR(VLOOKUP(A42,'fat-06-24'!A:C,3,FALSE),"") -> 1.017 | DA42: =IFERROR(VLOOKUP(A42,'fat-07-24'!A:C,3,FALSE),"") -> 12.9712 | DB42: =IFERROR(VLOOKUP(A42,'fat-08-24'!A:D,3,FALSE),"") -> 1.0152 | DC42: =IFERROR(VLOOKUP(A42,'fat-09-24'!A:C,3,FALSE),"") -> 0.268 | DD42: =IFERROR(VLOOKUP(A42,'fat-10-24'!A:C,3,FALSE),"") -> 6.7667 | DE42: =IFERROR(VLOOKUP(A42,'fat-11-24'!A:C,3,FALSE),"") -> 7.142 | DF42: =IFERROR(VLOOKUP(A42,'fat-12-24'!A:D,3,FALSE),"") -> 6.865 | DG42: =IFERROR(VLOOKUP(A42,'fat-01-25'!A:D,3,FALSE),"") -> 0.3807 | DH42: =IFERROR(VLOOKUP(A42,'fat-02-25'!A:D,3,FALSE),"") -> 0 | DI42: =IFERROR(VLOOKUP(A42,'fat-03-25'!A:C,3,FALSE),"") -> 2.3035 | DJ42: =IFERROR(VLOOKUP(A42,'fat-04-25'!A:C,3,FALSE),"") -> 0.335 | DK42: =IFERROR(VLOOKUP(A42,'fat-02-25'!A:C,3,FALSE),"") -> 0 | DL42: =IFERROR(VLOOKUP(A42,'fat-06-25'!A:C,3,FALSE),"") -> 0 | DM42: =IFERROR(VLOOKUP(A42,'fat-05-25'!A:C,3,FALSE),"") -> 4.5914 | DN42: =IFERROR(VLOOKUP(A42,'fat-08-25'!A:C,3,FALSE),"") -> 3.776 | DO42: =IFERROR(VLOOKUP(A42,'fat-09-25'!A:C,3,FALSE),"") -> 2.6848 | DP42: =IFERROR(VLOOKUP(A42,'fat-10-25'!A:C,3,FALSE),"") -> 11.1834 | DQ42: =IFERROR(VLOOKUP(A42,'fat-11-25'!A:D,3,FALSE),"") | DR42: =IFERROR(VLOOKUP(A42,'fat-12-25'!A:D,3,FALSE),"") | DS42: =IFERROR(VLOOKUP(A42,'fat-01-26'!A:C,3,FALSE),"") -> 2.85 | DT42: =IFERROR(VLOOKUP(A42,'fat-02-26'!A:C,3,FALSE),"") -> 0.254 | DU42: =IFERROR(VLOOKUP(A42,'fat-03-26'!A:C,3,FALSE),"") | DV42: =IFERROR(VLOOKUP(A42,'fat-04-26'!A:C,3,FALSE),"") -> 0.423 | DW42: =IFERROR(VLOOKUP(A42,'fat-05-26'!A:C,3,FALSE),"") -> 1.4514 | DX42: =SUM(DR42:DW42)/6 -> 0.82973333 | DY42: =DX42/30*45 -> 1.2446 | DZ42: 5 | EA42: =VLOOKUP(A42,Estoque!B:I,8,FALSE) -> 12.2253 | EB42: =VLOOKUP(A42,Estoque!B:N,13,FALSE) -> 20 | EC42: 15 | ED42: 20
A43: PRF10190 | B43: PERFIL U ENRIJ LQ 3,00 X 50 X 25 X 10 MM | C43: 0.0549 | H43: 7.21 | I43: 0.085 | N43: 0.055 | O43: 0.086 | P43: 0.582 | Q43: 3.785 | S43: 0.315 | T43: 0.09 | U43: 0.635 | V43: 1.9198 | W43: 0.03 | X43: 0.247 | Z43: 0.043 | AB43: 0.14 | AE43: 0.058 | AI43: 0.34 | AK43: 10.47 | AL43: 0.116 | AO43: 0.0433 | AT43: 4.018 | AV43: 0.193 | AW43: 2.972 | AY43: 1.446 | BB43: 0.058 | BD43: 0.303 | BE43: 1.275 | BF43: 0.5589 | BG43: 0.433 | BH43: 0.13 | BI43: 3.24 | BJ43: 0.1587 | BK43: 4.413 | BL43: 0.3608 | BN43: 0.405 | BP43: 0.029 | BQ43: 3.547 | BR43: 2.45 | BS43: 0.231 | BT43: 3.144 | BU43: 8.554 | BV43: 0.014 | BW43: 0.144 | BX43: 0.014 | BY43: 3.455 | BZ43: 2.015 | CA43: 0.1745 | CB43: 3.447 | CD43: 0.1885 | CF43: 0.058 | CG43: 2.682 | CH43: 1.0585 | CI43: 4 | CJ43: 1.71 | CK43: 2.29 | CL43: 4.2615 | CM43: 5.6959 | CN43: 4.7255 | CO43: 4.261 | CP43: 5.45 | CQ43: 2.01 | CR43: 5.1835 | CS43: 3.005 | CT43: 5.638 | CU43: =IFERROR(VLOOKUP(A43,'fat-01-24'!A:C,3,FALSE),"") -> 0.087 | CV43: =IFERROR(VLOOKUP(A43,'fat-02-24'!A:C,3,FALSE),"") -> 3.112 | CW43: =IFERROR(VLOOKUP(A43,'fat-03-24'!A:C,3,FALSE),"") -> 3.0953 | CX43: =IFERROR(VLOOKUP(A43,'fat-04-24'!A:C,3,FALSE),"") -> 12.2125 | CY43: =IFERROR(VLOOKUP(A43,'fat-05-24'!A:C,3,FALSE),"") -> 2.015 | CZ43: =IFERROR(VLOOKUP(A43,'fat-06-24'!A:C,3,FALSE),"") -> 4.7255 | DA43: =IFERROR(VLOOKUP(A43,'fat-07-24'!A:C,3,FALSE),"") -> 0.4785 | DB43: =IFERROR(VLOOKUP(A43,'fat-08-24'!A:D,3,FALSE),"") -> 6.028 | DC43: =IFERROR(VLOOKUP(A43,'fat-09-24'!A:C,3,FALSE),"") -> 5.179 | DD43: =IFERROR(VLOOKUP(A43,'fat-10-24'!A:C,3,FALSE),"") -> 0 | DE43: =IFERROR(VLOOKUP(A43,'fat-11-24'!A:C,3,FALSE),"") -> 4.638 | DF43: =IFERROR(VLOOKUP(A43,'fat-12-24'!A:D,3,FALSE),"") -> 4.008 | DG43: =IFERROR(VLOOKUP(A43,'fat-01-25'!A:D,3,FALSE),"") -> 4.2205 | DH43: =IFERROR(VLOOKUP(A43,'fat-02-25'!A:D,3,FALSE),"") -> 0 | DI43: =IFERROR(VLOOKUP(A43,'fat-03-25'!A:C,3,FALSE),"") -> 8.16 | DJ43: =IFERROR(VLOOKUP(A43,'fat-04-25'!A:C,3,FALSE),"") -> 6.956 | DK43: =IFERROR(VLOOKUP(A43,'fat-02-25'!A:C,3,FALSE),"") -> 0 | DL43: =IFERROR(VLOOKUP(A43,'fat-06-25'!A:C,3,FALSE),"") -> 1.277 | DM43: =IFERROR(VLOOKUP(A43,'fat-05-25'!A:C,3,FALSE),"") -> 5.366 | DN43: =IFERROR(VLOOKUP(A43,'fat-08-25'!A:C,3,FALSE),"") -> 1.439 | DO43: =IFERROR(VLOOKUP(A43,'fat-09-25'!A:C,3,FALSE),"") -> 5.5398 | DP43: =IFERROR(VLOOKUP(A43,'fat-10-25'!A:C,3,FALSE),"") -> 5.002 | DQ43: =IFERROR(VLOOKUP(A43,'fat-11-25'!A:D,3,FALSE),"") -> 0 | DR43: =IFERROR(VLOOKUP(A43,'fat-12-25'!A:D,3,FALSE),"") -> 0.0145 | DS43: =IFERROR(VLOOKUP(A43,'fat-01-26'!A:C,3,FALSE),"") | DT43: =IFERROR(VLOOKUP(A43,'fat-02-26'!A:C,3,FALSE),"") -> 0.145 | DU43: =IFERROR(VLOOKUP(A43,'fat-03-26'!A:C,3,FALSE),"") -> 2.848 | DV43: =IFERROR(VLOOKUP(A43,'fat-04-26'!A:C,3,FALSE),"") -> 3.06 | DW43: =IFERROR(VLOOKUP(A43,'fat-05-26'!A:C,3,FALSE),"") -> 0.2244 | DX43: =SUM(DR43:DW43)/6 -> 1.04865 | DY43: =DX43/30*45 -> 1.572975 | DZ43: 10 | EA43: =VLOOKUP(A43,Estoque!B:I,8,FALSE) -> 6.643 | EB43: =VLOOKUP(A43,Estoque!B:N,13,FALSE) -> 10 | EC43: 30 | ED43: 30
A44: PRF10200 | B44: PERFIL U ENRIJ LQ 3,00 X 75 X 40 X 15 MM | C44: 1.726 | D44: 2.5802 | E44: 5.9131 | F44: 1.1833 | G44: 0.47 | H44: 1.984 | I44: 2.45 | J44: 0.538 | K44: 2.763 | L44: 0.28 | M44: 3.226 | N44: 0.645 | O44: 1.759 | P44: 0.162 | Q44: 0.919 | S44: 3.211 | T44: 1.004 | U44: 2.888 | V44: 0.719 | W44: 0.685 | X44: 2.2647 | Y44: 3.6569 | Z44: 1.823 | AA44: 1.012 | AB44: 3.1003 | AD44: 6.064 | AE44: 0.308 | AF44: 1.284 | AG44: 0.231 | AH44: 7.442 | AI44: 2.017 | AJ44: 1.595 | AK44: 1.463 | AL44: 2.03 | AM44: 2.428 | AN44: 4.628 | AO44: 7.179 | AP44: 1.813 | AQ44: 4.913 | AR44: 1.303 | AS44: 3.786 | AT44: 0.023 | AU44: 1.261 | AV44: 1.299 | AW44: 1.11 | AX44: 2.245 | AY44: 2.342 | BA44: 9.217 | BB44: 0.28 | BC44: 7.572 | BD44: 1.072 | BE44: 2 | BF44: 10.186 | BG44: 5.355 | BH44: 10.0426 | BI44: 8.2255 | BJ44: 4.629 | BK44: 19.352 | BL44: 0.235 | BM44: 7.23 | BN44: 6.017 | BO44: 15.631 | BP44: 5.096 | BQ44: 3.925 | BR44: 6.118 | BS44: 2.7438 | BT44: 4.6959 | BU44: 13.413 | BV44: 4.133 | BW44: 10.882 | BX44: 2.849 | BY44: 7.9399 | BZ44: 2.3343 | CA44: 6.5939 | CB44: 6.8463 | CC44: 14.04 | CD44: 5.9919 | CE44: 6.3753 | CF44: 16.8364 | CG44: 3.7282 | CH44: 12.4076 | CI44: 5.4542 | CJ44: 7.2632 | CK44: 17.4544 | CL44: 2.6932 | CM44: 4.8402 | CN44: 19.9686 | CO44: 9.711 | CP44: 8.3328 | CQ44: 11.4844 | CR44: 9.009 | CS44: 9.3463 | CT44: 8.5886 | CU44: =IFERROR(VLOOKUP(A44,'fat-01-24'!A:C,3,FALSE),"") -> 7.0826 | CV44: =IFERROR(VLOOKUP(A44,'fat-02-24'!A:C,3,FALSE),"") -> 4.4324 | CW44: =IFERROR(VLOOKUP(A44,'fat-03-24'!A:C,3,FALSE),"") -> 9.2126 | CX44: =IFERROR(VLOOKUP(A44,'fat-04-24'!A:C,3,FALSE),"") -> 2.106 | CY44: =IFERROR(VLOOKUP(A44,'fat-05-24'!A:C,3,FALSE),"") -> 11.3 | CZ44: =IFERROR(VLOOKUP(A44,'fat-06-24'!A:C,3,FALSE),"") -> 19.9686 | DA44: =IFERROR(VLOOKUP(A44,'fat-07-24'!A:C,3,FALSE),"") -> 19.8216 | DB44: =IFERROR(VLOOKUP(A44,'fat-08-24'!A:D,3,FALSE),"") -> 15.742 | DC44: =IFERROR(VLOOKUP(A44,'fat-09-24'!A:C,3,FALSE),"") -> 6.8094 | DD44: =IFERROR(VLOOKUP(A44,'fat-10-24'!A:C,3,FALSE),"") -> 10.6002 | DE44: =IFERROR(VLOOKUP(A44,'fat-11-24'!A:C,3,FALSE),"") -> 13.8998 | DF44: =IFERROR(VLOOKUP(A44,'fat-12-24'!A:D,3,FALSE),"") -> 5.1512 | DG44: =IFERROR(VLOOKUP(A44,'fat-01-25'!A:D,3,FALSE),"") -> 6.801 | DH44: =IFERROR(VLOOKUP(A44,'fat-02-25'!A:D,3,FALSE),"") -> 6.5754 | DI44: =IFERROR(VLOOKUP(A44,'fat-03-25'!A:C,3,FALSE),"") -> 16.0416 | DJ44: =IFERROR(VLOOKUP(A44,'fat-04-25'!A:C,3,FALSE),"") -> 9.0574 | DK44: =IFERROR(VLOOKUP(A44,'fat-02-25'!A:C,3,FALSE),"") -> 6.5754 | DL44: =IFERROR(VLOOKUP(A44,'fat-06-25'!A:C,3,FALSE),"") -> 15.486 | DM44: =IFERROR(VLOOKUP(A44,'fat-05-25'!A:C,3,FALSE),"") -> 1.4544 | DN44: =IFERROR(VLOOKUP(A44,'fat-08-25'!A:C,3,FALSE),"") -> 14.7208 | DO44: =IFERROR(VLOOKUP(A44,'fat-09-25'!A:C,3,FALSE),"") -> 41.1576 | DP44: =IFERROR(VLOOKUP(A44,'fat-10-25'!A:C,3,FALSE),"") -> 19.0138 | DQ44: =IFERROR(VLOOKUP(A44,'fat-11-25'!A:D,3,FALSE),"") -> 20.3338 | DR44: =IFERROR(VLOOKUP(A44,'fat-12-25'!A:D,3,FALSE),"") -> 8.2602 | DS44: =IFERROR(VLOOKUP(A44,'fat-01-26'!A:C,3,FALSE),"") -> 14.1616 | DT44: =IFERROR(VLOOKUP(A44,'fat-02-26'!A:C,3,FALSE),"") -> 30.8476 | DU44: =IFERROR(VLOOKUP(A44,'fat-03-26'!A:C,3,FALSE),"") -> 8.5398 | DV44: =IFERROR(VLOOKUP(A44,'fat-04-26'!A:C,3,FALSE),"") -> 21.4028 | DW44: =IFERROR(VLOOKUP(A44,'fat-05-26'!A:C,3,FALSE),"") -> 5.3828 | DX44: =SUM(DR44:DW44)/6 -> 14.7658 | DY44: =DX44/30*45 -> 22.1487 | EA44: =VLOOKUP(A44,Estoque!B:I,8,FALSE) -> 29.441 | EB44: =VLOOKUP(A44,Estoque!B:N,13,FALSE) -> 0 | EC44: 15 | ED44: 25
A45: PRF10210 | B45: PERFIL U ENRIJ LQ 3,00 X 100 X 50 X 17 MM | C45: 14.624 | D45: 3.075 | E45: 10.595 | F45: 13.468 | G45: 15.517 | H45: 4.724 | I45: 8.955 | J45: 3.12 | K45: 14.7517 | L45: 5.318 | M45: 4.817 | N45: 8.477 | O45: 21.241 | P45: 0.7225 | Q45: 11.036 | R45: 1.735 | S45: 2.212 | T45: 3.663 | U45: 8.042 | V45: 1.023 | W45: 1.94 | X45: 12.736 | Y45: 4.8534 | Z45: 3.851 | AA45: 6.734 | AB45: 16.553 | AC45: 9.841 | AD45: 15.207 | AE45: 6.192 | AF45: 7.58 | AG45: 7.049 | AH45: 7.565 | AI45: 16.951 | AJ45: 17.469 | AK45: 20.042 | AL45: 5.7826 | AM45: 11.283 | AN45: 17.08 | AO45: 19.5762 | AP45: 10.881 | AQ45: 13.925 | AR45: 11.549 | AS45: 13.297 | AT45: 9.038 | AU45: 12.085 | AV45: 12.965 | AW45: 9.922 | AX45: 6.566 | AY45: 9.7491 | AZ45: 10.886 | BA45: 9.109 | BB45: 5.021 | BC45: 2.426 | BD45: 11.494 | BE45: 9.246 | BF45: 5.907 | BG45: 14.09 | BH45: 1.29 | BI45: 22.189 | BJ45: 4.815 | BK45: 15.436 | BL45: 2.274 | BM45: 23.706 | BN45: 9.875 | BO45: 3.875 | BP45: 6.08 | BQ45: 11.652 | BR45: 8.263 | BS45: 2.9855 | BT45: 8.285 | BU45: 9.814 | BV45: 6.5347 | BW45: 21.3253 | BX45: 10.938 | BY45: 19.234 | BZ45: 33.326 | CA45: 41.826 | CB45: 7.417 | CC45: 4.567 | CD45: 17.3838 | CE45: 10.1536 | CF45: 22.6006 | CG45: 11.4525 | CH45: 16.0104 | CI45: 28.3385 | CJ45: 7.6133 | CK45: 41.0753 | CL45: 16.9959 | CM45: 13.7135 | CN45: 41.063 | CO45: 25.6879 | CP45: 41.6204 | CQ45: 24.9474 | CR45: 22.4652 | CS45: 17.5117 | CT45: 31.5068 | CU45: =IFERROR(VLOOKUP(A45,'fat-01-24'!A:C,3,FALSE),"") -> 13.7076 | CV45: =IFERROR(VLOOKUP(A45,'fat-02-24'!A:C,3,FALSE),"") -> 25.1983 | CW45: =IFERROR(VLOOKUP(A45,'fat-03-24'!A:C,3,FALSE),"") -> 8.7389 | CX45: =IFERROR(VLOOKUP(A45,'fat-04-24'!A:C,3,FALSE),"") -> 44.9183 | CY45: =IFERROR(VLOOKUP(A45,'fat-05-24'!A:C,3,FALSE),"") -> 32.029 | CZ45: =IFERROR(VLOOKUP(A45,'fat-06-24'!A:C,3,FALSE),"") -> 41.063 | DA45: =IFERROR(VLOOKUP(A45,'fat-07-24'!A:C,3,FALSE),"") -> 43.0763 | DB45: =IFERROR(VLOOKUP(A45,'fat-08-24'!A:D,3,FALSE),"") -> 10.9258 | DC45: =IFERROR(VLOOKUP(A45,'fat-09-24'!A:C,3,FALSE),"") -> 28.3171 | DD45: =IFERROR(VLOOKUP(A45,'fat-10-24'!A:C,3,FALSE),"") -> 22.0669 | DE45: =IFERROR(VLOOKUP(A45,'fat-11-24'!A:C,3,FALSE),"") -> 23.1168 | DF45: =IFERROR(VLOOKUP(A45,'fat-12-24'!A:D,3,FALSE),"") -> 22.7909 | DG45: =IFERROR(VLOOKUP(A45,'fat-01-25'!A:D,3,FALSE),"") -> 19.673 | DH45: =IFERROR(VLOOKUP(A45,'fat-02-25'!A:D,3,FALSE),"") -> 4.0936 | DI45: =IFERROR(VLOOKUP(A45,'fat-03-25'!A:C,3,FALSE),"") -> 9.3836 | DJ45: =IFERROR(VLOOKUP(A45,'fat-04-25'!A:C,3,FALSE),"") -> 27.6606 | DK45: =IFERROR(VLOOKUP(A45,'fat-02-25'!A:C,3,FALSE),"") -> 4.0936 | DL45: =IFERROR(VLOOKUP(A45,'fat-06-25'!A:C,3,FALSE),"") -> 17.4711 | DM45: =IFERROR(VLOOKUP(A45,'fat-05-25'!A:C,3,FALSE),"") -> 28.2281 | DN45: =IFERROR(VLOOKUP(A45,'fat-08-25'!A:C,3,FALSE),"") -> 39.525 | DO45: =IFERROR(VLOOKUP(A45,'fat-09-25'!A:C,3,FALSE),"") -> 39.9083 | DP45: =IFERROR(VLOOKUP(A45,'fat-10-25'!A:C,3,FALSE),"") -> 5.8775 | DQ45: =IFERROR(VLOOKUP(A45,'fat-11-25'!A:D,3,FALSE),"") -> 25.9046 | DR45: =IFERROR(VLOOKUP(A45,'fat-12-25'!A:D,3,FALSE),"") -> 9.5839 | DS45: =IFERROR(VLOOKUP(A45,'fat-01-26'!A:C,3,FALSE),"") -> 2.9498 | DT45: =IFERROR(VLOOKUP(A45,'fat-02-26'!A:C,3,FALSE),"") -> 31.635 | DU45: =IFERROR(VLOOKUP(A45,'fat-03-26'!A:C,3,FALSE),"") -> 16.6909 | DV45: =IFERROR(VLOOKUP(A45,'fat-04-26'!A:C,3,FALSE),"") -> 23.4063 | DW45: =IFERROR(VLOOKUP(A45,'fat-05-26'!A:C,3,FALSE),"") -> 27.3021 | DX45: =SUM(DR45:DW45)/6 -> 18.594667 | DY45: =DX45/30*45 -> 27.892 | EA45: =VLOOKUP(A45,Estoque!B:I,8,FALSE) -> -0.594 | EB45: =VLOOKUP(A45,Estoque!B:N,13,FALSE) -> 50
A46: PRF10211 | B46: PERFIL U ENRIJ LQ 3,00 X 100 X 40 X 17 MM | D46: 3.795 | E46: 2.33 | F46: 6.08 | G46: 0.135 | I46: 0.11 | J46: 0.415 | K46: 1.91 | M46: 0.875 | N46: 0.865 | O46: 2.5 | P46: 2.831 | Q46: 1.684 | S46: 0.551 | T46: 0.046 | U46: 0.545 | V46: 0.49 | W46: 0.545 | X46: 1.258 | Z46: 0.075 | AA46: 0.71 | AB46: 1 | AD46: 0.6 | AF46: 1.98 | AG46: 0.61 | AH46: 2.065 | AI46: -1.464 | AJ46: 3.73 | AM46: 0.327 | AN46: 3.378 | AO46: 0.185 | AP46: 1.479 | AQ46: 0.38 | AR46: 0.91 | AS46: 1.384 | AT46: 0.135 | AU46: 1.065 | AV46: 0.476 | AW46: 1.01 | AX46: 1.604 | AY46: 2.495 | AZ46: 1.47 | BA46: 3.145 | BB46: 2.13 | BD46: 1.275 | BE46: 3.872 | BF46: 2.797 | BG46: 4.138 | BI46: 12.792 | BJ46: 5.565 | BK46: 4.87 | BL46: 1.551 | BM46: 26.213 | BN46: 4.707 | BO46: 5.92 | BP46: 7.669 | BQ46: 6.049 | BR46: 3.68 | BS46: 2.765 | BT46: 5.764 | BU46: 15.7446 | BV46: 1.363 | BW46: 9.073 | BX46: 13.77 | BY46: 70.37 | BZ46: 3.848 | CA46: 27.4025 | CB46: 16.9544 | CC46: 10.6106 | CD46: 25.8391 | CE46: 23.4166 | CF46: 23.8224 | CG46: 30.7455 | CH46: 7.6629 | CI46: 20.5023 | CJ46: 8.8658 | CK46: 21.9922 | CL46: 5.3967 | CN46: 3.6036 | CO46: 6.2325 | CP46: 5.7396005 | CQ46: 8.3265 | CR46: 12.2308 | CS46: 8.3265 | CT46: 10.1164 | CU46: =IFERROR(VLOOKUP(A46,'fat-01-24'!A:C,3,FALSE),"") -> 14.6226 | CV46: =IFERROR(VLOOKUP(A46,'fat-02-24'!A:C,3,FALSE),"") -> 11.0086 | CW46: =IFERROR(VLOOKUP(A46,'fat-03-24'!A:C,3,FALSE),"") -> 21.2118 | CX46: =IFERROR(VLOOKUP(A46,'fat-04-24'!A:C,3,FALSE),"") -> 3.1323 | CY46: =IFERROR(VLOOKUP(A46,'fat-05-24'!A:C,3,FALSE),"") -> 22.952601 | CZ46: =IFERROR(VLOOKUP(A46,'fat-06-24'!A:C,3,FALSE),"") -> 3.6036 | DA46: =IFERROR(VLOOKUP(A46,'fat-07-24'!A:C,3,FALSE),"") -> 24.738 | DB46: =IFERROR(VLOOKUP(A46,'fat-08-24'!A:D,3,FALSE),"") -> 33.7846 | DC46: =IFERROR(VLOOKUP(A46,'fat-09-24'!A:C,3,FALSE),"") -> 8.9342 | DD46: =IFERROR(VLOOKUP(A46,'fat-10-24'!A:C,3,FALSE),"") -> 29.4351 | DE46: =IFERROR(VLOOKUP(A46,'fat-11-24'!A:C,3,FALSE),"") -> 15.9788 | DF46: =IFERROR(VLOOKUP(A46,'fat-12-24'!A:D,3,FALSE),"") -> 22.0393 | DG46: =IFERROR(VLOOKUP(A46,'fat-01-25'!A:D,3,FALSE),"") -> 14.6652 | DH46: =IFERROR(VLOOKUP(A46,'fat-02-25'!A:D,3,FALSE),"") -> 29.3862 | DI46: =IFERROR(VLOOKUP(A46,'fat-03-25'!A:C,3,FALSE),"") -> 42.6932 | DJ46: =IFERROR(VLOOKUP(A46,'fat-04-25'!A:C,3,FALSE),"") -> 26.5822 | DK46: =IFERROR(VLOOKUP(A46,'fat-02-25'!A:C,3,FALSE),"") -> 29.3862 | DL46: =IFERROR(VLOOKUP(A46,'fat-06-25'!A:C,3,FALSE),"") -> 26.4387 | DM46: =IFERROR(VLOOKUP(A46,'fat-05-25'!A:C,3,FALSE),"") -> 15.0174 | DN46: =IFERROR(VLOOKUP(A46,'fat-08-25'!A:C,3,FALSE),"") -> 24.9584 | DO46: =IFERROR(VLOOKUP(A46,'fat-09-25'!A:C,3,FALSE),"") -> 30.5956 | DP46: =IFERROR(VLOOKUP(A46,'fat-10-25'!A:C,3,FALSE),"") -> 19.61345 | DQ46: =IFERROR(VLOOKUP(A46,'fat-11-25'!A:D,3,FALSE),"") -> 13.5051 | DR46: =IFERROR(VLOOKUP(A46,'fat-12-25'!A:D,3,FALSE),"") -> 29.4839 | DS46: =IFERROR(VLOOKUP(A46,'fat-01-26'!A:C,3,FALSE),"") -> 3.3852 | DT46: =IFERROR(VLOOKUP(A46,'fat-02-26'!A:C,3,FALSE),"") -> 17.5489 | DU46: =IFERROR(VLOOKUP(A46,'fat-03-26'!A:C,3,FALSE),"") -> 14.1073 | DV46: =IFERROR(VLOOKUP(A46,'fat-04-26'!A:C,3,FALSE),"") -> 12.9494 | DW46: =IFERROR(VLOOKUP(A46,'fat-05-26'!A:C,3,FALSE),"") -> 33.8919 | DX46: =SUM(DR46:DW46)/6 -> 18.5611 | DY46: =DX46/30*45 -> 27.84165 | EA46: =VLOOKUP(A46,Estoque!B:I,8,FALSE) -> 7.6284 | EB46: =VLOOKUP(A46,Estoque!B:N,13,FALSE) -> 40
A47: PRF10220 | B47: PERFIL U ENRIJ LQ 3,00 X 127 X 50 X 17 MM | C47: 1.41 | D47: 16.9242 | E47: 24.12 | F47: 2.055 | G47: 2.615 | H47: 4.835 | I47: 2.61 | K47: 2.646 | L47: 1.416 | M47: 18.946 | N47: 0.913 | O47: 2.675 | P47: 1.064 | Q47: 20.492 | R47: 6.49 | S47: 1.78 | T47: 0.558 | U47: 8.935 | V47: 8.009 | W47: 4.495 | X47: 10.605 | Y47: 2.172 | Z47: 0.629 | AA47: 0.31 | AB47: 4.758 | AC47: 14.067 | AD47: 2.98 | AE47: 3.238 | AF47: 1.265 | AG47: 6.759 | AH47: 3.865 | AI47: 7.7568 | AJ47: 15.865 | AK47: 4.37 | AL47: 16.14 | AM47: 11.704 | AN47: 1.819 | AO47: 7.236 | AP47: 9.224 | AQ47: 21.565 | AR47: 9.762 | AS47: 8.719 | AT47: 8.451 | AU47: 3.9096 | AV47: 9.2042 | AW47: 8.235 | AX47: 8.85 | AY47: 2.9 | AZ47: 24.107 | BA47: 5.874 | BB47: 2.2 | BC47: 10.01 | BD47: 4.172 | BE47: 10.765 | BF47: 2.977 | BG47: 30.789 | BI47: 3.226 | BJ47: 17.3242 | BK47: 6.75 | BL47: 1.67 | BM47: 0.595 | BN47: 6.474 | BO47: 2.2 | BP47: 12.527 | BQ47: 36.862 | BR47: 7.68 | BS47: 12.335 | BT47: 6.366 | BU47: 11.009 | BV47: 6.529 | BW47: 8.248 | BX47: 3.08 | BY47: 10.802 | BZ47: 11.139 | CA47: 7.027 | CB47: 3.813 | CC47: 19.85 | CD47: 1.784 | CU47: =IFERROR(VLOOKUP(A47,'fat-01-24'!A:C,3,FALSE),"") | CV47: =IFERROR(VLOOKUP(A47,'fat-02-24'!A:C,3,FALSE),"") | CW47: =IFERROR(VLOOKUP(A47,'fat-03-24'!A:C,3,FALSE),"") | CX47: =IFERROR(VLOOKUP(A47,'fat-04-24'!A:C,3,FALSE),"") | CY47: =IFERROR(VLOOKUP(A47,'fat-05-24'!A:C,3,FALSE),"") | CZ47: =IFERROR(VLOOKUP(A47,'fat-06-24'!A:C,3,FALSE),"") | DA47: =IFERROR(VLOOKUP(A47,'fat-07-24'!A:C,3,FALSE),"") | DB47: =IFERROR(VLOOKUP(A47,'fat-08-24'!A:D,3,FALSE),"") | DC47: =IFERROR(VLOOKUP(A47,'fat-09-24'!A:C,3,FALSE),"") | DD47: =IFERROR(VLOOKUP(A47,'fat-10-24'!A:C,3,FALSE),"") | DE47: =IFERROR(VLOOKUP(A47,'fat-11-24'!A:C,3,FALSE),"") | DF47: =IFERROR(VLOOKUP(A47,'fat-12-24'!A:D,3,FALSE),"") | DG47: =IFERROR(VLOOKUP(A47,'fat-01-25'!A:D,3,FALSE),"") | DH47: =IFERROR(VLOOKUP(A47,'fat-02-25'!A:D,3,FALSE),"") | DI47: =IFERROR(VLOOKUP(A47,'fat-03-25'!A:C,3,FALSE),"") | DJ47: =IFERROR(VLOOKUP(A47,'fat-04-25'!A:C,3,FALSE),"") | DK47: =IFERROR(VLOOKUP(A47,'fat-02-25'!A:C,3,FALSE),"") | DL47: =IFERROR(VLOOKUP(A47,'fat-06-25'!A:C,3,FALSE),"") | DM47: =IFERROR(VLOOKUP(A47,'fat-05-25'!A:C,3,FALSE),"") | DN47: =IFERROR(VLOOKUP(A47,'fat-08-25'!A:C,3,FALSE),"") | DO47: =IFERROR(VLOOKUP(A47,'fat-09-25'!A:C,3,FALSE),"") | DP47: =IFERROR(VLOOKUP(A47,'fat-10-25'!A:C,3,FALSE),"") | DQ47: =IFERROR(VLOOKUP(A47,'fat-11-25'!A:D,3,FALSE),"") | DR47: =IFERROR(VLOOKUP(A47,'fat-12-25'!A:D,3,FALSE),"") | DS47: =IFERROR(VLOOKUP(A47,'fat-01-26'!A:C,3,FALSE),"") | DT47: =IFERROR(VLOOKUP(A47,'fat-02-26'!A:C,3,FALSE),"") | DU47: =IFERROR(VLOOKUP(A47,'fat-03-26'!A:C,3,FALSE),"") | DV47: =IFERROR(VLOOKUP(A47,'fat-04-26'!A:C,3,FALSE),"") | DW47: =IFERROR(VLOOKUP(A47,'fat-05-26'!A:C,3,FALSE),"") | DX47: =SUM(DR47:DW47)/6 -> 0 | DY47: =DX47/30*45 -> 0 | EB47: =VLOOKUP(A47,Estoque!B:N,13,FALSE) -> #N/A
A48: PRF10221 | B48: PERFIL U ENRIJ LQ 3,00 X 127 X 50 X 17 MM | CD48: 35.8768 | CE48: 1.21 | CF48: 20.615 | CG48: 13.405 | CH48: 24.455 | CI48: 20.683 | CJ48: 12.835 | CK48: 17.6072 | CL48: 35.328 | CM48: 22.67 | CN48: 12.389 | CO48: 12.191999 | CP48: 20.1914 | CQ48: 18.43 | CR48: 23.675 | CS48: 8.135 | CT48: 52.5019 | CU48: =IFERROR(VLOOKUP(A48,'fat-01-24'!A:C,3,FALSE),"") -> 13.3787 | CV48: =IFERROR(VLOOKUP(A48,'fat-02-24'!A:C,3,FALSE),"") -> 20.9132 | CW48: =IFERROR(VLOOKUP(A48,'fat-03-24'!A:C,3,FALSE),"") -> 16.381 | CX48: =IFERROR(VLOOKUP(A48,'fat-04-24'!A:C,3,FALSE),"") -> 20.035 | CY48: =IFERROR(VLOOKUP(A48,'fat-05-24'!A:C,3,FALSE),"") -> 13.4484 | CZ48: =IFERROR(VLOOKUP(A48,'fat-06-24'!A:C,3,FALSE),"") -> 12.389 | DA48: =IFERROR(VLOOKUP(A48,'fat-07-24'!A:C,3,FALSE),"") -> 28.82 | DB48: =IFERROR(VLOOKUP(A48,'fat-08-24'!A:D,3,FALSE),"") -> 47.095 | DC48: =IFERROR(VLOOKUP(A48,'fat-09-24'!A:C,3,FALSE),"") -> 15.4768 | DD48: =IFERROR(VLOOKUP(A48,'fat-10-24'!A:C,3,FALSE),"") -> 34.2164 | DE48: =IFERROR(VLOOKUP(A48,'fat-11-24'!A:C,3,FALSE),"") -> 13.7712 | DF48: =IFERROR(VLOOKUP(A48,'fat-12-24'!A:D,3,FALSE),"") -> 15.4286 | DG48: =IFERROR(VLOOKUP(A48,'fat-01-25'!A:D,3,FALSE),"") -> 14.94698 | DH48: =IFERROR(VLOOKUP(A48,'fat-02-25'!A:D,3,FALSE),"") -> 15.666 | DI48: =IFERROR(VLOOKUP(A48,'fat-03-25'!A:C,3,FALSE),"") -> 18.565 | DJ48: =IFERROR(VLOOKUP(A48,'fat-04-25'!A:C,3,FALSE),"") -> 56.4126 | DK48: =IFERROR(VLOOKUP(A48,'fat-02-25'!A:C,3,FALSE),"") -> 15.666 | DL48: =IFERROR(VLOOKUP(A48,'fat-06-25'!A:C,3,FALSE),"") -> 20.516 | DM48: =IFERROR(VLOOKUP(A48,'fat-05-25'!A:C,3,FALSE),"") -> 6.5022654 | DN48: =IFERROR(VLOOKUP(A48,'fat-08-25'!A:C,3,FALSE),"") -> 20.5662 | DO48: =IFERROR(VLOOKUP(A48,'fat-09-25'!A:C,3,FALSE),"") -> 23.27 | DP48: =IFERROR(VLOOKUP(A48,'fat-10-25'!A:C,3,FALSE),"") -> 19.1336 | DQ48: =IFERROR(VLOOKUP(A48,'fat-11-25'!A:D,3,FALSE),"") -> 14.453 | DR48: =IFERROR(VLOOKUP(A48,'fat-12-25'!A:D,3,FALSE),"") -> 22.05 | DS48: =IFERROR(VLOOKUP(A48,'fat-01-26'!A:C,3,FALSE),"") -> 28.463 | DT48: =IFERROR(VLOOKUP(A48,'fat-02-26'!A:C,3,FALSE),"") -> 27.8998 | DU48: =IFERROR(VLOOKUP(A48,'fat-03-26'!A:C,3,FALSE),"") -> 17.9594 | DV48: =IFERROR(VLOOKUP(A48,'fat-04-26'!A:C,3,FALSE),"") -> 28.34 | DW48: =IFERROR(VLOOKUP(A48,'fat-05-26'!A:C,3,FALSE),"") -> 13.753 | DX48: =SUM(DR48:DW48)/6 -> 23.077533 | DY48: =DX48/30*45 -> 34.6163 | DZ48: 30 | EA48: =VLOOKUP(A48,Estoque!B:I,8,FALSE) -> 23.3504 | EB48: =VLOOKUP(A48,Estoque!B:N,13,FALSE) -> 0
A49: PRF10229 | B49: PERFIL U ENRIJ LQ 3,00 X 150 X50 X 20 MM | BA49: 3.216 | BB49: 0.96 | BC49: 1.555 | BF49: 5.285 | BG49: 9.175 | BH49: 5.864 | BJ49: 12.065 | BK49: 0.19 | BL49: 1.16 | BM49: 9.099 | BN49: 9.2414 | BO49: 1.69 | BP49: 3.372 | BQ49: 8.121 | BR49: 2.555 | BS49: 1.505 | BT49: 6.873 | BU49: 8.792 | BV49: 2.326 | BW49: 1.185 | BX49: 1.27 | BY49: 6.787 | BZ49: 5.645 | CA49: 9.468 | CC49: 4.4632 | CD49: 1.39 | CE49: 11.1614 | CF49: 3.157 | CG49: 3.3156 | CH49: 22.2396 | CI49: 5.6564 | CJ49: 8.39 | CK49: 13.8205 | CL49: 0.847 | CM49: 7.191 | CN49: 4.3199 | CO49: 18.544 | CP49: 6.729 | CQ49: 5.0435 | CR49: 21.708 | CS49: 9.959 | CT49: 21.66 | CU49: =IFERROR(VLOOKUP(A49,'fat-01-24'!A:C,3,FALSE),"") -> 4.543 | CV49: =IFERROR(VLOOKUP(A49,'fat-02-24'!A:C,3,FALSE),"") -> 20.8517 | CW49: =IFERROR(VLOOKUP(A49,'fat-03-24'!A:C,3,FALSE),"") -> 29.4341 | CX49: =IFERROR(VLOOKUP(A49,'fat-04-24'!A:C,3,FALSE),"") -> 0.8064 | CY49: =IFERROR(VLOOKUP(A49,'fat-05-24'!A:C,3,FALSE),"") -> 27.833 | CZ49: =IFERROR(VLOOKUP(A49,'fat-06-24'!A:C,3,FALSE),"") -> 4.3199 | DA49: =IFERROR(VLOOKUP(A49,'fat-07-24'!A:C,3,FALSE),"") -> 19.1335 | DB49: =IFERROR(VLOOKUP(A49,'fat-08-24'!A:D,3,FALSE),"") -> 14.7625 | DC49: =IFERROR(VLOOKUP(A49,'fat-09-24'!A:C,3,FALSE),"") -> 8.475 | DD49: =IFERROR(VLOOKUP(A49,'fat-10-24'!A:C,3,FALSE),"") -> 11.611 | DE49: =IFERROR(VLOOKUP(A49,'fat-11-24'!A:C,3,FALSE),"") -> 17.974 | DF49: =IFERROR(VLOOKUP(A49,'fat-12-24'!A:D,3,FALSE),"") -> 11.6919 | DG49: =IFERROR(VLOOKUP(A49,'fat-01-25'!A:D,3,FALSE),"") -> 12.74 | DH49: =IFERROR(VLOOKUP(A49,'fat-02-25'!A:D,3,FALSE),"") -> 10.8125 | DI49: =IFERROR(VLOOKUP(A49,'fat-03-25'!A:C,3,FALSE),"") -> 9.1755 | DJ49: =IFERROR(VLOOKUP(A49,'fat-04-25'!A:C,3,FALSE),"") -> 22.4062 | DK49: =IFERROR(VLOOKUP(A49,'fat-02-25'!A:C,3,FALSE),"") -> 10.8125 | DL49: =IFERROR(VLOOKUP(A49,'fat-06-25'!A:C,3,FALSE),"") -> 15.4125 | DM49: =IFERROR(VLOOKUP(A49,'fat-05-25'!A:C,3,FALSE),"") -> 0.385 | DN49: =IFERROR(VLOOKUP(A49,'fat-08-25'!A:C,3,FALSE),"") -> 15.7405 | DO49: =IFERROR(VLOOKUP(A49,'fat-09-25'!A:C,3,FALSE),"") -> 17.085 | DP49: =IFERROR(VLOOKUP(A49,'fat-10-25'!A:C,3,FALSE),"") -> 9.836 | DQ49: =IFERROR(VLOOKUP(A49,'fat-11-25'!A:D,3,FALSE),"") -> 12.8842 | DR49: =IFERROR(VLOOKUP(A49,'fat-12-25'!A:D,3,FALSE),"") -> 7.5075 | DS49: =IFERROR(VLOOKUP(A49,'fat-01-26'!A:C,3,FALSE),"") -> 5.697 | DT49: =IFERROR(VLOOKUP(A49,'fat-02-26'!A:C,3,FALSE),"") -> 2.464 | DU49: =IFERROR(VLOOKUP(A49,'fat-03-26'!A:C,3,FALSE),"") -> 16.0635 | DV49: =IFERROR(VLOOKUP(A49,'fat-04-26'!A:C,3,FALSE),"") -> 24.0105 | DW49: =IFERROR(VLOOKUP(A49,'fat-05-26'!A:C,3,FALSE),"") -> 5.4155 | DX49: =SUM(DR49:DW49)/6 -> 10.193 | DY49: =DX49/30*45 -> 15.2895 | DZ49: 35 | EA49: =VLOOKUP(A49,Estoque!B:I,8,FALSE) -> -7.7983 | EB49: =VLOOKUP(A49,Estoque!B:N,13,FALSE) -> 0
A50: PRF10230 | B50: PERFIL U ENRIJ LQ 3,00 X 150 X 60 X 20 MM | C50: 18.986 | D50: 6.464 | E50: 28.266 | F50: 31.868 | G50: 8.9043 | H50: 43.684 | I50: 5.095 | J50: 23.749 | K50: 1.365 | L50: 17.313 | M50: 1.715 | N50: 9.768 | O50: 4.231 | P50: 3.166 | Q50: 8.691 | R50: 9.748 | S50: 25.343 | T50: 7.001 | U50: 24.598 | V50: 18.175 | W50: 10.019 | X50: 12.3304 | Y50: 22.775 | Z50: 7.095 | AA50: 15.65 | AB50: 18.747 | AC50: 11.984 | AD50: 32.352 | AE50: 7.422 | AF50: 12.385 | AG50: 19.473 | AH50: 20.978 | AI50: 12.231 | AJ50: 15.938 | AK50: 9.233 | AL50: 20.543 | AM50: 10.072 | AN50: 23.11 | AO50: 29.775 | AP50: 9.431 | AQ50: 4.049 | AR50: 32.637 | AS50: 18.893 | AT50: 31.92 | AU50: 7.449 | AV50: 25.074 | AW50: 29.788 | AX50: 8.107 | AY50: 16.442 | AZ50: 26.5 | BA50: 16.539 | BB50: 8.602 | BC50: 27.927 | BD50: 13.823 | BE50: 24.1408 | BF50: 31.309 | BG50: 36.0877 | BH50: 40.787 | BI50: 4.218 | BJ50: 22.444 | BK50: 39.352 | BL50: 38.7409 | BM50: 55.152 | BN50: 25.051 | BO50: 0.164 | BP50: 28.463 | BQ50: 28.274 | BR50: 32.6417 | BS50: 34.142 | BT50: 20.369 | BU50: 50.4818 | BV50: 13.555 | BW50: 33.861 | BX50: 31.525 | BY50: 81.0759 | BZ50: 19.734 | CA50: 42.2461 | CB50: 31.816 | CC50: 16.449 | CD50: 33.1754 | CE50: 84.2974 | CF50: 39.403 | CG50: 79.396701 | CH50: 6.929 | CI50: 66.177 | CJ50: 90.9112 | CK50: 24.55 | CL50: 16.2734 | CM50: 20.8549 | CN50: 49.069 | CO50: 33.09 | CP50: 25.1234 | CQ50: 41.2224 | CR50: 36.5782 | CS50: 41.2376 | CT50: 20.5452 | CU50: =IFERROR(VLOOKUP(A50,'fat-01-24'!A:C,3,FALSE),"") -> 11.198 | CV50: =IFERROR(VLOOKUP(A50,'fat-02-24'!A:C,3,FALSE),"") -> 14.6634 | CW50: =IFERROR(VLOOKUP(A50,'fat-03-24'!A:C,3,FALSE),"") -> 58.6334 | CX50: =IFERROR(VLOOKUP(A50,'fat-04-24'!A:C,3,FALSE),"") -> 22.59 | CY50: =IFERROR(VLOOKUP(A50,'fat-05-24'!A:C,3,FALSE),"") -> 37.2991 | CZ50: =IFERROR(VLOOKUP(A50,'fat-06-24'!A:C,3,FALSE),"") -> 49.069 | DA50: =IFERROR(VLOOKUP(A50,'fat-07-24'!A:C,3,FALSE),"") -> 42.284 | DB50: =IFERROR(VLOOKUP(A50,'fat-08-24'!A:D,3,FALSE),"") -> 31.019 | DC50: =IFERROR(VLOOKUP(A50,'fat-09-24'!A:C,3,FALSE),"") -> 37.23 | DD50: =IFERROR(VLOOKUP(A50,'fat-10-24'!A:C,3,FALSE),"") -> 48.9214 | DE50: =IFERROR(VLOOKUP(A50,'fat-11-24'!A:C,3,FALSE),"") -> 23.836 | DF50: =IFERROR(VLOOKUP(A50,'fat-12-24'!A:D,3,FALSE),"") -> 51.533439 | DG50: =IFERROR(VLOOKUP(A50,'fat-01-25'!A:D,3,FALSE),"") -> 22.377 | DH50: =IFERROR(VLOOKUP(A50,'fat-02-25'!A:D,3,FALSE),"") -> 22.615 | DI50: =IFERROR(VLOOKUP(A50,'fat-03-25'!A:C,3,FALSE),"") -> 21.566 | DJ50: =IFERROR(VLOOKUP(A50,'fat-04-25'!A:C,3,FALSE),"") -> 44.5112 | DK50: =IFERROR(VLOOKUP(A50,'fat-02-25'!A:C,3,FALSE),"") -> 22.615 | DL50: =IFERROR(VLOOKUP(A50,'fat-06-25'!A:C,3,FALSE),"") -> 49.81291 | DM50: =IFERROR(VLOOKUP(A50,'fat-05-25'!A:C,3,FALSE),"") -> 22.4094 | DN50: =IFERROR(VLOOKUP(A50,'fat-08-25'!A:C,3,FALSE),"") -> 52.286 | DO50: =IFERROR(VLOOKUP(A50,'fat-09-25'!A:C,3,FALSE),"") -> 34.4222 | DP50: =IFERROR(VLOOKUP(A50,'fat-10-25'!A:C,3,FALSE),"") -> 32.7908 | DQ50: =IFERROR(VLOOKUP(A50,'fat-11-25'!A:D,3,FALSE),"") -> 19.9622 | DR50: =IFERROR(VLOOKUP(A50,'fat-12-25'!A:D,3,FALSE),"") -> 26.043 | DS50: =IFERROR(VLOOKUP(A50,'fat-01-26'!A:C,3,FALSE),"") -> 26.8448 | DT50: =IFERROR(VLOOKUP(A50,'fat-02-26'!A:C,3,FALSE),"") -> 21.6092 | DU50: =IFERROR(VLOOKUP(A50,'fat-03-26'!A:C,3,FALSE),"") -> 14.5222 | DV50: =IFERROR(VLOOKUP(A50,'fat-04-26'!A:C,3,FALSE),"") -> 31.483 | DW50: =IFERROR(VLOOKUP(A50,'fat-05-26'!A:C,3,FALSE),"") -> 3.9022 | DX50: =SUM(DR50:DW50)/6 -> 20.734067 | DY50: =DX50/30*45 -> 31.1011 | DZ50: 50 | EA50: =VLOOKUP(A50,Estoque!B:I,8,FALSE) -> -15.9813 | EB50: =VLOOKUP(A50,Estoque!B:N,13,FALSE) -> 20 | ED50: 10 | EE50: 10
A51: PRF10240 | B51: PERFIL U ENRIJ LQ 3,00 X 200 X 75 X 20 MM | J51: 4.004 | L51: 20 | M51: 3.76 | N51: 7.309 | O51: 2.7483 | P51: 2.215 | Q51: 7.897 | S51: 18.666 | T51: 6.026 | U51: 5.211 | V51: 16.743 | W51: 2.214 | X51: 2 | Y51: 11.264 | Z51: 5.745 | AA51: 5.881 | AB51: 11.691 | AC51: 32.544 | AD51: 39.66 | AE51: 3.341 | AF51: 7.967 | AG51: 23.175 | AH51: 21.271 | AI51: 10.894 | AJ51: 6.587 | AK51: 3.232 | AL51: 19.491 | AM51: 9.422 | AN51: 13.101 | AO51: 7.449 | AP51: 1.077 | AQ51: 2.304 | AR51: 36.315 | AS51: 21.065 | AT51: 3.89 | AU51: 16.001 | AV51: 42.715 | AW51: 11.463 | AX51: 9.998 | AY51: 13.256 | AZ51: 12.728 | BA51: 14.772 | BB51: 7.515 | BC51: 2.145 | BD51: 10.682 | BE51: 18.32 | BF51: 13.379 | BG51: 15.459 | BH51: 11.4372 | BI51: 0.8621 | BJ51: 19.482 | BK51: 3.704 | BL51: 98.946 | BM51: 37.197 | BN51: 19.386 | BO51: 27.517 | BP51: 29.663 | BQ51: 59.1854 | BR51: 62.883 | BS51: 36.614 | BT51: 7.253 | BU51: 70.582 | BV51: 40.679 | BW51: 24.55 | BX51: 18.622 | BY51: 57.832 | BZ51: 28.4402 | CA51: 14.88 | CB51: 21.101 | CC51: 13.3627 | CD51: 15.6 | CU51: =IFERROR(VLOOKUP(A51,'fat-01-24'!A:C,3,FALSE),"") | CV51: =IFERROR(VLOOKUP(A51,'fat-02-24'!A:C,3,FALSE),"") | CW51: =IFERROR(VLOOKUP(A51,'fat-03-24'!A:C,3,FALSE),"") | CX51: =IFERROR(VLOOKUP(A51,'fat-04-24'!A:C,3,FALSE),"") | CY51: =IFERROR(VLOOKUP(A51,'fat-05-24'!A:C,3,FALSE),"") | CZ51: =IFERROR(VLOOKUP(A51,'fat-06-24'!A:C,3,FALSE),"") | DA51: =IFERROR(VLOOKUP(A51,'fat-07-24'!A:C,3,FALSE),"") | DB51: =IFERROR(VLOOKUP(A51,'fat-08-24'!A:D,3,FALSE),"") | DC51: =IFERROR(VLOOKUP(A51,'fat-09-24'!A:C,3,FALSE),"") | DD51: =IFERROR(VLOOKUP(A51,'fat-10-24'!A:C,3,FALSE),"") | DE51: =IFERROR(VLOOKUP(A51,'fat-11-24'!A:C,3,FALSE),"") | DF51: =IFERROR(VLOOKUP(A51,'fat-12-24'!A:D,3,FALSE),"") | DG51: =IFERROR(VLOOKUP(A51,'fat-01-25'!A:D,3,FALSE),"") | DH51: =IFERROR(VLOOKUP(A51,'fat-02-25'!A:D,3,FALSE),"") | DI51: =IFERROR(VLOOKUP(A51,'fat-03-25'!A:C,3,FALSE),"") | DJ51: =IFERROR(VLOOKUP(A51,'fat-04-25'!A:C,3,FALSE),"") | DK51: =IFERROR(VLOOKUP(A51,'fat-02-25'!A:C,3,FALSE),"") | DL51: =IFERROR(VLOOKUP(A51,'fat-06-25'!A:C,3,FALSE),"") | DM51: =IFERROR(VLOOKUP(A51,'fat-05-25'!A:C,3,FALSE),"") | DN51: =IFERROR(VLOOKUP(A51,'fat-08-25'!A:C,3,FALSE),"") | DO51: =IFERROR(VLOOKUP(A51,'fat-09-25'!A:C,3,FALSE),"") | DP51: =IFERROR(VLOOKUP(A51,'fat-10-25'!A:C,3,FALSE),"") | DQ51: =IFERROR(VLOOKUP(A51,'fat-11-25'!A:D,3,FALSE),"") | DR51: =IFERROR(VLOOKUP(A51,'fat-12-25'!A:D,3,FALSE),"") | DS51: =IFERROR(VLOOKUP(A51,'fat-01-26'!A:C,3,FALSE),"") | DT51: =IFERROR(VLOOKUP(A51,'fat-02-26'!A:C,3,FALSE),"") | DU51: =IFERROR(VLOOKUP(A51,'fat-03-26'!A:C,3,FALSE),"") | DV51: =IFERROR(VLOOKUP(A51,'fat-04-26'!A:C,3,FALSE),"") | DW51: =IFERROR(VLOOKUP(A51,'fat-05-26'!A:C,3,FALSE),"") | DX51: =SUM(DR51:DW51)/6 -> 0 | DY51: =DX51/30*45 -> 0 | EB51: =VLOOKUP(A51,Estoque!B:N,13,FALSE) -> #N/A | EC51: 20 | ED51: 20
A52: PRF10255 | B52: PERFIL U ENRIJ LQ 3,00 X 200 X 75 X 20 MM | CD52: 19.7206 | CE52: 21.5696 | CF52: 33.6566 | CG52: 18.1008 | CH52: 20.9132 | CI52: 15.5159 | CJ52: 13.4431 | CK52: 14.2585 | CL52: 48.8743 | CM52: 13.4988 | CN52: 19.2958 | CO52: 43.2639 | CP52: 19.1596 | CQ52: 38.1179 | CR52: 30.4044 | CS52: 60.1791 | CT52: 14.227 | CU52: =IFERROR(VLOOKUP(A52,'fat-01-24'!A:C,3,FALSE),"") -> 32.3166 | CV52: =IFERROR(VLOOKUP(A52,'fat-02-24'!A:C,3,FALSE),"") -> 70.837 | CW52: =IFERROR(VLOOKUP(A52,'fat-03-24'!A:C,3,FALSE),"") -> 15.9549 | CX52: =IFERROR(VLOOKUP(A52,'fat-04-24'!A:C,3,FALSE),"") -> 27.2747 | CY52: =IFERROR(VLOOKUP(A52,'fat-05-24'!A:C,3,FALSE),"") -> 24.3461 | CZ52: =IFERROR(VLOOKUP(A52,'fat-06-24'!A:C,3,FALSE),"") -> 19.2958 | DA52: =IFERROR(VLOOKUP(A52,'fat-07-24'!A:C,3,FALSE),"") -> 78.85612 | DB52: =IFERROR(VLOOKUP(A52,'fat-08-24'!A:D,3,FALSE),"") -> 40.2411 | DC52: =IFERROR(VLOOKUP(A52,'fat-09-24'!A:C,3,FALSE),"") -> 42.7766 | DD52: =IFERROR(VLOOKUP(A52,'fat-10-24'!A:C,3,FALSE),"") -> 36.1096 | DE52: =IFERROR(VLOOKUP(A52,'fat-11-24'!A:C,3,FALSE),"") -> 43.857 | DF52: =IFERROR(VLOOKUP(A52,'fat-12-24'!A:D,3,FALSE),"") -> 28.382 | DG52: =IFERROR(VLOOKUP(A52,'fat-01-25'!A:D,3,FALSE),"") -> 8.9746 | DH52: =IFERROR(VLOOKUP(A52,'fat-02-25'!A:D,3,FALSE),"") -> 13.3007 | DI52: =IFERROR(VLOOKUP(A52,'fat-03-25'!A:C,3,FALSE),"") -> 17.734 | DJ52: =IFERROR(VLOOKUP(A52,'fat-04-25'!A:C,3,FALSE),"") -> 27.0578 | DK52: =IFERROR(VLOOKUP(A52,'fat-02-25'!A:C,3,FALSE),"") -> 13.3007 | DL52: =IFERROR(VLOOKUP(A52,'fat-06-25'!A:C,3,FALSE),"") -> 23.9091 | DM52: =IFERROR(VLOOKUP(A52,'fat-05-25'!A:C,3,FALSE),"") -> 19.4294 | DN52: =IFERROR(VLOOKUP(A52,'fat-08-25'!A:C,3,FALSE),"") -> 40.3742 | DO52: =IFERROR(VLOOKUP(A52,'fat-09-25'!A:C,3,FALSE),"") -> 27.8613 | DP52: =IFERROR(VLOOKUP(A52,'fat-10-25'!A:C,3,FALSE),"") -> 29.0672 | DQ52: =IFERROR(VLOOKUP(A52,'fat-11-25'!A:D,3,FALSE),"") -> 9.81 | DR52: =IFERROR(VLOOKUP(A52,'fat-12-25'!A:D,3,FALSE),"") -> 28.454 | DS52: =IFERROR(VLOOKUP(A52,'fat-01-26'!A:C,3,FALSE),"") -> 12.61 | DT52: =IFERROR(VLOOKUP(A52,'fat-02-26'!A:C,3,FALSE),"") -> 29.1097 | DU52: =IFERROR(VLOOKUP(A52,'fat-03-26'!A:C,3,FALSE),"") -> 10.6312 | DV52: =IFERROR(VLOOKUP(A52,'fat-04-26'!A:C,3,FALSE),"") -> 104.7461 | DW52: =IFERROR(VLOOKUP(A52,'fat-05-26'!A:C,3,FALSE),"") -> 46.4996 | DX52: =SUM(DR52:DW52)/6 -> 38.6751 | DY52: =DX52/30*45 -> 58.01265 | DZ52: 50 | EA52: =VLOOKUP(A52,Estoque!B:I,8,FALSE) -> 12.5721 | EB52: =VLOOKUP(A52,Estoque!B:N,13,FALSE) -> 40 | EC52: 21 | ED52: 21
A53: PRF10241 | B53: PERFIL U ENRIJ LQ 3,00 X 200 X 60 X 20 MM | C53: 1.878 | D53: 3.312 | E53: 4.759 | F53: 5.286 | G53: 15.61 | H53: 9.13 | I53: 8.295 | J53: 0.972 | L53: 1.07 | M53: 17.753 | N53: 2.245 | O53: 2.202 | P53: 1.05 | Q53: 9.565 | S53: 3.431 | T53: 2.89 | U53: 1.005 | W53: 0.095 | X53: 0.855 | Y53: 3.536 | Z53: 0.382 | AB53: 0.55 | AC53: 0.19 | AD53: 6.353 | AE53: 0.686 | AF53: 0.537 | AG53: 0.237 | AH53: 3.665 | AI53: 0.27 | AJ53: 1.056 | AK53: 0.382 | AL53: 0.637 | AM53: 0.441 | AP53: 1.36 | AR53: 0.049 | AS53: 5.157 | AT53: 4.594 | AU53: 0.525 | AW53: 2.057 | AX53: 1.91 | AY53: 0.318 | BE53: 0.238 | BI53: 0.098 | BN53: 0.162 | BO53: 0.24 | BY53: 0.44 | CB53: 1.676 | CC53: 0.862 | CD53: 2.1045 | CF53: 2.08 | CG53: 7.284 | CH53: 0.5454 | CI53: 6.684 | CJ53: 7.319 | CK53: 2.925 | CL53: 5.75 | CM53: 1.029 | CN53: 5.369 | CO53: 1.47 | CP53: 3.51 | CQ53: 2.896 | CR53: 8.163 | CS53: 1.421 | CT53: 2.401 | CU53: =IFERROR(VLOOKUP(A53,'fat-01-24'!A:C,3,FALSE),"") -> 4.6926 | CV53: =IFERROR(VLOOKUP(A53,'fat-02-24'!A:C,3,FALSE),"") -> 1.764 | CW53: =IFERROR(VLOOKUP(A53,'fat-03-24'!A:C,3,FALSE),"") | CX53: =IFERROR(VLOOKUP(A53,'fat-04-24'!A:C,3,FALSE),"") | CY53: =IFERROR(VLOOKUP(A53,'fat-05-24'!A:C,3,FALSE),"") | CZ53: =IFERROR(VLOOKUP(A53,'fat-06-24'!A:C,3,FALSE),"") -> 5.369 | DA53: =IFERROR(VLOOKUP(A53,'fat-07-24'!A:C,3,FALSE),"") -> 30.784 | DB53: =IFERROR(VLOOKUP(A53,'fat-08-24'!A:D,3,FALSE),"") -> 3.72 | DC53: =IFERROR(VLOOKUP(A53,'fat-09-24'!A:C,3,FALSE),"") -> 3.245 | DD53: =IFERROR(VLOOKUP(A53,'fat-10-24'!A:C,3,FALSE),"") -> 28.24 | DE53: =IFERROR(VLOOKUP(A53,'fat-11-24'!A:C,3,FALSE),"") -> 18.307 | DF53: =IFERROR(VLOOKUP(A53,'fat-12-24'!A:D,3,FALSE),"") -> 5.4399 | DG53: =IFERROR(VLOOKUP(A53,'fat-01-25'!A:D,3,FALSE),"") -> 4.018 | DH53: =IFERROR(VLOOKUP(A53,'fat-02-25'!A:D,3,FALSE),"") -> 8.553 | DI53: =IFERROR(VLOOKUP(A53,'fat-03-25'!A:C,3,FALSE),"") -> 9.166 | DJ53: =IFERROR(VLOOKUP(A53,'fat-04-25'!A:C,3,FALSE),"") -> 2.548 | DK53: =IFERROR(VLOOKUP(A53,'fat-02-25'!A:C,3,FALSE),"") -> 8.553 | DL53: =IFERROR(VLOOKUP(A53,'fat-06-25'!A:C,3,FALSE),"") -> 0.37 | DM53: =IFERROR(VLOOKUP(A53,'fat-05-25'!A:C,3,FALSE),"") -> 0.049 | DN53: =IFERROR(VLOOKUP(A53,'fat-08-25'!A:C,3,FALSE),"") -> 9.139 | DO53: =IFERROR(VLOOKUP(A53,'fat-09-25'!A:C,3,FALSE),"") -> 4.853 | DP53: =IFERROR(VLOOKUP(A53,'fat-10-25'!A:C,3,FALSE),"") -> 6.958 | DQ53: =IFERROR(VLOOKUP(A53,'fat-11-25'!A:D,3,FALSE),"") -> 8.748 | DR53: =IFERROR(VLOOKUP(A53,'fat-12-25'!A:D,3,FALSE),"") -> 4.0035 | DS53: =IFERROR(VLOOKUP(A53,'fat-01-26'!A:C,3,FALSE),"") -> 4.263 | DT53: =IFERROR(VLOOKUP(A53,'fat-02-26'!A:C,3,FALSE),"") -> 2.842 | DU53: =IFERROR(VLOOKUP(A53,'fat-03-26'!A:C,3,FALSE),"") -> 2.9934 | DV53: =IFERROR(VLOOKUP(A53,'fat-04-26'!A:C,3,FALSE),"") -> 11.012 | DW53: =IFERROR(VLOOKUP(A53,'fat-05-26'!A:C,3,FALSE),"") -> 20.0606 | DX53: =SUM(DR53:DW53)/6 -> 7.5290833 | DY53: =DX53/30*45 -> 11.293625 | DZ53: 13 | EA53: =VLOOKUP(A53,Estoque!B:I,8,FALSE) -> 2.521 | EB53: =VLOOKUP(A53,Estoque!B:N,13,FALSE) -> 0 | EC53: 15 | ED53: 10
A54: PRF10242 | B54: PERFIL U ENRIJ LQ 3,00 X 200 X 85 X 25 MM | BU54: 1.948 | CU54: =IFERROR(VLOOKUP(A54,'fat-01-24'!A:C,3,FALSE),"") | CV54: =IFERROR(VLOOKUP(A54,'fat-02-24'!A:C,3,FALSE),"") | CW54: =IFERROR(VLOOKUP(A54,'fat-03-24'!A:C,3,FALSE),"") | CX54: =IFERROR(VLOOKUP(A54,'fat-04-24'!A:C,3,FALSE),"") | CY54: =IFERROR(VLOOKUP(A54,'fat-05-24'!A:C,3,FALSE),"") | CZ54: =IFERROR(VLOOKUP(A54,'fat-06-24'!A:C,3,FALSE),"") | DA54: =IFERROR(VLOOKUP(A54,'fat-07-24'!A:C,3,FALSE),"") | DB54: =IFERROR(VLOOKUP(A54,'fat-08-24'!A:D,3,FALSE),"") | DC54: =IFERROR(VLOOKUP(A54,'fat-09-24'!A:C,3,FALSE),"") | DD54: =IFERROR(VLOOKUP(A54,'fat-10-24'!A:C,3,FALSE),"") | DE54: =IFERROR(VLOOKUP(A54,'fat-11-24'!A:C,3,FALSE),"") | DF54: =IFERROR(VLOOKUP(A54,'fat-12-24'!A:D,3,FALSE),"") | DG54: =IFERROR(VLOOKUP(A54,'fat-01-25'!A:D,3,FALSE),"") | DH54: =IFERROR(VLOOKUP(A54,'fat-02-25'!A:D,3,FALSE),"") | DI54: =IFERROR(VLOOKUP(A54,'fat-03-25'!A:C,3,FALSE),"") | DJ54: =IFERROR(VLOOKUP(A54,'fat-04-25'!A:C,3,FALSE),"") | DK54: =IFERROR(VLOOKUP(A54,'fat-02-25'!A:C,3,FALSE),"") | DL54: =IFERROR(VLOOKUP(A54,'fat-06-25'!A:C,3,FALSE),"") | DM54: =IFERROR(VLOOKUP(A54,'fat-05-25'!A:C,3,FALSE),"") | DN54: =IFERROR(VLOOKUP(A54,'fat-08-25'!A:C,3,FALSE),"") | DO54: =IFERROR(VLOOKUP(A54,'fat-09-25'!A:C,3,FALSE),"") | DP54: =IFERROR(VLOOKUP(A54,'fat-10-25'!A:C,3,FALSE),"") | DQ54: =IFERROR(VLOOKUP(A54,'fat-11-25'!A:D,3,FALSE),"") | DR54: =IFERROR(VLOOKUP(A54,'fat-12-25'!A:D,3,FALSE),"") | DS54: =IFERROR(VLOOKUP(A54,'fat-01-26'!A:C,3,FALSE),"") | DT54: =IFERROR(VLOOKUP(A54,'fat-02-26'!A:C,3,FALSE),"") | DU54: =IFERROR(VLOOKUP(A54,'fat-03-26'!A:C,3,FALSE),"") | DV54: =IFERROR(VLOOKUP(A54,'fat-04-26'!A:C,3,FALSE),"") | DW54: =IFERROR(VLOOKUP(A54,'fat-05-26'!A:C,3,FALSE),"") | DX54: =SUM(DR54:DW54)/6 -> 0 | DY54: =DX54/30*45 -> 0 | EB54: =VLOOKUP(A54,Estoque!B:N,13,FALSE) -> #N/A | EC54: 15 | ED54: 15
A55: prf10244 | B55: PERFIL U ENRIJ LQ 3,35 X 150 X 60 X 20 MM | U55: 3.375 | X55: 0.765 | AA55: 0.532 | AB55: 0.225 | AO55: 6.605 | AQ55: 0.277 | AS55: 0.09 | AT55: 1.3 | CU55: =IFERROR(VLOOKUP(A55,'fat-01-24'!A:C,3,FALSE),"") | CV55: =IFERROR(VLOOKUP(A55,'fat-02-24'!A:C,3,FALSE),"") | CW55: =IFERROR(VLOOKUP(A55,'fat-03-24'!A:C,3,FALSE),"") | CX55: =IFERROR(VLOOKUP(A55,'fat-04-24'!A:C,3,FALSE),"") -> 1.18 | CY55: =IFERROR(VLOOKUP(A55,'fat-05-24'!A:C,3,FALSE),"") | CZ55: =IFERROR(VLOOKUP(A55,'fat-06-24'!A:C,3,FALSE),"") | DA55: =IFERROR(VLOOKUP(A55,'fat-07-24'!A:C,3,FALSE),"") | DB55: =IFERROR(VLOOKUP(A55,'fat-08-24'!A:D,3,FALSE),"") | DC55: =IFERROR(VLOOKUP(A55,'fat-09-24'!A:C,3,FALSE),"") | DD55: =IFERROR(VLOOKUP(A55,'fat-10-24'!A:C,3,FALSE),"") | DE55: =IFERROR(VLOOKUP(A55,'fat-11-24'!A:C,3,FALSE),"") | DF55: =IFERROR(VLOOKUP(A55,'fat-12-24'!A:D,3,FALSE),"") | DG55: =IFERROR(VLOOKUP(A55,'fat-01-25'!A:D,3,FALSE),"") | DH55: =IFERROR(VLOOKUP(A55,'fat-02-25'!A:D,3,FALSE),"") -> 0 | DI55: =IFERROR(VLOOKUP(A55,'fat-03-25'!A:C,3,FALSE),"") -> 20.025 | DJ55: =IFERROR(VLOOKUP(A55,'fat-04-25'!A:C,3,FALSE),"") -> 0 | DK55: =IFERROR(VLOOKUP(A55,'fat-02-25'!A:C,3,FALSE),"") -> 0 | DL55: =IFERROR(VLOOKUP(A55,'fat-06-25'!A:C,3,FALSE),"") -> 3.96 | DM55: =IFERROR(VLOOKUP(A55,'fat-05-25'!A:C,3,FALSE),"") -> 0 | DN55: =IFERROR(VLOOKUP(A55,'fat-08-25'!A:C,3,FALSE),"") -> 2.61 | DO55: =IFERROR(VLOOKUP(A55,'fat-09-25'!A:C,3,FALSE),"") -> 16.785 | DP55: =IFERROR(VLOOKUP(A55,'fat-10-25'!A:C,3,FALSE),"") -> 0 | DQ55: =IFERROR(VLOOKUP(A55,'fat-11-25'!A:D,3,FALSE),"") | DR55: =IFERROR(VLOOKUP(A55,'fat-12-25'!A:D,3,FALSE),"") | DS55: =IFERROR(VLOOKUP(A55,'fat-01-26'!A:C,3,FALSE),"") | DT55: =IFERROR(VLOOKUP(A55,'fat-02-26'!A:C,3,FALSE),"") | DU55: =IFERROR(VLOOKUP(A55,'fat-03-26'!A:C,3,FALSE),"") | DV55: =IFERROR(VLOOKUP(A55,'fat-04-26'!A:C,3,FALSE),"") | DW55: =IFERROR(VLOOKUP(A55,'fat-05-26'!A:C,3,FALSE),"") | DX55: =SUM(DR55:DW55)/6 -> 0 | DY55: =DX55/30*45 -> 0 | EA55: =VLOOKUP(A55,Estoque!B:I,8,FALSE) -> 0 | EB55: =VLOOKUP(A55,Estoque!B:N,13,FALSE) -> 0 | EC55: 10
A56: PRF10245 | B56: PERFIL U ENRIJ LQ 3,35 X 100 X 50 X 17 MM | CU56: =IFERROR(VLOOKUP(A56,'fat-01-24'!A:C,3,FALSE),"") | CV56: =IFERROR(VLOOKUP(A56,'fat-02-24'!A:C,3,FALSE),"") | CW56: =IFERROR(VLOOKUP(A56,'fat-03-24'!A:C,3,FALSE),"") | CX56: =IFERROR(VLOOKUP(A56,'fat-04-24'!A:C,3,FALSE),"") | CY56: =IFERROR(VLOOKUP(A56,'fat-05-24'!A:C,3,FALSE),"") | CZ56: =IFERROR(VLOOKUP(A56,'fat-06-24'!A:C,3,FALSE),"") | DA56: =IFERROR(VLOOKUP(A56,'fat-07-24'!A:C,3,FALSE),"") | DB56: =IFERROR(VLOOKUP(A56,'fat-08-24'!A:D,3,FALSE),"") | DC56: =IFERROR(VLOOKUP(A56,'fat-09-24'!A:C,3,FALSE),"") -> 5.712 | DD56: =IFERROR(VLOOKUP(A56,'fat-10-24'!A:C,3,FALSE),"") | DE56: =IFERROR(VLOOKUP(A56,'fat-11-24'!A:C,3,FALSE),"") | DF56: =IFERROR(VLOOKUP(A56,'fat-12-24'!A:D,3,FALSE),"") -> 0.51 | DG56: =IFERROR(VLOOKUP(A56,'fat-01-25'!A:D,3,FALSE),"") -> 0 | DH56: =IFERROR(VLOOKUP(A56,'fat-02-25'!A:D,3,FALSE),"") | DI56: =IFERROR(VLOOKUP(A56,'fat-03-25'!A:C,3,FALSE),"") | DJ56: =IFERROR(VLOOKUP(A56,'fat-04-25'!A:C,3,FALSE),"") | DK56: =IFERROR(VLOOKUP(A56,'fat-02-25'!A:C,3,FALSE),"") | DL56: =IFERROR(VLOOKUP(A56,'fat-06-25'!A:C,3,FALSE),"") | DM56: =IFERROR(VLOOKUP(A56,'fat-05-25'!A:C,3,FALSE),"") | DN56: =IFERROR(VLOOKUP(A56,'fat-08-25'!A:C,3,FALSE),"") | DO56: =IFERROR(VLOOKUP(A56,'fat-09-25'!A:C,3,FALSE),"") | DP56: =IFERROR(VLOOKUP(A56,'fat-10-25'!A:C,3,FALSE),"") | DQ56: =IFERROR(VLOOKUP(A56,'fat-11-25'!A:D,3,FALSE),"") | DR56: =IFERROR(VLOOKUP(A56,'fat-12-25'!A:D,3,FALSE),"") | DS56: =IFERROR(VLOOKUP(A56,'fat-01-26'!A:C,3,FALSE),"") | DT56: =IFERROR(VLOOKUP(A56,'fat-02-26'!A:C,3,FALSE),"") | DU56: =IFERROR(VLOOKUP(A56,'fat-03-26'!A:C,3,FALSE),"") | DV56: =IFERROR(VLOOKUP(A56,'fat-04-26'!A:C,3,FALSE),"") | DW56: =IFERROR(VLOOKUP(A56,'fat-05-26'!A:C,3,FALSE),"") -> 9.588 | DX56: =SUM(DR56:DW56)/6 -> 1.598 | DY56: =DX56/30*45 -> 2.397 | EA56: =VLOOKUP(A56,Estoque!B:I,8,FALSE) -> 1.957 | EB56: =VLOOKUP(A56,Estoque!B:N,13,FALSE) -> 0 | EC56: 30 | ED56: 20
A57: PRF10246 | B57: PERFIL U ENRIJ LQ 3,35 X 200 X 75 X 20 MM | CO57: 1.48 | CQ57: 1.446 | CU57: =IFERROR(VLOOKUP(A57,'fat-01-24'!A:C,3,FALSE),"") | CV57: =IFERROR(VLOOKUP(A57,'fat-02-24'!A:C,3,FALSE),"") | CW57: =IFERROR(VLOOKUP(A57,'fat-03-24'!A:C,3,FALSE),"") -> 0.5355 | CX57: =IFERROR(VLOOKUP(A57,'fat-04-24'!A:C,3,FALSE),"") | CY57: =IFERROR(VLOOKUP(A57,'fat-05-24'!A:C,3,FALSE),"") | CZ57: =IFERROR(VLOOKUP(A57,'fat-06-24'!A:C,3,FALSE),"") | DA57: =IFERROR(VLOOKUP(A57,'fat-07-24'!A:C,3,FALSE),"") -> 0.5355 | DB57: =IFERROR(VLOOKUP(A57,'fat-08-24'!A:D,3,FALSE),"") -> 33.6175 | DC57: =IFERROR(VLOOKUP(A57,'fat-09-24'!A:C,3,FALSE),"") | DD57: =IFERROR(VLOOKUP(A57,'fat-10-24'!A:C,3,FALSE),"") -> 0.8925 | DE57: =IFERROR(VLOOKUP(A57,'fat-11-24'!A:C,3,FALSE),"") -> 15.876 | DF57: =IFERROR(VLOOKUP(A57,'fat-12-24'!A:D,3,FALSE),"") -> 19.6275 | DG57: =IFERROR(VLOOKUP(A57,'fat-01-25'!A:D,3,FALSE),"") -> 1.4231 | DH57: =IFERROR(VLOOKUP(A57,'fat-02-25'!A:D,3,FALSE),"") -> 0 | DI57: =IFERROR(VLOOKUP(A57,'fat-03-25'!A:C,3,FALSE),"") -> 1.0115 | DJ57: =IFERROR(VLOOKUP(A57,'fat-04-25'!A:C,3,FALSE),"") -> 13.9655 | DK57: =IFERROR(VLOOKUP(A57,'fat-02-25'!A:C,3,FALSE),"") -> 0 | DL57: =IFERROR(VLOOKUP(A57,'fat-06-25'!A:C,3,FALSE),"") -> 18.445 | DM57: =IFERROR(VLOOKUP(A57,'fat-05-25'!A:C,3,FALSE),"") -> 2.8224 | DN57: =IFERROR(VLOOKUP(A57,'fat-08-25'!A:C,3,FALSE),"") -> 2.856 | DO57: =IFERROR(VLOOKUP(A57,'fat-09-25'!A:C,3,FALSE),"") -> 0.357 | DP57: =IFERROR(VLOOKUP(A57,'fat-10-25'!A:C,3,FALSE),"") -> 2.2015 | DQ57: =IFERROR(VLOOKUP(A57,'fat-11-25'!A:D,3,FALSE),"") -> 0.238 | DR57: =IFERROR(VLOOKUP(A57,'fat-12-25'!A:D,3,FALSE),"") -> 0 | DS57: =IFERROR(VLOOKUP(A57,'fat-01-26'!A:C,3,FALSE),"") | DT57: =IFERROR(VLOOKUP(A57,'fat-02-26'!A:C,3,FALSE),"") | DU57: =IFERROR(VLOOKUP(A57,'fat-03-26'!A:C,3,FALSE),"") | DV57: =IFERROR(VLOOKUP(A57,'fat-04-26'!A:C,3,FALSE),"") | DW57: =IFERROR(VLOOKUP(A57,'fat-05-26'!A:C,3,FALSE),"") -> 5.6525 | DX57: =SUM(DR57:DW57)/6 -> 0.94208333 | DY57: =DX57/30*45 -> 1.413125 | EA57: =VLOOKUP(A57,Estoque!B:I,8,FALSE) -> 10.9528 | EB57: =VLOOKUP(A57,Estoque!B:N,13,FALSE) -> 0
A58: PRF10247 | B58: PERFIL U ENRIJ LQ 3,35 X 127 X 50 X 17 MM | CU58: =IFERROR(VLOOKUP(A58,'fat-01-24'!A:C,3,FALSE),"") | CV58: =IFERROR(VLOOKUP(A58,'fat-02-24'!A:C,3,FALSE),"") | CW58: =IFERROR(VLOOKUP(A58,'fat-03-24'!A:C,3,FALSE),"") | CX58: =IFERROR(VLOOKUP(A58,'fat-04-24'!A:C,3,FALSE),"") -> 7.1796 | CY58: =IFERROR(VLOOKUP(A58,'fat-05-24'!A:C,3,FALSE),"") | CZ58: =IFERROR(VLOOKUP(A58,'fat-06-24'!A:C,3,FALSE),"") | DA58: =IFERROR(VLOOKUP(A58,'fat-07-24'!A:C,3,FALSE),"") | DB58: =IFERROR(VLOOKUP(A58,'fat-08-24'!A:D,3,FALSE),"") | DC58: =IFERROR(VLOOKUP(A58,'fat-09-24'!A:C,3,FALSE),"") | DD58: =IFERROR(VLOOKUP(A58,'fat-10-24'!A:C,3,FALSE),"") | DE58: =IFERROR(VLOOKUP(A58,'fat-11-24'!A:C,3,FALSE),"") | DF58: =IFERROR(VLOOKUP(A58,'fat-12-24'!A:D,3,FALSE),"") | DG58: =IFERROR(VLOOKUP(A58,'fat-01-25'!A:D,3,FALSE),"") | DH58: =IFERROR(VLOOKUP(A58,'fat-02-25'!A:D,3,FALSE),"") | DI58: =IFERROR(VLOOKUP(A58,'fat-03-25'!A:C,3,FALSE),"") | DJ58: =IFERROR(VLOOKUP(A58,'fat-04-25'!A:C,3,FALSE),"") | DK58: =IFERROR(VLOOKUP(A58,'fat-02-25'!A:C,3,FALSE),"") | DL58: =IFERROR(VLOOKUP(A58,'fat-06-25'!A:C,3,FALSE),"") -> 0 | DM58: =IFERROR(VLOOKUP(A58,'fat-05-25'!A:C,3,FALSE),"") | DN58: =IFERROR(VLOOKUP(A58,'fat-08-25'!A:C,3,FALSE),"") -> 0 | DO58: =IFERROR(VLOOKUP(A58,'fat-09-25'!A:C,3,FALSE),"") -> 4.255 | DP58: =IFERROR(VLOOKUP(A58,'fat-10-25'!A:C,3,FALSE),"") -> 0 | DQ58: =IFERROR(VLOOKUP(A58,'fat-11-25'!A:D,3,FALSE),"") | DR58: =IFERROR(VLOOKUP(A58,'fat-12-25'!A:D,3,FALSE),"") | DS58: =IFERROR(VLOOKUP(A58,'fat-01-26'!A:C,3,FALSE),"") | DT58: =IFERROR(VLOOKUP(A58,'fat-02-26'!A:C,3,FALSE),"") | DU58: =IFERROR(VLOOKUP(A58,'fat-03-26'!A:C,3,FALSE),"") | DV58: =IFERROR(VLOOKUP(A58,'fat-04-26'!A:C,3,FALSE),"") | DW58: =IFERROR(VLOOKUP(A58,'fat-05-26'!A:C,3,FALSE),"") | DX58: =SUM(DR58:DW58)/6 -> 0 | DY58: =DX58/30*45 -> 0 | EA58: =VLOOKUP(A58,Estoque!B:I,8,FALSE) -> 0.069 | EB58: =VLOOKUP(A58,Estoque!B:N,13,FALSE) -> 0 | EC58: 25
A59: PRF10249 | B59: PERFIL U ENRIJ LQ 4,50 X 100 X 50 X 17 MM | CO59: 1.806 | CU59: =IFERROR(VLOOKUP(A59,'fat-01-24'!A:C,3,FALSE),"") | CV59: =IFERROR(VLOOKUP(A59,'fat-02-24'!A:C,3,FALSE),"") | CW59: =IFERROR(VLOOKUP(A59,'fat-03-24'!A:C,3,FALSE),"") | CX59: =IFERROR(VLOOKUP(A59,'fat-04-24'!A:C,3,FALSE),"") | CY59: =IFERROR(VLOOKUP(A59,'fat-05-24'!A:C,3,FALSE),"") | CZ59: =IFERROR(VLOOKUP(A59,'fat-06-24'!A:C,3,FALSE),"") | DA59: =IFERROR(VLOOKUP(A59,'fat-07-24'!A:C,3,FALSE),"") | DB59: =IFERROR(VLOOKUP(A59,'fat-08-24'!A:D,3,FALSE),"") | DC59: =IFERROR(VLOOKUP(A59,'fat-09-24'!A:C,3,FALSE),"") | DD59: =IFERROR(VLOOKUP(A59,'fat-10-24'!A:C,3,FALSE),"") | DE59: =IFERROR(VLOOKUP(A59,'fat-11-24'!A:C,3,FALSE),"") | DF59: =IFERROR(VLOOKUP(A59,'fat-12-24'!A:D,3,FALSE),"") | DG59: =IFERROR(VLOOKUP(A59,'fat-01-25'!A:D,3,FALSE),"") | DH59: =IFERROR(VLOOKUP(A59,'fat-02-25'!A:D,3,FALSE),"") | DI59: =IFERROR(VLOOKUP(A59,'fat-03-25'!A:C,3,FALSE),"") | DJ59: =IFERROR(VLOOKUP(A59,'fat-04-25'!A:C,3,FALSE),"") | DK59: =IFERROR(VLOOKUP(A59,'fat-02-25'!A:C,3,FALSE),"") | DL59: =IFERROR(VLOOKUP(A59,'fat-06-25'!A:C,3,FALSE),"") | DM59: =IFERROR(VLOOKUP(A59,'fat-05-25'!A:C,3,FALSE),"") | DN59: =IFERROR(VLOOKUP(A59,'fat-08-25'!A:C,3,FALSE),"") | DO59: =IFERROR(VLOOKUP(A59,'fat-09-25'!A:C,3,FALSE),"") | DP59: =IFERROR(VLOOKUP(A59,'fat-10-25'!A:C,3,FALSE),"") | DQ59: =IFERROR(VLOOKUP(A59,'fat-11-25'!A:D,3,FALSE),"") | DR59: =IFERROR(VLOOKUP(A59,'fat-12-25'!A:D,3,FALSE),"") | DS59: =IFERROR(VLOOKUP(A59,'fat-01-26'!A:C,3,FALSE),"") | DT59: =IFERROR(VLOOKUP(A59,'fat-02-26'!A:C,3,FALSE),"") | DU59: =IFERROR(VLOOKUP(A59,'fat-03-26'!A:C,3,FALSE),"") | DV59: =IFERROR(VLOOKUP(A59,'fat-04-26'!A:C,3,FALSE),"") | DW59: =IFERROR(VLOOKUP(A59,'fat-05-26'!A:C,3,FALSE),"") | DX59: =SUM(DR59:DW59)/6 -> 0 | DY59: =DX59/30*45 -> 0 | EA59: =VLOOKUP(A59,Estoque!B:I,8,FALSE) -> 0 | EB59: =VLOOKUP(A59,Estoque!B:N,13,FALSE) -> 0
A60: PRF10250 | B60: PERFIL U ENRIJ LQ 4,75 X 100 X 50 X 17 MM | N60: 1.866 | O60: 2.67 | Q60: 0.146 | X60: 0.19 | Z60: 0.095 | AC60: 0.46 | AI60: 4.723 | AJ60: 0.708 | AL60: 1.375 | AN60: 5.13 | AP60: 1.68 | AQ60: 9.345 | AR60: 1.926 | AS60: 0.265 | AT60: 1.109 | AU60: 0.044 | AV60: 11.962 | AW60: 0.8 | AX60: 0.528 | BG60: 2.21 | BH60: 2.795 | BI60: 1.2182 | BJ60: 4.7624 | BM60: 4.105 | BN60: 0.089 | BP60: 4.66 | BQ60: 1.895 | CB60: 3.1828 | CF60: 3.129 | CH60: 1.6465 | CL60: 2.144 | CN60: 1.869 | CO60: 0.178 | CQ60: 0.495 | CR60: 3.1 | CS60: 0.6675 | CU60: =IFERROR(VLOOKUP(A60,'fat-01-24'!A:C,3,FALSE),"") | CV60: =IFERROR(VLOOKUP(A60,'fat-02-24'!A:C,3,FALSE),"") | CW60: =IFERROR(VLOOKUP(A60,'fat-03-24'!A:C,3,FALSE),"") | CX60: =IFERROR(VLOOKUP(A60,'fat-04-24'!A:C,3,FALSE),"") | CY60: =IFERROR(VLOOKUP(A60,'fat-05-24'!A:C,3,FALSE),"") | CZ60: =IFERROR(VLOOKUP(A60,'fat-06-24'!A:C,3,FALSE),"") | DA60: =IFERROR(VLOOKUP(A60,'fat-07-24'!A:C,3,FALSE),"") | DB60: =IFERROR(VLOOKUP(A60,'fat-08-24'!A:D,3,FALSE),"") | DC60: =IFERROR(VLOOKUP(A60,'fat-09-24'!A:C,3,FALSE),"") | DD60: =IFERROR(VLOOKUP(A60,'fat-10-24'!A:C,3,FALSE),"") | DE60: =IFERROR(VLOOKUP(A60,'fat-11-24'!A:C,3,FALSE),"") | DF60: =IFERROR(VLOOKUP(A60,'fat-12-24'!A:D,3,FALSE),"") | DG60: =IFERROR(VLOOKUP(A60,'fat-01-25'!A:D,3,FALSE),"") | DH60: =IFERROR(VLOOKUP(A60,'fat-02-25'!A:D,3,FALSE),"") | DI60: =IFERROR(VLOOKUP(A60,'fat-03-25'!A:C,3,FALSE),"") | DJ60: =IFERROR(VLOOKUP(A60,'fat-04-25'!A:C,3,FALSE),"") | DK60: =IFERROR(VLOOKUP(A60,'fat-02-25'!A:C,3,FALSE),"") | DL60: =IFERROR(VLOOKUP(A60,'fat-06-25'!A:C,3,FALSE),"") | DM60: =IFERROR(VLOOKUP(A60,'fat-05-25'!A:C,3,FALSE),"") | DN60: =IFERROR(VLOOKUP(A60,'fat-08-25'!A:C,3,FALSE),"") | DO60: =IFERROR(VLOOKUP(A60,'fat-09-25'!A:C,3,FALSE),"") | DP60: =IFERROR(VLOOKUP(A60,'fat-10-25'!A:C,3,FALSE),"") | DQ60: =IFERROR(VLOOKUP(A60,'fat-11-25'!A:D,3,FALSE),"") | DR60: =IFERROR(VLOOKUP(A60,'fat-12-25'!A:D,3,FALSE),"") | DS60: =IFERROR(VLOOKUP(A60,'fat-01-26'!A:C,3,FALSE),"") | DT60: =IFERROR(VLOOKUP(A60,'fat-02-26'!A:C,3,FALSE),"") | DU60: =IFERROR(VLOOKUP(A60,'fat-03-26'!A:C,3,FALSE),"") | DV60: =IFERROR(VLOOKUP(A60,'fat-04-26'!A:C,3,FALSE),"") | DW60: =IFERROR(VLOOKUP(A60,'fat-05-26'!A:C,3,FALSE),"") | DX60: =SUM(DR60:DW60)/6 -> 0 | DY60: =DX60/30*45 -> 0 | EA60: =VLOOKUP(A60,Estoque!B:I,8,FALSE) -> 0 | EB60: =VLOOKUP(A60,Estoque!B:N,13,FALSE) -> 0
